Workbook
Name ABRIL: #REF!
Name AGOSTO: #REF!
Name AnoSelecionado: #REF!
Name Comisiones: #REF!
Name Comisiones_Vs._Primas_Netas_Cobradas: #REF!
Name ComisionesEmpresaSelec: #REF!
Name CostoReaseguroPorcent: #REF!
Name CU: #REF!
Name DICIEMBRE: #REF!
Name Empresa1: #REF!
Name Empresa10: #REF!
Name Empresa11: #REF!
Name Empresa12: #REF!
Name Empresa13: #REF!
Name Empresa14: #REF!
Name Empresa15: #REF!
Name Empresa16: #REF!
Name Empresa17: #REF!
Name Empresa18: #REF!
Name Empresa19: #REF!
Name Empresa2: #REF!
Name Empresa20: #REF!
Name Empresa3: #REF!
Name Empresa4: #REF!
Name Empresa5: #REF!
Name Empresa6: #REF!
Name Empresa7: #REF!
Name Empresa8: #REF!
Name Empresa9: #REF!
Name Empresaselec: #REF!
Name ENERO: #REF!
Name FEBRERO: #REF!
Name Fotos: INDEX(LOGOS!$D$2:$D$52,MATCH([1]Hoja1!$G$5,LOGOS!$A$2:$A$52,0))
Name Gastos_de_Administración: #REF!
Name Gastos_de_Administración_Vs._Primas_Netas_Cobradas: #REF!
Name Gastos_de_AdministraciónEmpresaSelec: #REF!
Name Gastos_de_Adquisición: #REF!
Name Gastos_de_Adquisición_Vs._Primas_Netas_Cobradas: #REF!
Name Gastos_de_AdquisiciónEmpresaSelec: #REF!
Name Indice_de_Cobertura_de_Reservas: #REF!
Name JULIO: #REF!
Name JUNIO: #REF!
Name LOGOS: INDEX(LOGOS!$D$2:$D$52,MATCH(#REF!,LOGOS!$C$2:$C$52,0))
Name LOGOS2: INDEX(LOGOS!$D$2:$D$52,MATCH(#REF!,LOGOS!$C$2:$C$52,0))
Name LugarPNC: #REF!
Name MARZO: #REF!
Name MAYO: #REF!
Name Mes_Elegido: #REF!
Name NOVIEMBRE: #REF!
Name OCTUBRE: #REF!
Name Participacion: #REF!
Name PNC: #REF!
Name PNCEmpresaSelec: #REF!
Name PNCUSD: #REF!
Name PNCUSDANT: #REF!
Name PNDUSDANT: #REF!
Name primaje1: #REF!
Name primaje10: #REF!
Name primaje11: #REF!
Name primaje12: #REF!

Sheet Compilado
A4: Registre los datos compilados
A6: NumerodeInscripciondelaEmpresa | B6: Nombre Empresa | C6: PrimasNetasCobradas | D6: SiniestrosPagados_NetosdeSalvamento | E6: SiniestrosPendientes | F6: ComisionesyGastosdeAdquision | G6: Gastosdeadministracion | H6: SaldodeOperaciones | I6: InversionesAptas | J6: InversionesNoAptas | K6: ReservasTecnicas | L6: ReservasdePrimas | M6: RetenciondePrimasaCargodeReaseguradoresRetrocesionarios | N6: RetenciondelasReservasdePrestacionesySiniestrosPendientes | O6: RTE_REF_RTEA | P6: ResultadoTecnicoBruto | Q6: ResultadodelReaseguroCedido | R6: ResultadoTecnicoNeto | S6: ResultadodeGestionGeneral | T6: ProductodeInversiones | U6: AjustedeValores_Ingresos | V6: IngresosporFideicomiso | W6: IngresosporServicios | X6: BeneficiosDiversos | Y6: GastosdeAdministración_GestiónGeneral | Z6: EgresosFinancieros | AA6: AjustedeReservasdeProvisión | AB6: AjustedeValoresyOtrosActivos | AC6: PérdidasenActivos | AD6: EgresosporFideicomiso | AE6: EgresosporServicios | AF6: OtrosEgresos | AG6: ReservasPrimasBrutas | AH6: ReservasdeSiniestrosPendientesBrutas | AI6: ReservasTécnicasdelEjercicioBrutas | AJ6: ReservasTécnicasdelEjercicioAnteriorBrutas | AK6: ReintegroconExperienciaFavorable | AL6: MontodeSuficienciaoInsuficienciaenlaCoberturadeReserva | AM6: IndicedeCoberturadeReservas | AN6: Comisiones | AO6: GastosdeAdquision | AP6: Total GeneralPDev | AQ6: TotalGenralSI | AR6: CapitalSocial | AS6: Fecha | AT6: MES | AU6: Saldo "+"/"-" | AV6: AÑO | AW6: NombreCorto | AX6: TasaPromedio | AY6: TasaCierre
A7: 32 | B7: Adriática de Seguros, C.A. | C7: 0 | D7: 0 | E7: 1e-08 | F7: 0 | G7: 4084.4249 | H7: 0 | I7: 742825.32 | J7: 3999.8323 | K7: 0.01136762 | L7: 0.01136761 | M7: 0 | N7: 0 | O7: 0.01136761 | P7: -4084.4363 | Q7: 0 | R7: -4084.4363 | S7: 4084.4363 | T7: 0 | U7: 0 | V7: 0 | W7: 0 | X7: 4169.6066 | Y7: 83.350097 | Z7: 1.7284438 | AA7: 0.09174916 | AB7: 0 | AC7: 0 | AD7: 0 | AE7: 0 | AF7: 0 | AG7: 0.01136761 | AH7: 1e-08 | AI7: 0.01136761 | AJ7: 0 | AK7: 0 | AL7: 742825.31 | AM7: 65.345721 | AN7: 0 | AO7: 0 | AP7: -0.01136761 | AQ7: 0 | AS7: 44227 | AT7: ENERO | AU7: Positivo | AV7: 2021 | AW7: ADRIÁTICA C.A. | AX7: 1.51 | AY7: 1.82
A8: 107 | B8: Altamira C.A., Seguros | C8: 168982.13 | D8: 28771.33 | E8: 66412.43 | F8: 32744.89 | G8: 46299.31 | H8: 2647.96 | I8: 674389.29 | J8: 305094.21 | K8: 192773.91 | L8: 126361.48 | M8: 515683.51 | N8: 0 | O8: 52630.75 | P8: 8535.85 | Q8: -57900.06 | R8: -49364.21 | S8: 52012.17 | T8: 429.11 | U8: 0 | V8: 0 | W8: 0 | X8: 57159.57 | Y8: 944.88 | Z8: 4578.86 | AA8: 0 | AB8: 52.77 | AC8: 0 | AD8: 0 | AE8: 0 | AF8: 0 | AG8: 642045 | AH8: 66412.43 | AI8: 708159.84 | AJ8: 655529.09 | AK8: 0 | AL8: 481615.38 | AM8: 3.4983432 | AN8: 18262.88 | AO8: 14482 | AP8: 107736.56 | AQ8: 20156.53 | AS8: 44227 | AT8: ENERO | AU8: Positivo | AV8: 2021 | AW8: ALTAMIRA C.A. | AX8: 1.51 | AY8: 1.82
A9: 66 | B9: American International, C.A. de Seguros | C9: 203938.17 | D9: 309858.9 | E9: 309.66 | F9: 16357.67 | G9: 90856.02 | H9: -19748.53 | I9: 1308860.8 | J9: 11475649 | K9: 574.92 | L9: 265.26 | M9: 93857.63 | N9: 14508.84 | O9: 40214.42 | P9: -253348.84 | Q9: 251025.9 | R9: -2322.94 | S9: -17425.6 | T9: 0.06 | U9: 0 | V9: 0 | W9: 0 | X9: 8093942.8 | Y9: 1824.32 | Z9: 2071.34 | AA9: 758.5 | AB9: 3.45 | AC9: 0 | AD9: 0 | AE9: 0 | AF9: 8106710.9 | AG9: 94122.89 | AH9: 14818.5 | AI9: 108921.73 | AJ9: 68707.31 | AK9: 0 | AL9: 1308285.9 | AM9: 2276.5965 | AN9: 16357.67 | AO9: 0 | AP9: 178232.88 | AQ9: 324368.02 | AS9: 44227 | AT9: ENERO | AU9: Negativo | AV9: 2021 | AW9: A.I.G. C.A. | AX9: 1.51 | AY9: 1.82
A10: 44 | B10: Andes C.A., Seguros | C10: 246928.41 | D10: 39898.67 | E10: 147435.18 | F10: 33427.73 | G10: 60313.04 | H10: 899.41 | I10: 1409163.4 | J10: 573077.77 | K10: 523742.31 | L10: 376166.53 | M10: 1489.52 | N10: 154 | O10: 200102.18 | P10: -86813.21 | Q10: -220.09 | R10: -87033.3 | S10: 87932.72 | T10: 0.09 | U10: 0 | V10: 0 | W10: 0 | X10: 99496.19 | Y10: 1230.88 | Z10: 186.45 | AA10: 9239.49 | AB10: 76.65 | AC10: 0 | AD10: 0 | AE10: 0 | AF10: 830.1 | AG10: 377656.06 | AH10: 147589.18 | AI10: 524486.26 | AJ10: 324473.65 | AK10: 89.57 | AL10: 885421.05 | AM10: 2.6905662 | AN10: 25987.72 | AO10: 7440.01 | AP10: 141612.51 | AQ10: 134684.95 | AS10: 44227 | AT10: ENERO | AU10: Positivo | AV10: 2021 | AW10: ANDES C.A. | AX10: 1.51 | AY10: 1.82
A11: 113 | B11: Aseguradora Nacional Unida Uniseguros, S.A. | C11: 17979.16 | D11: 0 | E11: 697.46 | F11: 1182.41 | G11: 14066.91 | H11: 344167.35 | I11: 4889941.7 | J11: 883307.32 | K11: 61477.34 | L11: 30915.73 | M11: 38330.68 | N11: 0 | O11: 15197.38 | P11: -12467.54 | Q11: 758.76 | R11: -11708.78 | S11: 355876.14 | T11: 11.83 | U11: 0 | V11: 0 | W11: 0 | X11: 357165.1 | Y11: 287.08 | Z11: 832.69 | AA11: 98.88 | AB11: 33.45 | AC11: 0 | AD11: 0 | AE11: 0 | AF11: 48.68 | AG11: 69246.4 | AH11: 697.46 | AI11: 69217.88 | AJ11: 54020.5 | AK11: 0 | AL11: 4828464.4 | AM11: 79.540555 | AN11: 656.86 | AO11: 525.55 | AP11: 2781.76 | AQ11: 0.01 | AS11: 44227 | AT11: ENERO | AU11: Positivo | AV11: 2021 | AW11: UNISEGUROS S.A. | AX11: 1.51 | AY11: 1.82
A12: 98 | B12: Atrio Seguros S.A. | C12: 1033456.5 | D12: 298403.57 | E12: 218345.18 | F12: 223089.82 | G12: 383256.93 | H12: 7135.1 | I12: 1022930.2 | J12: 737928.98 | K12: 919614.59 | L12: 701269.41 | M12: 1501190.8 | N12: 1124115.8 | O12: 1260479.9 | P12: -1131773.7 | Q12: 965682.32 | R12: -166091.42 | S12: 173226.51 | T12: 2344.5 | U12: 1475.46 | V12: 0 | W12: 0 | X12: 290884.82 | Y12: 5155.45 | Z12: 26925.02 | AA12: 15623.71 | AB12: 846.83 | AC12: 0 | AD12: 0 | AE12: 0 | AF12: 72927.28 | AG12: 2202460.2 | AH12: 1342461 | AI12: 3544699.1 | AJ12: 2284219.3 | AK12: 0 | AL12: 103315.57 | AM12: 1.1123466 | AN12: 137897.97 | AO12: 85191.85 | AP12: 421962.65 | AQ12: 947389.62 | AS12: 44227 | AT12: ENERO | AU12: Positivo | AV12: 2021 | AW12: ATRIO S.A. | AX12: 1.51 | AY12: 1.82
A13: 1 | B13: Ávila C.A., de Seguros | C13: 62608.11 | D13: 4262.47 | E13: 3052.09 | F13: 8114.33 | G13: 25175.81 | H13: 97.58 | I13: 43580.27 | J13: 56215.87 | K13: 21163.05 | L13: 18110.96 | M13: 104245.39 | N13: 2.05 | O13: 37781.7 | P13: -12726.2 | Q13: -3866.69 | R13: -16592.89 | S13: 16690.47 | T13: 451.41 | U13: 0 | V13: 0 | W13: 0 | X13: 17866.26 | Y13: 498.95 | Z13: 1065.7 | AA13: 58.92 | AB13: 3.62 | AC13: 0 | AD13: 0 | AE13: 0 | AF13: 0 | AG13: 122356.35 | AH13: 3054.14 | AI13: 125137.84 | AJ13: 87356.14 | AK13: 0 | AL13: 22417.22 | AM13: 2.0592623 | AN13: 4899.08 | AO13: 3215.25 | AP13: 27880.55 | AQ13: 7316.62 | AS13: 44227 | AT13: ENERO | AU13: Positivo | AV13: 2021 | AW13: ÁVILA C.A. | AX13: 1.51 | AY13: 1.82
A14: 109 | B14: Banesco Seguros C.A. | C14: 1688390.6 | D14: 550561.69 | E14: 771786.64 | F14: 273735.59 | G14: 338104.24 | H14: 3337.83 | I14: 34859480 | J14: 2968549.1 | K14: 2381498.1 | L14: 1543510.3 | M14: 268808.18 | N14: 5011615.9 | O14: 3196705.4 | P14: -2670716.3 | Q14: 1802592.1 | R14: -868124.18 | S14: 871462.02 | T14: 11110.98 | U14: 0 | V14: 0 | W14: 11091.31 | X14: 987764.84 | Y14: 5701.63 | Z14: 0 | AA14: 29533.85 | AB14: 359.36 | AC14: 0 | AD14: 0 | AE14: 0 | AF14: 102910.26 | AG14: 1812318.5 | AH14: 5783402.5 | AI14: 7585824.4 | AJ14: 4389119 | AK14: 0 | AL14: 32477982 | AM14: 14.637627 | AN14: 121731.57 | AO14: 152004.02 | AP14: 771029.97 | AQ14: 2829906.4 | AS14: 44227 | AT14: ENERO | AU14: Positivo | AV14: 2021 | AW14: BANESCO C.A. | AX14: 1.51 | AY14: 1.82
A15: 25 | B15: BBVA Seguros,C.A. | C15: 138687.95 | D15: 22313 | E15: 12653.72 | F15: 0 | G15: 78723.47 | H15: 133334.16 | I15: 294309.05 | J15: 20092674 | K15: 185483.26 | L15: 172829.54 | M15: 0 | N15: 0 | O15: 54156.01 | P15: -16504.53 | Q15: -10.59 | R15: -16515.12 | S15: 149849.28 | T15: 57711.45 | U15: 19.2 | V15: 0 | W15: 0 | X15: 95747.61 | Y15: 1606.6 | Z15: 2017.62 | AA15: 0 | AB15: 4.76 | AC15: 0 | AD15: 0 | AE15: 0 | AF15: 0 | AG15: 172829.54 | AH15: 12653.72 | AI15: 183482.61 | AJ15: 129326.6 | AK15: 0 | AL15: 108825.79 | AM15: 1.5867149 | AN15: 0 | AO15: 0 | AP15: 86603.82 | AQ15: 24384.88 | AS15: 44227 | AT15: ENERO | AU15: Positivo | AV15: 2021 | AW15: BBVA C.A. | AX15: 1.51 | AY15: 1.82
A16: 121 | B16: Bolivariana de Seguros y Reaseguros, S.A. | C16: 3.81 | D16: 0 | E16: 69.62 | F16: 0 | G16: 7416.09 | H16: 5320.42 | I16: 78064.59 | J16: 1503816.8 | K16: 504.58 | L16: 434.97 | M16: 1486.4 | N16: 0 | O16: -1346.15 | P16: -6066.13 | Q16: -287.26 | R16: -6353.39 | S16: 11673.81 | T16: 0 | U16: 0 | V16: 0 | W16: 4197.63 | X16: 7823.3 | Y16: 151.35 | Z16: 151.32 | AA16: 0 | AB16: 44.44 | AC16: 0 | AD16: 0 | AE16: 0 | AF16: 0 | AG16: 1921.36 | AH16: 69.62 | AI16: 1985.16 | AJ16: 3331.31 | AK16: 0 | AL16: 77560.01 | AM16: 154.71202 | AN16: 0 | AO16: 0 | AP16: 1070.67 | AQ16: -279.28 | AS16: 44227 | AT16: ENERO | AU16: Positivo | AV16: 2021 | AW16: BOLIVARIANA S.A. | AX16: 1.51 | AY16: 1.82
A17: 122 | B17: Capital, C.A. Seguros | C17: 44896.96 | D17: 0 | E17: 0 | F17: 0 | G17: 2379.34 | H17: 2052.63 | I17: 51870.2 | J17: 0 | K17: 2.23 | L17: 2.23 | M17: 1676.19 | N17: 0 | O17: 423.59 | P17: 42094.03 | Q17: -39983.35 | R17: 2110.68 | S17: -58.06 | T17: 0 | U17: 0 | V17: 0 | W17: 0 | X17: 0 | Y17: 48.56 | Z17: 2.39 | AA17: 0 | AB17: 7.12 | AC17: 0 | AD17: 0 | AE17: 0 | AF17: 0 | AG17: 1678.43 | AH17: 0 | AI17: 1678.19 | AJ17: 1254.6 | AK17: 0 | AL17: 51867.97 | AM17: 23260.179 | AN17: 0 | AO17: 0 | AP17: 44473.37 | AQ17: 0 | AS17: 44227 | AT17: ENERO | AU17: Positivo | AV17: 2021 | AW17: CAPITAL C.A. | AX17: 1.51 | AY17: 1.82
A18: 13 | B18: Caracas C.A., Seguros | C18: 9074282.1 | D18: 4407699 | E18: 6969072.2 | F18: 1550567.1 | G18: 2238860.6 | H18: 6040911.4 | I18: 58910597 | J18: 35432636 | K18: 21801653 | L18: 14832573 | M18: 88943.15 | N18: 11546.97 | O18: 8112638.6 | P18: -7235483.2 | Q18: -664348.87 | R18: -7899832 | S18: 13940743 | T18: 18524.55 | U18: 4162.83 | V18: 0 | W18: 80.79 | X18: 15725542 | Y18: 45691.03 | Z18: 263880.58 | AA18: 28680.33 | AB18: 380.48 | AC18: 0 | AD18: 0 | AE18: 0 | AF18: 1468934.5 | AG18: 14921517 | AH18: 6980619.2 | AI18: 21858594 | AJ18: 13745956 | AK18: 0.08 | AL18: 37108944 | AM18: 2.7021161 | AN18: 1144413.9 | AO18: 406153.2 | AP18: 4694041.5 | AQ18: 8140097 | AS18: 44227 | AT18: ENERO | AU18: Positivo | AV18: 2021 | AW18: CARACAS C.A. | AX18: 1.51 | AY18: 1.82
... A81: 91 | B81: Multinacional de Seguros C.A. | C81: 97517.07 | D81: 5265.48 | E81: 12499.41 | F81: 20248.27 | G81: 107607.59 | H81: -870541 | I81: 65655744 | J81: 12276206 | K81: 33719.1 | L81: 20773.36 | M81: 0 | N81: 429716.63 | O81: 104738.22 | P81: -140342.49 | Q81: 304208.72 | R81: 163866.23 | S81: -1034407.2 | T81: 6.48 | U81: 0 | V81: 0 | W81: 0 | X81: 38761.37 | Y81: 516.86 | Z81: 13634.63 | AA81: 514094.7 | AB81: 506226.95 | AC81: 0 | AD81: 0 | AE81: 0 | AF81: 38701.93 | AG81: 20773.36 | AH81: 442216.04 | AI81: 462958.13 | AJ81: 358219.91 | AK81: 0 | AL81: 65622025 | AM81: 1947.1381 | AN81: 20248.27 | AO81: 0 | AP81: 78693.78 | AQ81: 91180.41 | AS81: 44255 | AT81: FEBRERO | AU81: Negativo | AV81: 2021 | AW81: MULTINACIONAL C.A. | AX81: 1.8 | AY81: 1.87
A82: 73 | B82: Mundial de Seguros,C.A. | C82: 0 | D82: 0 | E82: 0 | F82: 0 | G82: 51190.02 | H82: -141044.18 | I82: 15155.21 | J82: 235329.93 | K82: 0 | L82: 0 | M82: 0 | N82: 0 | O82: -1427.87 | P82: -49762.15 | Q82: -571.15 | R82: -50333.3 | S82: -90710.89 | T82: 0.15 | U82: 0 | V82: 0 | W82: 0 | X82: 133604.58 | Y82: 1044.69 | Z82: 0.26 | AA82: 12.6 | AB82: 1.9 | AC82: 0 | AD82: 0 | AE82: 0 | AF82: 223256.17 | AG82: 0 | AH82: 0 | AI82: 0 | AJ82: 1427.87 | AK82: 0 | AL82: 15155.21 | AN82: 0 | AO82: 0 | AP82: 1427.87 | AQ82: 0 | AS82: 44255 | AT82: FEBRERO | AU82: Negativo | AV82: 2021 | AW82: MUNDIAL C.A. | AX82: 1.8 | AY82: 1.87
A83: 46 | B83: Nuevo Mundo S.A., Seguros | C83: 324434.54 | D83: 54179.16 | E83: 96847.53 | F83: 61503.31 | G83: 68332.11 | H83: 20008.78 | I83: 9197196.6 | J83: 879031.62 | K83: 502892.84 | L83: 406043.93 | M83: 31515.2 | N83: 3.14 | O83: 176974.98 | P83: -36555.02 | Q83: -4495.06 | R83: -41050.08 | S83: 61058.86 | T83: 69683.86 | U83: 0 | V83: 0 | W83: 0 | X83: 0 | Y83: 1394.53 | Z83: 796.25 | AA83: 5351.48 | AB83: 1082.74 | AC83: 0 | AD83: 0 | AE83: 0 | AF83: 0 | AG83: 437559.13 | AH83: 96850.67 | AI83: 533856.83 | AJ83: 356881.85 | AK83: 0 | AL83: 8694303.7 | AM83: 18.288581 | AN83: 34207.74 | AO83: 27295.58 | AP83: 122636.18 | AQ83: 29355.78 | AS83: 44255 | AT83: FEBRERO | AU83: Positivo | AV83: 2021 | AW83: NUEVO MUNDO S.A. | AX83: 1.8 | AY83: 1.87
A84: 51 | B84: Occidental C.A., Seguros | C84: 626179.48 | D84: 95401.68 | E84: 744816.45 | F84: 35131.95 | G84: 726438.62 | H84: 190352.1 | I84: 10376787 | J84: 11443842 | K84: 1340046.1 | L84: 595229.63 | M84: 80125.57 | N84: 8.84 | O84: 711863.31 | P84: -942656.08 | Q84: -3721.6 | R84: -946377.68 | S84: 1136729.8 | T84: 0 | U84: 0 | V84: 0 | W84: 0 | X84: 5090301.7 | Y84: 13939.29 | Z84: 17820.76 | AA84: 954063.73 | AB84: 919.13 | AC84: 0 | AD84: 0 | AE84: 0 | AF84: 2966829 | AG84: 675355.2 | AH84: 744825.29 | AI84: 1420051.5 | AJ84: 708188.16 | AK84: 0 | AL84: 9036740.6 | AM84: 7.7436043 | AN84: 22963.35 | AO84: 12168.59 | AP84: 164631.08 | AQ84: 345716.6 | AS84: 44255 | AT84: FEBRERO | AU84: Positivo | AV84: 2021 | AW84: OCCIDENTAL C.A. | AX84: 1.8 | AY84: 1.87
A85: 117 | B85: Oceánica de Seguros, C.A. | C85: 5104187.7 | D85: 3077849.4 | E85: 247085.42 | F85: 765378.64 | G85: 1402282.9 | H85: 16365.11 | I85: 6741659.5 | J85: 2892983.3 | K85: 687125.16 | L85: 440039.73 | M85: 7312407.5 | N85: 4683122.6 | O85: 4312782.9 | P85: -4454106.2 | Q85: 4514027.1 | R85: 59920.96 | S85: -43555.84 | T85: 72.82 | U85: 0 | V85: 0 | W85: 2758.59 | X85: 920456.17 | Y85: 15344.87 | Z85: 68754.31 | AA85: 20621.81 | AB85: 4647.16 | AC85: 0 | AD85: 0 | AE85: 0 | AF85: 857475.27 | AG85: 7752447.2 | AH85: 4930208 | AI85: 12681631 | AJ85: 8368848.5 | AK85: 0 | AL85: 6054534.3 | AM85: 9.8113996 | AN85: 721155.38 | AO85: 44223.27 | AP85: 3606719.7 | AQ85: 5893164.4 | AS85: 44255 | AT85: FEBRERO | AU85: Positivo | AV85: 2021 | AW85: OCEÁNICA C.A. | AX85: 1.8 | AY85: 1.87
A86: 78 | B86: Oriental de Seguros C.A. | C86: 14434.13 | D86: 0 | E86: 1.93 | F86: 2180.27 | G86: 14994.78 | H86: 29091.17 | I86: 108907.52 | J86: 107788.54 | K86: 11119.46 | L86: 11117.54 | M86: 35010.81 | N86: 0 | O86: 14123.84 | P86: -16864.76 | Q86: 4776.57 | R86: -12088.19 | S86: 41179.37 | T86: 1514.39 | U86: 3.25 | V86: 0 | W86: 0 | X86: 40696.22 | Y86: 294.02 | Z86: 735.82 | AA86: 0 | AB86: 4.55 | AC86: 0 | AD86: 0 | AE86: 0 | AF86: 0.11 | AG86: 46128.34 | AH86: 1.93 | AI86: 46119.24 | AJ86: 31995.4 | AK86: 0 | AL86: 97788.06 | AM86: 9.7943173 | AN86: 1757.48 | AO86: 422.8 | AP86: 311.07 | AQ86: 0.79 | AS86: 44255 | AT86: FEBRERO | AU86: Positivo | AV86: 2021 | AW86: ORIENTAL C.A. | AX86: 1.8 | AY86: 1.87
A87: 80 | B87: Pirámide C.A., Seguros | C87: 15906287 | D87: 6720497.5 | E87: 668038.2 | F87: 1444672.6 | G87: 3055119.6 | H87: 21120.51 | I87: 21985409 | J87: 31521345 | K87: 1014401.1 | L87: 346362.93 | M87: 9707168.3 | N87: 1.2497847e+08 | O87: 58705519 | P87: -54019522 | Q87: 55353887 | R87: 1334364.7 | S87: -1313244.2 | T87: 143.09 | U87: 0 | V87: 0 | W87: 364.41 | X87: 6868021.2 | Y87: 48560.58 | Z87: 203841.13 | AA87: 7689301.5 | AB87: 13744.74 | AC87: 0 | AD87: 0 | AE87: 0 | AF87: 226324.97 | AG87: 10053531 | AH87: 1.2564651e+08 | AI87: 1.3568234e+08 | AJ87: 76976819 | AK87: 0 | AL87: 20971007 | AM87: 21.673289 | AN87: 1335328.4 | AO87: 109344.21 | AP87: 11515618 | AQ87: 61035347 | AS87: 44255 | AT87: FEBRERO | AU87: Positivo | AV87: 2021 | AW87: PIRÁMIDE C.A. | AX87: 1.8 | AY87: 1.87
A88: 2 | B88: Previsora, C.N.A. de Seguros | C88: 370417.46 | D88: 925.32 | E88: 3504.38 | F88: 1393.81 | G88: 104071.47 | H88: 51723.05 | I88: 4966636.1 | J88: 4376953.5 | K88: 49895.95 | L88: 46391.57 | M88: 64.74 | N88: 3.19 | O88: 33534.86 | P88: 230492 | Q88: -195434.55 | R88: 35057.45 | S88: 16665.6 | T88: 13031.35 | U88: 0 | V88: 0 | W88: 4600 | X88: 6900.26 | Y88: 2113.7 | Z88: 0 | AA88: 4155.33 | AB88: 0 | AC88: 0 | AD88: 0 | AE88: 0 | AF88: 1596.98 | AG88: 46456.31 | AH88: 3507.57 | AI88: 49905.99 | AJ88: 16371.13 | AK88: 0 | AL88: 4916740.2 | AM88: 99.539865 | AN88: 1393.81 | AO88: 0 | AP88: 336803.97 | AQ88: 846.7 | AS88: 44255 | AT88: FEBRERO | AU88: Positivo | AV88: 2021 | AW88: PREVISORA C.N.A. | AX88: 1.8 | AY88: 1.87
A89: 115 | B89: Seguros Seguramiga C.A. | C89: 0.06 | D89: 0 | E89: 0 | F89: 0 | G89: 4749.53 | H89: 105753.37 | I89: 149815.77 | J89: 272647.04 | K89: 12.25 | L89: 12.25 | M89: 0 | N89: 0 | O89: -2.5 | P89: -4746.97 | Q89: 0 | R89: -4746.97 | S89: 110500.32 | T89: 4.72 | U89: 0 | V89: 0 | W89: 0 | X89: 110835.52 | Y89: 96.93 | Z89: 74.05 | AA89: 0 | AB89: 0.01 | AC89: 0 | AD89: 0 | AE89: 168.94 | AF89: 0 | AG89: 12.25 | AH89: 0 | AI89: 11.88 | AJ89: 14.38 | AK89: 0 | AL89: 149803.52 | AM89: 12229.859 | AN89: 0 | AO89: 0 | AP89: 2.56 | AQ89: 0 | AS89: 44255 | AT89: FEBRERO | AU89: Positivo | AV89: 2021 | AW89: SEGURAMIGA C.A. | AX89: 1.8 | AY89: 1.87
A90: 106 | B90: Proseguros, S.A. | C90: 102359.85 | D90: 11.47 | E90: 198.73 | F90: 21080.27 | G90: 45249.02 | H90: 79.86 | I90: 305162.97 | J90: 7770.98 | K90: 64615.99 | L90: 64417.25 | M90: 68008.86 | N90: 11.85 | O90: 68404.62 | P90: -32385.53 | Q90: 8845.77 | R90: -23539.76 | S90: 23619.64 | T90: 0.02 | U90: 0 | V90: 0 | W90: 0 | X90: 27496.05 | Y90: 918.22 | Z90: 284.46 | AA90: 840 | AB90: 317.03 | AC90: 0 | AD90: 0 | AE90: 0 | AF90: 1516.73 | AG90: 132426.12 | AH90: 210.58 | AI90: 132581.88 | AJ90: 64177.26 | AK90: 0 | AL90: 240546.98 | AM90: 4.722716 | AN90: 14967.33 | AO90: 6112.94 | AP90: 34154.49 | AQ90: 210.72 | AS90: 44255 | AT90: FEBRERO | AU90: Positivo | AV90: 2021 | AW90: PROSEGUROS S.A. | AX90: 1.8 | AY90: 1.87
A91: 118 | B91: Qualitas C.A., Seguros | C91: 1064307.5 | D91: 143154.23 | E91: 48345.46 | F91: 77692.57 | G91: 161768.39 | H91: 7387.85 | I91: 3831802.2 | J91: 836581.04 | K91: 132124.09 | L91: 83778.63 | M91: 713855.87 | N91: 444840.55 | O91: 520835.03 | P91: 160857.24 | Q91: -130918.57 | R91: 29938.67 | S91: -22550.82 | T91: 32.29 | U91: 0 | V91: 0 | W91: 2985.09 | X91: 11519.03 | Y91: 2956.33 | Z91: 1888.89 | AA91: 28642.47 | AB91: 799.46 | AC91: 0 | AD91: 0 | AE91: 2800.08 | AF91: 0.01 | AG91: 797634.5 | AH91: 493186.01 | AI91: 1290767.8 | AJ91: 769932.79 | AK91: 0 | AL91: 3699678.1 | AM91: 29.001541 | AN91: 50351.51 | AO91: 27341.06 | AP91: 771070.59 | AQ91: 370752.39 | AS91: 44255 | AT91: FEBRERO | AU91: Positivo | AV91: 2021 | AW91: QUALITAS C.A. | AX91: 1.8 | AY91: 1.87
A92: 29 | B92: Real Seguros, S.A. | C92: 1223702.3 | D92: 56628.23 | E92: 94477.01 | F92: 178884.13 | G92: 276499.3 | H92: 467778.04 | I92: 11113413 | J92: 8632313.4 | K92: 548664.36 | L92: 454187.34 | M92: 805946.28 | N92: 549404.04 | O92: 807567.89 | P92: -95877.27 | Q92: -135751.75 | R92: -231629.02 | S92: 699407.1 | T92: 468040.34 | U92: 0 | V92: 0 | W92: 0 | X92: 1296677 | Y92: 5642.84 | Z92: 8012.23 | AA92: 6446.34 | AB92: 675.03 | AC92: 0 | AD92: 0 | AE92: 0 | AF92: 1044533.8 | AG92: 1260133.6 | AH92: 643881.05 | AI92: 1896418.3 | AJ92: 1088850.4 | AK92: 0 | AL92: 10564748 | AM92: 20.255394 | AN92: 152388.99 | AO92: 26495.14 | AP92: 749172.04 | AQ92: 389665.91 | AS92: 44255 | AT92: FEBRERO | AU92: Positivo | AV92: 2021 | AW92: REAL S.A. | AX92: 1.8 | AY92: 1.87
A93: 111 | B93: Universal de Seguros C.A. | C93: 130170.09 | D93: 6564.62 | E93: 100591.56 | F93: 9698.51 | G93: 173186.59 | H93: 19013.71 | I93: 287884.95 | J93: 86041.03 | K93: 203509.16 | L93: 102917.59 | M93: 0 | N93: 0 | O93: -64564.76 | P93: 5285.13 | Q93: -7425.73 | R93: -2140.6 | S93: 21154.32 | T93: 0 | U93: 0 | V93: 0 | W93: 238.84 | X93: 43377.86 | Y93: 3525.26 | Z93: 1594.34 | AA93: 11156.6 | AB93: 112.33 | AC93: 0 | AD93: 0 | AE93: 0 | AF93: 6073.85 | AG93: 102917.59 | AH93: 100591.56 | AI93: 203482.48 | AJ93: 268047.24 | AK93: 0 | AL93: 84375.79 | AM93: 1.4146044 | AN93: 5628.02 | AO93: 4070.49 | AP93: 199453.07 | AQ93: 11282.85 | AS93: 44255 | AT93: FEBRERO | AU93: Positivo | AV93: 2021 | AW93: UNIVERSAL C.A. | AX93: 1.8 | AY93: 1.87
A94: 83 | B94: Universitas, C.A. Seguros | C94: 8119615.9 | D94: 486464.96 | E94: 5212572.8 | F94: 1379529.8 | G94: 3040701.2 | H94: 145767.19 | I94: 16470210 | J94: 1510437.7 | K94: 9849333.3 | L94: 4636760.5 | M94: 6202795.3 | N94: 0 | O94: 5502719.5 | P94: -2289799.5 | Q94: -1698357.9 | R94: -3988157.5 | S94: 4133924.6 | T94: 48438.99 | U94: 0 | V94: 0 | W94: 193436.62 | X94: 5130906.2 | Y94: 36921.12 | Z94: 111713.38 | AA94: 229256.91 | AB94: 11955.81 | AC94: 0 | AD94: 0 | AE94: 0 | AF94: 849009.99 | AG94: 10839556 | AH94: 5212572.8 | AI94: 16044185 | AJ94: 10541465 | AK94: 0 | AL94: 6620876.5 | AM94: 1.6722157 | AN94: 1149498.5 | AO94: 230031.25 | AP94: 4766682.1 | AQ94: 2636250.5 | AS94: 44255 | AT94: FEBRERO | AU94: Positivo | AV94: 2021 | AW94: UNIVERSITAS C.A. | AX94: 1.8 | AY94: 1.87
... A128: 91 | B128: Multinacional de Seguros C.A. | C128: 138628.41 | D128: 5306.44 | E128: 12015.31 | F128: 21026.67 | G128: 160984.37 | H128: -1164560.8 | I128: 65445859 | J128: 12259982 | K128: 31417.46 | L128: 18955.82 | M128: 0 | N128: 429716.63 | O128: 102436.58 | P128: -151125.65 | Q128: 304208.72 | R128: 153083.07 | S128: -1317643.8 | T128: 6.48 | U128: 0 | V128: 0 | W128: 0 | X128: 56594.47 | Y128: 822.03 | Z128: 21581.47 | AA128: 547595.17 | AB128: 759340.43 | AC128: 0 | AD128: 0 | AE128: 0 | AF128: 44905.69 | AG128: 18955.83 | AH128: 441731.94 | AI128: 460656.49 | AJ128: 358219.91 | AK128: 0 | AL128: 65414442 | AM128: 2083.1047 | AN128: 21026.67 | AO128: 0 | AP128: 121622.66 | AQ128: 90737.27 | AS128: 44286 | AT128: MARZO | AU128: Negativo | AV128: 2021 | AW128: MULTINACIONAL C.A. | AX128: 1.86 | AY128: 1.97
A129: 73 | B129: Mundial de Seguros,C.A. | C129: 0 | D129: -57637 | E129: 0 | F129: 0 | G129: 79813.35 | H129: -191248.28 | I129: 43527.11 | J129: 260345.43 | K129: 0 | L129: 0 | M129: 0 | N129: 0 | O129: -1427.87 | P129: -20748.48 | Q129: -54173.59 | R129: -74922.07 | S129: -116326.21 | T129: 0.64 | U129: 0 | V129: 0 | W129: 0 | X129: 143776.59 | Y129: 1628.84 | Z129: 0.26 | AA129: 15.8 | AB129: 2.9 | AC129: 0 | AD129: 0 | AE129: 0 | AF129: 258455.65 | AG129: 0 | AH129: 0 | AI129: 0 | AJ129: 1427.87 | AK129: 0 | AL129: 43527.11 | AN129: 0 | AO129: 0 | AP129: 1427.87 | AQ129: -57637 | AS129: 44286 | AT129: MARZO | AU129: Negativo | AV129: 2021 | AW129: MUNDIAL C.A. | AX129: 1.86 | AY129: 1.97
A130: 46 | B130: Nuevo Mundo S.A., Seguros | C130: 561503.54 | D130: 98288.61 | E130: 155016.52 | F130: 106983.7 | G130: 159146.67 | H130: 15766.02 | I130: 9160791.3 | J130: 1057551.1 | K130: 694383.55 | L130: 539365.65 | M130: 35446.82 | N130: 3.14 | O130: 372397.3 | P130: -175312.74 | Q130: -5919.83 | R130: -181232.57 | S130: 196998.58 | T130: 93289.75 | U130: 0 | V130: 0 | W130: 0 | X130: 115000 | Y130: 3247.89 | Z130: 1069.28 | AA130: 5351.48 | AB130: 1622.51 | AC130: 0 | AD130: 0 | AE130: 0 | AF130: 0 | AG130: 574812.46 | AH130: 155019.66 | AI130: 729279.15 | AJ130: 356881.85 | AK130: 0 | AL130: 8466407.8 | AM130: 13.192696 | AN130: 64031.75 | AO130: 42951.95 | AP130: 222451.84 | AQ130: 131634.21 | AS130: 44286 | AT130: MARZO | AU130: Positivo | AV130: 2021 | AW130: NUEVO MUNDO S.A. | AX130: 1.86 | AY130: 1.97
A131: 51 | B131: Occidental C.A., Seguros | C131: 866876.41 | D131: 112388.2 | E131: 1004975.3 | F131: 66702.79 | G131: 901039.41 | H131: 152661.62 | I131: 10346414 | J131: 11613606 | K131: 1639765.4 | L131: 634790.07 | M131: 154178.33 | N131: 48165.78 | O131: 1133792.3 | P131: -1347046.3 | Q131: -9295.58 | R131: -1356341.9 | S131: 1509003.5 | T131: 0 | U131: 0 | V131: 0 | W131: 0 | X131: 5554214.2 | Y131: 16536.96 | Z131: 21278.6 | AA131: 427551.82 | AB131: 1428.33 | AC131: 0 | AD131: 0 | AE131: 0 | AF131: 3578415 | AG131: 788968.39 | AH131: 1053141.1 | AI131: 1841980.5 | AJ131: 708188.16 | AK131: 0 | AL131: 8706648.4 | AM131: 6.3096916 | AN131: 39740.82 | AO131: 26961.96 | AP131: 291714.81 | AQ131: 671018.91 | AS131: 44286 | AT131: MARZO | AU131: Positivo | AV131: 2021 | AW131: OCCIDENTAL C.A. | AX131: 1.86 | AY131: 1.97
A132: 117 | B132: Oceánica de Seguros, C.A. | C132: 10748941 | D132: 6427225.1 | E132: 333318.39 | F132: 1495536 | G132: 2343393.1 | H132: 21274.65 | I132: 10438969 | J132: 5055916.7 | K132: 924513.44 | L132: 591195.05 | M132: 9796097.7 | N132: 4995029 | O132: 7345767.9 | P132: -6862981.2 | Q132: 7319589.1 | R132: 456607.85 | S132: -435333.21 | T132: 429.03 | U132: 0 | V132: 0 | W132: 10883.14 | X132: 1578387.7 | Y132: 27356.74 | Z132: 108843.58 | AA132: 1008364.8 | AB132: 8607.13 | AC132: 0 | AD132: 0 | AE132: 0 | AF132: 871860.86 | AG132: 10387293 | AH132: 5328347.4 | AI132: 15714616 | AJ132: 8368848.5 | AK132: 0 | AL132: 9514455.2 | AM132: 11.291311 | AN132: 1440752.3 | AO132: 54783.74 | AP132: 6616627.3 | AQ132: 9640679.4 | AS132: 44286 | AT132: MARZO | AU132: Positivo | AV132: 2021 | AW132: OCEÁNICA C.A. | AX132: 1.86 | AY132: 1.97
A133: 78 | B133: Oriental de Seguros C.A. | C133: 27589.64 | D133: 0 | E133: 2.05 | F133: 4049.77 | G133: 30892.06 | H133: 24231.26 | I133: 110283.23 | J133: 115535.39 | K133: 14176.27 | L133: 14174.22 | M133: 34728.53 | N133: 0 | O133: 16898.37 | P133: -24250.56 | Q133: 1539.71 | R133: -22710.85 | S133: 46942.1 | T133: 1531.1 | U133: 9.43 | V133: 0 | W133: 0 | X133: 46987.39 | Y133: 600.77 | Z133: 978.11 | AA133: 0 | AB133: 6.83 | AC133: 0 | AD133: 0 | AE133: 0 | AF133: 0.11 | AG133: 48902.76 | AH133: 2.05 | AI133: 48893.77 | AJ133: 31995.4 | AK133: 0 | AL133: 96106.96 | AM133: 7.7794251 | AN133: 3342.42 | AO133: 707.35 | AP133: 10692.16 | AQ133: 0.91 | AS133: 44286 | AT133: MARZO | AU133: Positivo | AV133: 2021 | AW133: ORIENTAL C.A. | AX133: 1.86 | AY133: 1.97
A134: 80 | B134: Pirámide C.A., Seguros | C134: 24783582 | D134: 12526081 | E134: 800379.82 | F134: 2469511 | G134: 4854810.9 | H134: 27456.67 | I134: 24331972 | J134: 27351857 | K134: 1163960.3 | L134: 363580.48 | M134: 12097967 | N134: 1.349624e+08 | O134: 71229802 | P134: -66296623 | Q134: 67520139 | R134: 1223515.9 | S134: -1196059.2 | T134: 2062.85 | U134: 0 | V134: 0 | W134: 127088.94 | X134: 7612673.9 | Y134: 68379.25 | Z134: 425278.65 | AA134: 8145873.1 | AB134: 22532.74 | AC134: 0 | AD134: 0 | AE134: 0 | AF134: 275821.18 | AG134: 12461548 | AH134: 1.3576278e+08 | AI134: 1.4820662e+08 | AJ134: 76976819 | AK134: 0 | AL134: 23168012 | AM134: 20.904469 | AN134: 2233558.5 | AO134: 235952.47 | AP134: 17984896 | AQ134: 76957197 | AS134: 44286 | AT134: MARZO | AU134: Positivo | AV134: 2021 | AW134: PIRÁMIDE C.A. | AX134: 1.86 | AY134: 1.97
A135: 2 | B135: Previsora, C.N.A. de Seguros | C135: 474233.33 | D135: 4744.66 | E135: 3504.38 | F135: 1393.81 | G135: 217411.82 | H135: 2811.94 | I135: 4953871.7 | J135: 4376953.5 | K135: 49895.95 | L135: 46391.57 | M135: 64.74 | N135: 3.19 | O135: 33534.86 | P135: 217148.18 | Q135: -248472.36 | R135: -31324.18 | S135: 34136.13 | T135: 13031.35 | U135: 0 | V135: 0 | W135: 9138.67 | X135: 23869.62 | Y135: 4426.77 | Z135: 0 | AA135: 5879.76 | AB135: 0 | AC135: 0 | AD135: 0 | AE135: 0 | AF135: 1596.98 | AG135: 46456.31 | AH135: 3507.57 | AI135: 49905.99 | AJ135: 16371.13 | AK135: 0 | AL135: 4903975.8 | AM135: 99.284044 | AN135: 1393.81 | AO135: 0 | AP135: 440619.84 | AQ135: 4666.04 | AS135: 44286 | AT135: MARZO | AU135: Positivo | AV135: 2021 | AW135: PREVISORA C.N.A. | AX135: 1.86 | AY135: 1.97
A136: 115 | B136: Seguros Seguramiga C.A. | C136: 39.56 | D136: 0 | E136: 0 | F136: 0 | G136: 11449.54 | H136: 113672.77 | I136: 146047.5 | J136: 287621.67 | K136: 46.86 | L136: 46.87 | M136: 0 | N136: 0 | O136: 32.12 | P136: -11442.1 | Q136: 0 | R136: -11442.1 | S136: 125114.85 | T136: 6.96 | U136: 0 | V136: 0 | W136: 0 | X136: 125807.96 | Y136: 233.66 | Z136: 188.91 | AA136: 0 | AB136: 0.01 | AC136: 0 | AD136: 0 | AE136: 277.47 | AF136: 0 | AG136: 46.87 | AH136: 0 | AI136: 46.5 | AJ136: 14.38 | AK136: 0 | AL136: 146000.64 | AM136: 3116.6773 | AN136: 0 | AO136: 0 | AP136: 7.44 | AQ136: 0 | AS136: 44286 | AT136: MARZO | AU136: Positivo | AV136: 2021 | AW136: SEGURAMIGA C.A. | AX136: 1.86 | AY136: 1.97
A137: 106 | B137: Proseguros, S.A. | C137: 198959.66 | D137: 11.47 | E137: 452.61 | F137: 57566.59 | G137: 76170.01 | H137: 89.39 | I137: 314954.36 | J137: 7289.77 | K137: 99671.31 | L137: 99300.61 | M137: 96294.57 | N137: 20.86 | O137: 131754.66 | P137: -66543.07 | Q137: 35210.97 | R137: -31332.1 | S137: 31421.5 | T137: 0.03 | U137: 0 | V137: 0 | W137: 0 | X137: 38349.41 | Y137: 1546.13 | Z137: 521.21 | AA137: 1383 | AB137: 921.17 | AC137: 0 | AD137: 0 | AE137: 0 | AF137: 2556.41 | AG137: 195513.27 | AH137: 473.47 | AI137: 195931.92 | AJ137: 64177.26 | AK137: 0 | AL137: 215283.05 | AM137: 3.15993 | AN137: 29421.14 | AO137: 28145.46 | AP137: 67667.14 | AQ137: 473.61 | AS137: 44286 | AT137: MARZO | AU137: Positivo | AV137: 2021 | AW137: PROSEGUROS S.A. | AX137: 1.86 | AY137: 1.97
A138: 118 | B138: Qualitas C.A., Seguros | C138: 2191452 | D138: 358884.36 | E138: 98312.28 | F138: 132578.34 | G138: 373946.83 | H138: 7437.79 | I138: 3826913.6 | J138: 1204807.7 | K138: 318754.41 | L138: 220442.13 | M138: 1097929.9 | N138: 622319.42 | O138: 1269018.3 | P138: 57024.14 | Q138: -58395.94 | R138: -1371.8 | S138: 8809.58 | T138: 49.35 | U138: 0 | V138: 0 | W138: 2985.09 | X138: 58062.51 | Y138: 5979.27 | Z138: 8743.03 | AA138: 31555.22 | AB138: 1232.65 | AC138: 0 | AD138: 0 | AE138: 4775.69 | AF138: 1.5 | AG138: 1318372 | AH138: 720631.7 | AI138: 2038951.1 | AJ138: 769932.79 | AK138: 0 | AL138: 3508159.2 | AM138: 12.005837 | AN138: 85394.31 | AO138: 47184.04 | AP138: 1377477.5 | AQ138: 813928.21 | AS138: 44286 | AT138: MARZO | AU138: Positivo | AV138: 2021 | AW138: QUALITAS C.A. | AX138: 1.86 | AY138: 1.97
A139: 29 | B139: Real Seguros, S.A. | C139: 3722685.8 | D139: 364663.57 | E139: 55634.7 | F139: 411802.09 | G139: 600262.6 | H139: 422156.9 | I139: 11178966 | J139: 6716069 | K139: 664618.82 | L139: 608984.12 | M139: 2126292.4 | N139: 260121.34 | O139: 1954585.8 | P139: 391371.72 | Q139: -823204.48 | R139: -431832.76 | S139: 853989.67 | T139: 546760.6 | U139: 0 | V139: 0 | W139: 0 | X139: 1475098.5 | Y139: 12181.42 | Z139: 13619.25 | AA139: 306.73 | AB139: 1022.66 | AC139: 0 | AD139: 0 | AE139: 0 | AF139: 1140739.4 | AG139: 2735276.5 | AH139: 315756.04 | AI139: 3043436.2 | AJ139: 1088850.4 | AK139: 0 | AL139: 10514347 | AM139: 16.820116 | AN139: 280631.31 | AO139: 131170.77 | AP139: 1773012.6 | AQ139: 369576.24 | AS139: 44286 | AT139: MARZO | AU139: Positivo | AV139: 2021 | AW139: REAL S.A. | AX139: 1.86 | AY139: 1.97
A140: 111 | B140: Universal de Seguros C.A. | C140: 165867.36 | D140: 20335.48 | E140: 148380.23 | F140: 15091.2 | G140: 151874.99 | H140: 3094.53 | I140: 511652.72 | J140: 90032.26 | K140: 267918.03 | L140: 119537.79 | M140: 0 | N140: 0 | O140: -155.88 | P140: -21278.43 | Q140: -7425.73 | R140: -28704.16 | S140: 31798.69 | T140: 0 | U140: 0 | V140: 0 | W140: 689.9 | X140: 49058.15 | Y140: 3088.07 | Z140: 2406.86 | AA140: 6197.68 | AB140: 173.21 | AC140: 0 | AD140: 0 | AE140: 0 | AF140: 6083.56 | AG140: 119537.78 | AH140: 148380.23 | AI140: 267891.36 | AJ140: 268047.24 | AK140: 0 | AL140: 243734.69 | AM140: 1.909736 | AN140: 8434.1 | AO140: 6657.09 | AP140: 218530.14 | AQ140: 72842.39 | AS140: 44286 | AT140: MARZO | AU140: Positivo | AV140: 2021 | AW140: UNIVERSAL C.A. | AX140: 1.86 | AY140: 1.97
A141: 83 | B141: Universitas, C.A. Seguros | C141: 13095027 | D141: 914099.8 | E141: 3076631.3 | F141: 2385817.1 | G141: 6081525.4 | H141: 209354.52 | I141: 16341771 | J141: 1307471.1 | K141: 8714281.5 | L141: 5637650.2 | M141: 7011235.2 | N141: 5623.04 | O141: 5181730.6 | P141: -1468146 | Q141: -2595073.4 | R141: -4063219.4 | S141: 4272573.9 | T141: 11032.46 | U141: 0 | V141: 0 | W141: 576016.52 | X141: 5928228.6 | Y141: 83957.44 | Z141: 179997.22 | AA141: 821834.11 | AB141: 25654.13 | AC141: 0 | AD141: 0 | AE141: 0 | AF141: 1131260.8 | AG141: 12648885 | AH141: 3082254.4 | AI141: 15723196 | AJ141: 10541465 | AK141: 0 | AL141: 7627489.7 | AM141: 1.8752861 | AN141: 1761275.9 | AO141: 624541.2 | AP141: 7932763.4 | AQ141: 933566.95 | AS141: 44286 | AT141: MARZO | AU141: Positivo | AV141: 2021 | AW141: UNIVERSITAS C.A. | AX141: 1.86 | AY141: 1.97
... A143: 24 | B143: Venezuela C.A., Seguros | C143: 623686.58 | D143: 178512.72 | E143: 162972.19 | F143: 78506.06 | G143: 328211.12 | H143: 362949.68 | I143: 2014191.9 | J143: 2235472.8 | K143: 554803.85 | L143: 369648.09 | M143: 138436.01 | N143: 11.59 | O143: 440329.49 | P143: -401872.81 | Q143: -11471.07 | R143: -413343.88 | S143: 776293.57 | T143: 30459.96 | U143: 0 | V143: 0 | W143: 119339.88 | X143: 996960.28 | Y143: 5393.33 | Z143: 26360.33 | AA143: 50725.46 | AB143: 2633.47 | AC143: 0 | AD143: 0 | AE143: 0 | AF143: 285353.96 | AG143: 508084.11 | AH143: 162983.78 | AI143: 668982.62 | AJ143: 241520.75 | AK143: 12867.62 | AL143: 1459388 | AM143: 3.6304577 | AN143: 67708.44 | AO143: 10797.61 | AP143: 319579.25 | AQ143: 314734.87 | AS143: 44286 | AT143: MARZO | AU143: Positivo | AV143: 2021 | AW143: VENEZUELA C.A. | AX143: 1.86 | AY143: 1.97
A144: 124 | B144: Vértice, C.A Seguros | C144: 0 | D144: 0 | E144: 0 | F144: 0 | G144: 0 | H144: 0 | I144: 33.56 | J144: 0 | K144: 0 | L144: 0 | M144: 0 | N144: 0 | O144: 0 | P144: 0 | Q144: 0 | R144: 0 | S144: 0 | T144: 0 | U144: 0 | V144: 0 | W144: 0 | X144: 0 | Y144: 0 | Z144: 0 | AA144: 0 | AB144: 0 | AC144: 0 | AD144: 0 | AE144: 0 | AF144: 0 | AG144: 0 | AH144: 0 | AI144: 0 | AJ144: 0 | AK144: 0 | AL144: 33.56 | AN144: 0 | AO144: 0 | AP144: 0 | AQ144: 0 | AS144: 44286 | AT144: MARZO | AU144: Positivo | AV144: 2021 | AW144: VÉRTICE, C.A. | AX144: 1.86 | AY144: 1.97
A145: 70 | B145: Virgen del Valle C.A., Seguros | C145: 22115.85 | D145: 2661.66 | E145: 1190.68 | F145: 0 | G145: 8065.95 | H145: 11220.68 | I145: 27174.89 | J145: 6933.93 | K145: 1302.14 | L145: 111.46 | M145: 0 | N145: 0 | O145: -36.26 | P145: 11424.5 | Q145: 0 | R145: 11424.5 | S145: -203.81 | T145: 0.01 | U145: 0 | V145: 0 | W145: 0 | X145: 0 | Y145: 59.02 | Z145: 144.81 | AA145: 0 | AB145: 0 | AC145: 0 | AD145: 0 | AE145: 0 | AF145: 0 | AG145: 111.46 | AH145: 1190.68 | AI145: 1302.14 | AJ145: 1338.4 | AK145: 0 | AL145: 25872.75 | AM145: 20.869407 | AN145: 0 | AO145: 0 | AP145: 23285.77 | AQ145: 3795.32 | AS145: 44286 | AT145: MARZO | AU145: Positivo | AV145: 2021 | AW145: VIRGEN DEL VALLE C.A. | AX145: 1.86 | AY145: 1.97
A146: 119 | B146: Vitalicia, S.A., Seguros | C146: 0 | D146: 0 | E146: 0 | F146: 0 | G146: 2100.41 | H146: 2.25 | I146: 29232.13 | J146: 3632.31 | K146: 1.69 | L146: 1.7 | M146: 0 | N146: 0 | O146: -2.83 | P146: -2097.58 | Q146: 0 | R146: -2097.58 | S146: 2099.83 | T146: 2192.94 | U146: 0 | V146: 0 | W146: 0 | X146: 0 | Y146: 42.87 | Z146: 39.51 | AA146: 10.47 | AB146: 0.27 | AC146: 0 | AD146: 0 | AE146: 0 | AF146: 0 | AG146: 1.69 | AH146: 0 | AI146: 1.69 | AJ146: 4.52 | AK146: 0 | AL146: 29230.44 | AM146: 17297.118 | AN146: 0 | AO146: 0 | AP146: 2.83 | AQ146: 0 | AS146: 44286 | AT146: MARZO | AU146: Positivo | AV146: 2021 | AW146: VITALICIA S.A. | AX146: 1.86 | AY146: 1.97
A147: 108 | B147: Vivir Seguros C.A. | C147: 215684.74 | D147: 86567.7 | E147: 46338.36 | F147: 16983.81 | G147: 34666.96 | H147: -604.59 | I147: 2736362.8 | J147: 83784.16 | K147: 95491.57 | L147: 49152.52 | M147: 63993.91 | N147: 7565.81 | O147: 65576.61 | P147: 11889.66 | Q147: -49157.32 | R147: -37267.66 | S147: 36663.06 | T147: 1897.93 | U147: 0 | V147: 0 | W147: 0 | X147: 82091.03 | Y147: 622.82 | Z147: 1012.86 | AA147: 13612.83 | AB147: 11.38 | AC147: 0 | AD147: 0 | AE147: 0 | AF147: 32065.99 | AG147: 113146.42 | AH147: 53904.17 | AI147: 166512.65 | AJ147: 100936.04 | AK147: 0 | AL147: 2640871.2 | AM147: 28.655543 | AN147: 16484.06 | AO147: 499.75 | AP147: 183297.19 | AQ147: 119756.77 | AS147: 44286 | AT147: MARZO | AU147: Negativo | AV147: 2021 | AW147: VIVIR C.A. | AX147: 1.86 | AY147: 1.97
A148: 93 | B148: Zuma Seguros, C.A. | C148: 136764.37 | D148: 19 | E148: 1.03 | F148: 35708.09 | G148: 95476.5 | H148: 18295.54 | I148: 2774626.5 | J148: 1308745.8 | K148: 103623.36 | L148: 103622.33 | M148: 7398.19 | N148: 0 | O148: 81988.28 | P148: -76427.5 | Q148: 145.16 | R148: -76282.34 | S148: 94577.89 | T148: 1182.24 | U148: 0 | V148: 0 | W148: 0 | X148: 112498.8 | Y148: 1894.34 | Z148: 4312.27 | AA148: 12268.41 | AB148: 3.29 | AC148: 0 | AD148: 0 | AE148: 0 | AF148: 624.83 | AG148: 111020.54 | AH148: 1.03 | AI148: 110994.9 | AJ148: 29006.62 | AK148: 0 | AL148: 2671003.1 | AM148: 26.776071 | AN148: 20858.82 | AO148: 14849.28 | AP148: 54712.33 | AQ148: -44.76 | AS148: 44286 | AT148: MARZO | AU148: Positivo | AV148: 2021 | AW148: ZUMA C.A. | AX148: 1.86 | AY148: 1.97
A149: 32 | B149: Adriática de Seguros, C.A. | C149: 1e-08 | D149: 0 | E149: 1e-08 | F149: 0 | G149: 19413.629 | H149: 1750.1337 | I149: 735372.14 | J149: 3999.8323 | K149: 2e-08 | L149: 1e-08 | M149: 0 | N149: 0 | O149: 1e-08 | P149: -19413.629 | Q149: 0 | R149: -19413.629 | S149: 21163.763 | T149: 0 | U149: 0 | V149: 0 | W149: 0 | X149: 21568.986 | Y149: 396.19651 | Z149: 8.9344896 | AA149: 0.09174916 | AB149: 0 | AC149: 0 | AD149: 0 | AE149: 0 | AF149: 0 | AG149: 1e-08 | AH149: 1e-08 | AI149: 1e-08 | AJ149: 0 | AK149: 0 | AL149: 735372.14 | AM149: 36768607 | AN149: 0 | AO149: 0 | AP149: 0 | AQ149: 0 | AS149: 44316 | AT149: ABRIL | AU149: Positivo | AV149: 2021 | AW149: ADRIÁTICA C.A. | AX149: 2.39 | AY149: 2.75
A150: 107 | B150: Altamira C.A., Seguros | C150: 2690950.5 | D150: 211335.14 | E150: 185689.25 | F150: 242142.59 | G150: 223490.69 | H150: 5912.02 | I150: 1061231.1 | J150: 359250.03 | K150: 548477.36 | L150: 362788.11 | M150: 1187270.7 | N150: 189129.66 | O150: 1269051.1 | P150: 744930.99 | Q150: -822872.61 | R150: -77941.62 | S150: 83853.63 | T150: 2122.73 | U150: 0 | V150: 0 | W150: 0 | X150: 135538.62 | Y150: 4561.03 | Z150: 30358.19 | AA150: 18453.69 | AB150: 433.8 | AC150: 0 | AD150: 0 | AE150: 0 | AF150: 1 | AG150: 1550058.8 | AH150: 374818.91 | AI150: 1924580.2 | AJ150: 655529.09 | AK150: 0 | AL150: 512753.77 | AM150: 1.9348677 | AN150: 173250.98 | AO150: 68891.61 | AP150: 1721691.1 | AQ150: 511126.81 | AS150: 44316 | AT150: ABRIL | AU150: Positivo | AV150: 2021 | AW150: ALTAMIRA C.A. | AX150: 2.39 | AY150: 2.75
A151: 66 | B151: American International, C.A. de Seguros | C151: 1094967.2 | D151: 322523.92 | E151: 13.14 | F151: 37677.78 | G151: 409935.41 | H151: -419269.25 | I151: 1291023.1 | J151: 16679159 | K151: 29863.55 | L151: 29850.41 | M151: 448842.25 | N151: 5332.89 | O151: 415312.3 | P151: -90482.25 | Q151: -168691.6 | R151: -259173.85 | S151: -160095.4 | T151: 2586.42 | U151: 0 | V151: 0 | W151: 0 | X151: 18105267 | Y151: 8096.85 | Z151: 9084.09 | AA151: 1043.98 | AB151: 136.42 | AC151: 0 | AD151: 0 | AE151: 0 | AF151: 18249587 | AG151: 478692.66 | AH151: 5346.03 | AI151: 484019.61 | AJ151: 68707.31 | AK151: 0 | AL151: 1261159.5 | AM151: 43.23073 | AN151: 37677.78 | AO151: 0 | AP151: 684691.52 | AQ151: 327560.57 | AS151: 44316 | AT151: ABRIL | AU151: Negativo | AV151: 2021 | AW151: A.I.G. C.A. | AX151: 2.39 | AY151: 2.75
A152: 44 | B152: Andes C.A., Seguros | C152: 1456239.6 | D152: 397575.75 | E152: 342302.95 | F152: 196765.51 | G152: 367261.12 | H152: 3320.45 | I152: 1493872.4 | J152: 811027.22 | K152: 1138023.9 | L152: 795580.34 | M152: 907.26 | N152: 148.95 | O152: 813796.45 | P152: -319159.18 | Q152: -481.22 | R152: -319640.4 | S152: 322960.82 | T152: 25.07 | U152: 0 | V152: 0 | W152: 0 | X152: 382417.08 | Y152: 6369.3 | Z152: 1357.76 | AA152: 50480.12 | AB152: 306.58 | AC152: 0 | AD152: 0 | AE152: 0 | AF152: 967.56 | AG152: 796487.6 | AH152: 342451.9 | AI152: 1138180.5 | AJ152: 324473.65 | AK152: 89.57 | AL152: 355848.51 | AM152: 1.3126898 | AN152: 149819.09 | AO152: 46946.42 | AP152: 932092.2 | AQ152: 687224.74 | AS152: 44316 | AT152: ABRIL | AU152: Positivo | AV152: 2021 | AW152: ANDES C.A. | AX152: 2.39 | AY152: 2.75
A153: 113 | B153: Aseguradora Nacional Unida Uniseguros, S.A. | C153: 68184.86 | D153: 3310.25 | E153: 18.05 | F153: 4978.76 | G153: 123661.25 | H153: 700289.44 | I153: 7340324.1 | J153: 1261938.1 | K153: 117448.09 | L153: 37911.72 | M153: 39131.76 | N153: 34.75 | O153: 22349.81 | P153: -86115.21 | Q153: -7315.22 | R153: -93430.43 | S153: 793719.86 | T153: 584.83 | U153: 0 | V153: 0 | W153: 0 | X153: 800292.3 | Y153: 2523.7 | Z153: 3979.25 | AA153: 202.67 | AB153: 410.01 | AC153: 0 | AD153: 0 | AE153: 0 | AF153: 41.65 | AG153: 77043.47 | AH153: 52.8 | AI153: 76370.31 | AJ153: 54020.5 | AK153: 0 | AL153: 7222876 | AM153: 62.498455 | AN153: 2669.35 | AO153: 2309.4 | AP153: 45190.4 | AQ153: 2665.6 | AS153: 44316 | AT153: ABRIL | AU153: Positivo | AV153: 2021 | AW153: UNISEGUROS S.A. | AX153: 2.39 | AY153: 2.75
A154: 98 | B154: Atrio Seguros S.A. | C154: 5164161.5 | D154: 2200714.5 | E154: 634630.25 | F154: 1299981.9 | G154: 1655678.2 | H154: 21191.08 | I154: 3009657.8 | J154: 623315.94 | K154: 1919668.7 | L154: 1285038.4 | M154: 2768526.7 | N154: 3521939.1 | O154: 5925693.1 | P154: -5917906.2 | Q154: 4839561.5 | R154: -1078344.7 | S154: 1099535.8 | T154: 4699.18 | U154: 2989.55 | V154: 0 | W154: 0 | X154: 1552990.7 | Y154: 27207.91 | Z154: 89711.12 | AA154: 104975.25 | AB154: 4838.75 | AC154: 0 | AD154: 0 | AE154: 0 | AF154: 234410.55 | AG154: 4053565.2 | AH154: 4156569.3 | AI154: 8209912.4 | AJ154: 2284219.3 | AK154: 0 | AL154: 1089989.1 | AM154: 1.5678006 | AN154: 650814.97 | AO154: 649166.94 | AP154: 2701562.7 | AQ154: 5663808.8 | AS154: 44316 | AT154: ABRIL | AU154: Positivo | AV154: 2021 | AW154: ATRIO S.A. | AX154: 2.39 | AY154: 2.75
A155: 1 | B155: Ávila C.A., de Seguros | C155: 489794.58 | D155: 40030.05 | E155: 1144.86 | F155: 137930.98 | G155: 117733.48 | H155: 20.39 | I155: 51783.98 | J155: 157825.95 | K155: 146142.27 | L155: 144997.42 | M155: 222055.5 | N155: 2.05 | O155: 280571.04 | P155: -86470.97 | Q155: -5734.86 | R155: -92205.83 | S155: 92226.24 | T155: 7026.51 | U155: 0 | V155: 0 | W155: 0 | X155: 97740.47 | Y155: 2352.85 | Z155: 9907.82 | AA155: 244.17 | AB155: 14.65 | AC155: 0 | AD155: 0 | AE155: 0 | AF155: 21.26 | AG155: 367052.93 | AH155: 1146.91 | AI155: 367927.18 | AJ155: 87356.14 | AK155: 0 | AL155: -94358.29 | AM155: 0.35433951 | AN155: 66867.34 | AO155: 71063.65 | AP155: 210370.44 | AQ155: 41176.96 | AS155: 44316 | AT155: ABRIL | AU155: Positivo | AV155: 2021 | AW155: ÁVILA C.A. | AX155: 2.39 | AY155: 2.75
A156: 109 | B156: Banesco Seguros C.A. | C156: 7166939.6 | D156: 3486261.2 | E156: 3210601.4 | F156: 722044.94 | G156: 1053806.1 | H156: -2035310.3 | I156: 34478710 | J156: 4510595.1 | K156: 7286736.7 | L156: 2554348.6 | M156: 1074501.8 | N156: 7767071.8 | O156: 10207508 | P156: -8302680.6 | Q156: 3863560.3 | R156: -4439120.3 | S156: 2403810 | T156: 49274.59 | U156: 0 | V156: 0 | W156: 43722.06 | X156: 3165798.5 | Y156: 19201.44 | Z156: 65.42 | AA156: 161053.53 | AB156: 1631.21 | AC156: 0 | AD156: 0 | AE156: 0 | AF156: 673033.53 | AG156: 3628850.5 | AH156: 10977673 | AI156: 14596627 | AJ156: 4389119 | AK156: 0 | AL156: 27191974 | AM156: 4.731708 | AN156: 408635.62 | AO156: 313409.32 | AP156: 4433047 | AQ156: 10959877 | AS156: 44316 | AT156: ABRIL | AU156: Negativo | AV156: 2021 | AW156: BANESCO C.A. | AX156: 2.39 | AY156: 2.75
... A176: 91 | B176: Multinacional de Seguros C.A. | C176: 178594.58 | D176: 5306.44 | E176: 10161.31 | F176: 21066.45 | G176: 234930.37 | H176: -1678813.3 | I176: 65225866 | J176: 12239297 | K176: 26092.16 | L176: 15484.51 | M176: 0 | N176: 429716.63 | O176: 97111.28 | P176: -179819.96 | Q176: 304208.72 | R176: 124388.76 | S176: -1803202.1 | T176: 6.48 | U176: 0 | V176: 0 | W176: 0 | X176: 105804.13 | Y176: 1367.24 | Z176: 29760.02 | AA176: 777880.58 | AB176: 1012453.9 | AC176: 0 | AD176: 0 | AE176: 0 | AF176: 87550.94 | AG176: 15484.51 | AH176: 439877.94 | AI176: 455331.19 | AJ176: 358219.91 | AK176: 0 | AL176: 65199774 | AM176: 2499.8262 | AN176: 21066.45 | AO176: 0 | AP176: 165060.13 | AQ176: 88883.27 | AS176: 44316 | AT176: ABRIL | AU176: Negativo | AV176: 2021 | AW176: MULTINACIONAL C.A. | AX176: 2.39 | AY176: 2.75
A177: 73 | B177: Mundial de Seguros,C.A. | C177: 0 | D177: -57637 | E177: 0 | F177: 0 | G177: 115458.97 | H177: -357941.4 | I177: 40740.1 | J177: 321826.86 | K177: 0 | L177: 0 | M177: 0 | N177: 0 | O177: -1427.87 | P177: -56394.1 | Q177: -49885.39 | R177: -106279.49 | S177: -251661.9 | T177: 1.18 | U177: 0 | V177: 0 | W177: 0 | X177: 253959.94 | Y177: 2356.31 | Z177: 0.51 | AA177: 19 | AB177: 3.87 | AC177: 0 | AD177: 0 | AE177: 0 | AF177: 503243.34 | AG177: 0 | AH177: 0 | AI177: 0 | AJ177: 1427.87 | AK177: 0 | AL177: 40740.1 | AN177: 0 | AO177: 0 | AP177: 1427.87 | AQ177: -57637 | AS177: 44316 | AT177: ABRIL | AU177: Negativo | AV177: 2021 | AW177: MUNDIAL C.A. | AX177: 2.39 | AY177: 2.75
A178: 46 | B178: Nuevo Mundo S.A., Seguros | C178: 772772.12 | D178: 209299.86 | E178: 225032.96 | F178: 152743.84 | G178: 240683.79 | H178: 21073.46 | I178: 9123157.6 | J178: 1223611.9 | K178: 871939.3 | L178: 646904.96 | M178: 31550.25 | N178: 3.14 | O178: 546056.48 | P178: -376011.85 | Q178: -9900.28 | R178: -385912.13 | S178: 406985.57 | T178: 119570.61 | U178: 0 | V178: 0 | W178: 0 | X178: 301522.56 | Y178: 4911.91 | Z178: 1355.82 | AA178: 5677.56 | AB178: 2162.29 | AC178: 0 | AD178: 0 | AE178: 0 | AF178: 0 | AG178: 678455.2 | AH178: 225036.1 | AI178: 902938.33 | AJ178: 356881.85 | AK178: 0 | AL178: 8251218.3 | AM178: 10.463065 | AN178: 89597.78 | AO178: 63146.07 | AP178: 330077.69 | AQ178: 312661.9 | AS178: 44316 | AT178: ABRIL | AU178: Positivo | AV178: 2021 | AW178: NUEVO MUNDO S.A. | AX178: 2.39 | AY178: 2.75
A179: 51 | B179: Occidental C.A., Seguros | C179: 1054717 | D179: 135145.12 | E179: 1241331.2 | F179: 94761.25 | G179: 1224020.4 | H179: 427484.46 | I179: 10318838 | J179: 16521798 | K179: 1855858.8 | L179: 614527.61 | M179: 203286.93 | N179: 64099.29 | O179: 1414927.8 | P179: -1814137.6 | Q179: -32958.14 | R179: -1847095.8 | S179: 2274580.2 | T179: 0 | U179: 0 | V179: 0 | W179: 0 | X179: 10954681 | Y179: 21917.16 | Z179: 24537.17 | AA179: 1712537.8 | AB179: 2476.38 | AC179: 0 | AD179: 0 | AE179: 0 | AF179: 6918632.3 | AG179: 817814.54 | AH179: 1305430.5 | AI179: 2123116 | AJ179: 708188.16 | AK179: 0 | AL179: 8462979.1 | AM179: 5.5601417 | AN179: 62228.38 | AO179: 32532.86 | AP179: 450709.22 | AQ179: 946065.22 | AS179: 44316 | AT179: ABRIL | AU179: Positivo | AV179: 2021 | AW179: OCCIDENTAL C.A. | AX179: 2.39 | AY179: 2.75
A180: 117 | B180: Oceánica de Seguros, C.A. | C180: 14956527 | D180: 9627498.4 | E180: 378396.12 | F180: 1984265.7 | G180: 3540229.8 | H180: 28295.28 | I180: 12307442 | J180: 4413377.6 | K180: 1002285.7 | L180: 623889.54 | M180: 10718844 | N180: 6723247.9 | O180: 10074506 | P180: -10269973 | Q180: 10761212 | R180: 491239.25 | S180: -462943.99 | T180: 623 | U180: 0 | V180: 0 | W180: 20619.33 | X180: 1786835.2 | Y180: 39480.35 | Z180: 301094.58 | AA180: 1031258.9 | AB180: 13148.11 | AC180: 0 | AD180: 0 | AE180: 0 | AF180: 886039.55 | AG180: 11342734 | AH180: 7101644.1 | AI180: 18443354 | AJ180: 8368848.5 | AK180: 0 | AL180: 11305156 | AM180: 12.279375 | AN180: 1915686.3 | AO180: 68579.36 | AP180: 9868772.1 | AQ180: 14614249 | AS180: 44316 | AT180: ABRIL | AU180: Positivo | AV180: 2021 | AW180: OCEÁNICA C.A. | AX180: 2.39 | AY180: 2.75
A181: 78 | B181: Oriental de Seguros C.A. | C181: 38949.06 | D181: 0 | E181: 144.25 | F181: 6036.3 | G181: 51397.44 | H181: 42435.4 | I181: 113838.9 | J181: 146155.34 | K181: 18956.11 | L181: 18811.86 | M181: 41934.97 | N181: 0 | O181: 28884.65 | P181: -47369.33 | Q181: 4622.7 | R181: -42746.63 | S181: 85182.04 | T181: 3777.69 | U181: 12.58 | V181: 0 | W181: 0 | X181: 84331.34 | Y181: 1009.23 | Z181: 1459.33 | AA181: 0 | AB181: 9.1 | AC181: 0 | AD181: 0 | AE181: 0 | AF181: 461.91 | AG181: 60746.84 | AH181: 144.25 | AI181: 60880.05 | AJ181: 31995.4 | AK181: 0 | AL181: 94882.79 | AM181: 6.0053935 | AN181: 4783.77 | AO181: 1252.53 | AP181: 10207.51 | AQ181: 143.12 | AS181: 44316 | AT181: ABRIL | AU181: Positivo | AV181: 2021 | AW181: ORIENTAL C.A. | AX181: 2.39 | AY181: 2.75
A182: 80 | B182: Pirámide C.A., Seguros | C182: 34784749 | D182: 19600620 | E182: 1006704.3 | F182: 4001504.7 | G182: 8063085.4 | H182: 36517.37 | I182: 26237348 | J182: 31269697 | K182: 1445063.2 | L182: 438358.92 | M182: 14332329 | N182: 1.9814665e+08 | O182: 1.3692952e+08 | P182: -1.3380998e+08 | Q182: 1.3389618e+08 | R182: 86205.12 | S182: -49687.72 | T182: 2071.02 | U182: 0 | V182: 0 | W182: 127088.94 | X182: 12332955 | Y182: 116812.9 | Z182: 531853.13 | AA182: 11447373 | AB182: 32651.51 | AC182: 0 | AD182: 0 | AE182: 0 | AF182: 383112.11 | AG182: 14770688 | AH182: 1.9915335e+08 | AI182: 2.1390633e+08 | AJ182: 76976819 | AK182: 0 | AL182: 24792284 | AM182: 18.15654 | AN182: 3197442.5 | AO182: 804062.16 | AP182: 25676922 | AQ182: 1.4742231e+08 | AS182: 44316 | AT182: ABRIL | AU182: Positivo | AV182: 2021 | AW182: PIRÁMIDE C.A. | AX182: 2.39 | AY182: 2.75
A183: 2 | B183: Previsora, C.N.A. de Seguros | C183: 478305.53 | D183: 8203.88 | E183: 3504.38 | F183: 1393.81 | G183: 393271.93 | H183: 48130.57 | I183: 4910598.3 | J183: 4376953.5 | K183: 49895.95 | L183: 46391.57 | M183: 64.74 | N183: 3.19 | O183: 33534.86 | P183: 41901.05 | Q183: -248472.36 | R183: -206571.31 | S183: 254701.89 | T183: 13031.35 | U183: 0 | V183: 0 | W183: 271145.65 | X183: 6900.42 | Y183: 7998.47 | Z183: 0 | AA183: 23121.53 | AB183: 0 | AC183: 0 | AD183: 0 | AE183: 0 | AF183: 5255.54 | AG183: 46456.31 | AH183: 3507.57 | AI183: 49905.99 | AJ183: 16371.13 | AK183: 0 | AL183: 4860702.4 | AM183: 98.416772 | AN183: 1393.81 | AO183: 0 | AP183: 444692.04 | AQ183: 8125.26 | AS183: 44316 | AT183: ABRIL | AU183: Positivo | AV183: 2021 | AW183: PREVISORA C.N.A. | AX183: 2.39 | AY183: 2.75
A184: 115 | B184: Seguros Seguramiga C.A. | C184: 75.87 | D184: 0 | E184: 0 | F184: 0 | G184: 34423.82 | H184: 203782.37 | I184: 144864.94 | J184: 401338.25 | K184: 72.14 | L184: 72.13 | M184: 0 | N184: 0 | O184: 57.38 | P184: -34405.33 | Q184: 0 | R184: -34405.33 | S184: 238187.71 | T184: 10.4 | U184: 0 | V184: 0 | W184: 0 | X184: 239521.14 | Y184: 702.53 | Z184: 249.67 | AA184: 0 | AB184: 0.01 | AC184: 0 | AD184: 0 | AE184: 391.62 | AF184: 0 | AG184: 72.13 | AH184: 0 | AI184: 71.76 | AJ184: 14.38 | AK184: 0 | AL184: 144792.8 | AM184: 2008.1084 | AN184: 0 | AO184: 0 | AP184: 18.49 | AQ184: 0 | AS184: 44316 | AT184: ABRIL | AU184: Positivo | AV184: 2021 | AW184: SEGURAMIGA C.A. | AX184: 2.39 | AY184: 2.75
A185: 106 | B185: Proseguros, S.A. | C185: 279928.07 | D185: 34.02 | E185: 1411.06 | F185: 65052.47 | G185: 128113.83 | H185: 90.94 | I185: 363570.58 | J185: 34758.76 | K185: 110473.71 | L185: 109227.02 | M185: 133805.3 | N185: 9.01 | O185: 180055.93 | P185: -93328.18 | Q185: 25421.67 | R185: -67906.51 | S185: 67997.46 | T185: 0.03 | U185: 0 | V185: 0 | W185: 0 | X185: 79664.75 | Y185: 2543.68 | Z185: 730.04 | AA185: 2687 | AB185: 760.47 | AC185: 0 | AD185: 0 | AE185: 0 | AF185: 4946.13 | AG185: 242867.94 | AH185: 1420.07 | AI185: 244233.19 | AJ185: 64177.26 | AK185: 0 | AL185: 253096.87 | AM185: 3.2910145 | AN185: 36896.54 | AO185: 28155.93 | AP185: 101280.88 | AQ185: 1442.76 | AS185: 44316 | AT185: ABRIL | AU185: Positivo | AV185: 2021 | AW185: PROSEGUROS S.A. | AX185: 2.39 | AY185: 2.75
A186: 118 | B186: Qualitas C.A., Seguros | C186: 3239669.6 | D186: 648111.8 | E186: 264815.45 | F186: 196574.07 | G186: 618613 | H186: 9996.42 | I186: 3899207.9 | J186: 944505.41 | K186: 731675.29 | L186: 397652.95 | M186: 994319.42 | N186: 905807.29 | O186: 1792609.6 | P186: -16238.93 | Q186: 28403.07 | R186: 12164.14 | S186: -2167.71 | T186: 57.26 | U186: 0 | V186: 0 | W186: 2985.09 | X186: 166378.05 | Y186: 9415.56 | Z186: 19341.15 | AA186: 127171.4 | AB186: 1832.55 | AC186: 0 | AD186: 0 | AE186: 13825.15 | AF186: 2.31 | AG186: 1391972.4 | AH186: 1170622.7 | AI186: 2562542.4 | AJ186: 769932.79 | AK186: 0 | AL186: 3167532.6 | AM186: 5.3291508 | AN186: 126082.75 | AO186: 70491.32 | AP186: 2352094.9 | AQ186: 1553146.7 | AS186: 44316 | AT186: ABRIL | AU186: Positivo | AV186: 2021 | AW186: QUALITAS C.A. | AX186: 2.39 | AY186: 2.75
A187: 29 | B187: Real Seguros, S.A. | C187: 5844453.2 | D187: 473484.2 | E187: 66036.98 | F187: 853807.73 | G187: 894467.08 | H187: 634587.14 | I187: 11757945 | J187: 7292340.5 | K187: 1065000.3 | L187: 998963.34 | M187: 2747952 | N187: 373610.71 | O187: 3090116.2 | P187: 532577.99 | Q187: -1149569 | R187: -616991.04 | S187: 1251578.2 | T187: 636033.5 | U187: 0 | V187: 0 | W187: 0 | X187: 2945822 | Y187: 18241.22 | Z187: 21648.81 | AA187: 638.29 | AB187: 8538.45 | AC187: 0 | AD187: 0 | AE187: 0 | AF187: 2281210.6 | AG187: 3746915.3 | AH187: 439647.69 | AI187: 4178966.6 | AJ187: 1088850.4 | AK187: 0 | AL187: 10692945 | AM187: 11.040321 | AN187: 642073.72 | AO187: 211734.01 | AP187: 2883141.3 | AQ187: 602288.51 | AS187: 44316 | AT187: ABRIL | AU187: Positivo | AV187: 2021 | AW187: REAL S.A. | AX187: 2.39 | AY187: 2.75
A188: 111 | B188: Universal de Seguros C.A. | C188: 256122.26 | D188: 26111.98 | E188: 208863.57 | F188: 24438.23 | G188: 181307.89 | H188: 3323.82 | I188: 538793.22 | J188: 125782.17 | K188: 362142.32 | L188: 153278.75 | M188: 0 | N188: 0 | O188: 94068.4 | P188: -69804.24 | Q188: -8621.51 | R188: -78425.75 | S188: 81749.58 | T188: 2465.36 | U188: 0 | V188: 0 | W188: 860.17 | X188: 98958.98 | Y188: 3688.74 | Z188: 3365.82 | AA188: 6295.32 | AB188: 234.09 | AC188: 0 | AD188: 0 | AE188: 0 | AF188: 6950.97 | AG188: 153278.76 | AH188: 208863.57 | AI188: 362115.64 | AJ188: 268047.24 | AK188: 0 | AL188: 176650.9 | AM188: 1.4877941 | AN188: 13439.98 | AO188: 10998.26 | AP188: 275044.08 | AQ188: 139102.21 | AS188: 44316 | AT188: ABRIL | AU188: Positivo | AV188: 2021 | AW188: UNIVERSAL C.A. | AX188: 2.39 | AY188: 2.75
A189: 83 | B189: Universitas, C.A. Seguros | C189: 17623741 | D189: 2006236.4 | E189: 4043951.9 | F189: 3236909.4 | G189: 8488961.6 | H189: 307048.1 | I189: 16611686 | J189: 1408470.9 | K189: 11179137 | L189: 7135185.3 | M189: 6645450.5 | N189: 174.94 | O189: 7275353.5 | P189: -3383719.7 | Q189: -4623584.8 | R189: -8007304.5 | S189: 8314352.6 | T189: 283200.15 | U189: 0 | V189: 0 | W189: 854748.49 | X189: 11045413 | Y189: 120205.22 | Z189: 245963.47 | AA189: 1408614.5 | AB189: 38287.57 | AC189: 0 | AD189: 0 | AE189: 0 | AF189: 2055938.1 | AG189: 13780636 | AH189: 4044126.8 | AI189: 17816819 | AJ189: 10541465 | AK189: 0 | AL189: 5432548.4 | AM189: 1.4859542 | AN189: 2352428 | AO189: 884481.35 | AP189: 11329727 | AQ189: 2987576 | AS189: 44316 | AT189: ABRIL | AU189: Positivo | AV189: 2021 | AW189: UNIVERSITAS C.A. | AX189: 2.39 | AY189: 2.75
... A191: 24 | B191: Venezuela C.A., Seguros | C191: 780861.22 | D191: 339429.41 | E191: 84283.24 | F191: 96890.34 | G191: 547590.28 | H191: 597333.63 | I191: 2101731.1 | J191: 2946579 | K191: 609598.16 | L191: 497796.58 | M191: 183038.01 | N191: 630.07 | O191: 540344.27 | P191: -743393.08 | Q191: 26820.36 | R191: -716572.72 | S191: 1313906.4 | T191: 52263.57 | U191: 0 | V191: 0 | W191: 198337.46 | X191: 1555539 | Y191: 8953.15 | Z191: 47710.76 | AA191: 92159.33 | AB191: 4022.86 | AC191: 0 | AD191: 0 | AE191: 0 | AF191: 339387.57 | AG191: 680834.58 | AH191: 84913.31 | AI191: 763662.63 | AJ191: 241520.75 | AK191: 18202.39 | AL191: 1492132.9 | AM191: 3.447732 | AN191: 85499.4 | AO191: 11390.95 | AP191: 298668.64 | AQ191: 397581.09 | AS191: 44316 | AT191: ABRIL | AU191: Positivo | AV191: 2021 | AW191: VENEZUELA C.A. | AX191: 2.39 | AY191: 2.75
A192: 124 | B192: Vértice, C.A Seguros | C192: 0 | D192: 0 | E192: 0 | F192: 0 | G192: 0 | H192: 0 | I192: 33.54 | J192: 0 | K192: 0 | L192: 0 | M192: 0 | N192: 0 | O192: 0 | P192: 0 | Q192: 0 | R192: 0 | S192: 0 | T192: 0 | U192: 0 | V192: 0 | W192: 0 | X192: 0 | Y192: 0 | Z192: 0 | AA192: 0 | AB192: 0 | AC192: 0 | AD192: 0 | AE192: 0 | AF192: 0 | AG192: 0 | AH192: 0 | AI192: 0 | AJ192: 0 | AK192: 0 | AL192: 33.54 | AN192: 0 | AO192: 0 | AP192: 0 | AQ192: 0 | AS192: 44316 | AT192: ABRIL | AU192: Positivo | AV192: 2021 | AW192: VÉRTICE, C.A. | AX192: 2.39 | AY192: 2.75
A193: 70 | B193: Virgen del Valle C.A., Seguros | C193: 34733.25 | D193: 4538.46 | E193: 2255.29 | F193: 0 | G193: 14559.26 | H193: 10760.84 | I193: 33251.11 | J193: 6903.11 | K193: 5906.43 | L193: 3651.14 | M193: 0 | N193: 0 | O193: 4568.03 | P193: 11067.5 | Q193: 0 | R193: 11067.5 | S193: -306.66 | T193: 0.01 | U193: 0 | V193: 0 | W193: 0 | X193: 0 | Y193: 72.24 | Z193: 234.43 | AA193: 0 | AB193: 0 | AC193: 0 | AD193: 0 | AE193: 0 | AF193: 0 | AG193: 3651.14 | AH193: 2255.29 | AI193: 5906.43 | AJ193: 1338.4 | AK193: 0 | AL193: 27344.68 | AM193: 5.629646 | AN193: 0 | AO193: 0 | AP193: 32363.49 | AQ193: 6736.73 | AS193: 44316 | AT193: ABRIL | AU193: Positivo | AV193: 2021 | AW193: VIRGEN DEL VALLE C.A. | AX193: 2.39 | AY193: 2.75
A194: 119 | B194: Vitalicia, S.A., Seguros | C194: 0 | D194: 0 | E194: 0 | F194: 0 | G194: 2596.68 | H194: 2.24 | I194: 29431.55 | J194: 3632.31 | K194: 1.16 | L194: 1.16 | M194: 0 | N194: 0 | O194: -3.37 | P194: -2593.31 | Q194: 0 | R194: -2593.31 | S194: 2595.56 | T194: 2700.36 | U194: 0 | V194: 0 | W194: 0 | X194: 0 | Y194: 52.99 | Z194: 41.06 | AA194: 10.47 | AB194: 0.27 | AC194: 0 | AD194: 0 | AE194: 0 | AF194: 0 | AG194: 1.16 | AH194: 0 | AI194: 1.15 | AJ194: 4.52 | AK194: 0 | AL194: 29430.39 | AM194: 25372.026 | AN194: 0 | AO194: 0 | AP194: 3.37 | AQ194: 0 | AS194: 44316 | AT194: ABRIL | AU194: Positivo | AV194: 2021 | AW194: VITALICIA S.A. | AX194: 2.39 | AY194: 2.75
A195: 108 | B195: Vivir Seguros C.A. | C195: 557151.87 | D195: 97960.18 | E195: 86326.16 | F195: 20751.28 | G195: 64259.59 | H195: 817.16 | I195: 2740594.8 | J195: 68016.46 | K195: 143852.73 | L195: 57525.88 | M195: 96709.75 | N195: 16685.15 | O195: 155772.96 | P195: 218407.86 | Q195: -296117.92 | R195: -77710.06 | S195: 78527.22 | T195: 1897.93 | U195: 0 | V195: 0 | W195: 0 | X195: 152313.98 | Y195: 1224.24 | Z195: 1403.89 | AA195: 13612.83 | AB195: 11.38 | AC195: 0 | AD195: 0 | AE195: 0 | AF195: 59432.35 | AG195: 154235.63 | AH195: 103011.31 | AI195: 256709 | AJ195: 100936.04 | AK195: 0 | AL195: 2596742.1 | AM195: 19.051392 | AN195: 20121.55 | AO195: 629.74 | AP195: 483675.11 | AQ195: 180256.39 | AS195: 44316 | AT195: ABRIL | AU195: Positivo | AV195: 2021 | AW195: VIVIR C.A. | AX195: 2.39 | AY195: 2.75
A196: 93 | B196: Zuma Seguros, C.A. | C196: 190493.31 | D196: 19 | E196: 3395.35 | F196: 46135.22 | G196: 159713.87 | H196: 52886.95 | I196: 2682439 | J196: 1442660.7 | K196: 135662.68 | L196: 132267.33 | M196: 5709.55 | N196: 0 | O196: 112338.96 | P196: -127713.74 | Q196: -537.08 | R196: -128250.82 | S196: 181137.78 | T196: 1472.52 | U196: 0 | V196: 0 | W196: 0 | X196: 203097.71 | Y196: 3152.62 | Z196: 6662.68 | AA196: 12273.39 | AB196: 4.39 | AC196: 0 | AD196: 0 | AE196: 0 | AF196: 1339.37 | AG196: 137976.89 | AH196: 3395.35 | AI196: 141345.58 | AJ196: 29006.62 | AK196: 0 | AL196: 2546776.3 | AM196: 19.772859 | AN196: 28543.85 | AO196: 17591.35 | AP196: 81484.91 | AQ196: 3349.56 | AS196: 44316 | AT196: ABRIL | AU196: Positivo | AV196: 2021 | AW196: ZUMA C.A. | AX196: 2.39 | AY196: 2.75
A197: 32 | B197: Adriática de Seguros, C.A. | C197: 1e-08 | D197: 0 | E197: 1e-08 | F197: 0 | G197: 22827.916 | H197: 1898.2131 | I197: 732892.47 | J197: 3999.8323 | K197: 2e-08 | L197: 1e-08 | M197: 0 | N197: 0 | O197: 1e-08 | P197: -22827.916 | Q197: 0 | R197: -22827.916 | S197: 24726.129 | T197: 0 | U197: 0 | V197: 0 | W197: 0 | X197: 28138.465 | Y197: 465.259 | Z197: 9.6060315 | AA197: 2484.414 | AB197: 0 | AC197: 0 | AD197: 0 | AE197: 0 | AF197: 453.05689 | AG197: 1e-08 | AH197: 1e-08 | AI197: 1e-08 | AJ197: 0 | AK197: 0 | AL197: 732892.47 | AM197: 36644623 | AN197: 0 | AO197: 0 | AP197: 0 | AQ197: 0 | AS197: 44347 | AT197: MAYO | AU197: Positivo | AV197: 2021 | AW197: ADRIÁTICA C.A. | AX197: 2.94 | AY197: 3.1
A198: 107 | B198: Altamira C.A., Seguros | C198: 4958398.5 | D198: 292284.58 | E198: 154680.4 | F198: 383980.58 | G198: 286269.08 | H198: 17703.95 | I198: 710514.42 | J198: 935260.2 | K198: 562277.78 | L198: 407597.39 | M198: 1580313.2 | N198: 366987.11 | O198: 1853751.4 | P198: 2142112.8 | Q198: -2172012.2 | R198: -29899.35 | S198: 47603.31 | T198: 2956.25 | U198: 0 | V198: 0 | W198: 0 | X198: 118439.64 | Y198: 5842.23 | Z198: 44685.8 | AA198: 22665.63 | AB198: 597.93 | AC198: 0 | AD198: 0 | AE198: 0 | AF198: 1 | AG198: 1987910.6 | AH198: 521667.5 | AI198: 2509280.5 | AJ198: 655529.09 | AK198: 0 | AL198: 148236.64 | AM198: 1.263636 | AN198: 274679.24 | AO198: 109301.34 | AP198: 3551287.3 | AQ198: 738924.84 | AS198: 44347 | AT198: MAYO | AU198: Positivo | AV198: 2021 | AW198: ALTAMIRA C.A. | AX198: 2.94 | AY198: 3.1
A199: 66 | B199: American International, C.A. de Seguros | C199: 1262039.9 | D199: 332738.32 | E199: 9.35 | F199: 39342.74 | G199: 663274.77 | H199: 1587609.4 | I199: 1486108.1 | J199: 18521610 | K199: 3262.53 | L199: 3253.18 | M199: 421565.79 | N199: 1536.05 | O199: 357637.97 | P199: -130953.93 | Q199: -339310.3 | R199: -470264.23 | S199: 2057873.6 | T199: 2586.52 | U199: 0 | V199: 0 | W199: 0 | X199: 25415912 | Y199: 13213.85 | Z199: 12616.34 | AA199: 1356588.8 | AB199: 17.25 | AC199: 0 | AD199: 0 | AE199: 0 | AF199: 21978188 | AG199: 424818.97 | AH199: 1545.4 | AI199: 426345.28 | AJ199: 68707.31 | AK199: 0 | AL199: 1482845.5 | AM199: 455.50786 | AN199: 39342.74 | AO199: 0 | AP199: 905637.92 | AQ199: 333974.34 | AS199: 44347 | AT199: MAYO | AU199: Positivo | AV199: 2021 | AW199: A.I.G. C.A. | AX199: 2.94 | AY199: 3.1
A200: 44 | B200: Andes C.A., Seguros | C200: 2014447.4 | D200: 536202.67 | E200: 442849.91 | F200: 272611.96 | G200: 500263.7 | H200: 4518.48 | I200: 1519753.6 | J200: 939379.94 | K200: 1406833.6 | L200: 963843.09 | M200: 855.03 | N200: 133.95 | O200: 1082538.9 | P200: -377169.82 | Q200: -697.63 | R200: -377867.45 | S200: 382385.91 | T200: 25.61 | U200: 0 | V200: 0 | W200: 0 | X200: 475984.35 | Y200: 8897.59 | Z200: 2226.58 | AA200: 73046.06 | AB200: 8485.47 | AC200: 0 | AD200: 0 | AE200: 0 | AF200: 968.35 | AG200: 964698.12 | AH200: 442983.86 | AI200: 1406923 | AJ200: 324473.65 | AK200: 89.57 | AL200: 112920.01 | AM200: 1.0802654 | AN200: 205121.06 | AO200: 67490.9 | AP200: 1322089.5 | AQ200: 926383.63 | AS200: 44347 | AT200: MAYO | AU200: Positivo | AV200: 2021 | AW200: ANDES C.A. | AX200: 2.94 | AY200: 3.1
A201: 113 | B201: Aseguradora Nacional Unida Uniseguros, S.A. | C201: 98797.59 | D201: 7416.85 | E201: 151.61 | F201: 6163.42 | G201: 177891.49 | H201: 841266.63 | I201: 8285586.6 | J201: 1415910.4 | K201: 152332.73 | L201: 38234.44 | M201: 39131.76 | N201: 709.9 | O201: 23481.25 | P201: -116155.42 | Q201: -12010.98 | R201: -128166.4 | S201: 969433.01 | T201: 775.14 | U201: 0 | V201: 0 | W201: 0 | X201: 978674.34 | Y201: 3630.44 | Z201: 5349.79 | AA201: 255.77 | AB201: 585.51 | AC201: 0 | AD201: 0 | AE201: 0 | AF201: 194.97 | AG201: 77366.19 | AH201: 861.51 | AI201: 77501.75 | AJ201: 54020.5 | AK201: 0 | AL201: 8133253.9 | AM201: 54.391375 | AN201: 3739.52 | AO201: 2423.9 | AP201: 75480.4 | AQ201: 7580.91 | AS201: 44347 | AT201: MAYO | AU201: Positivo | AV201: 2021 | AW201: UNISEGUROS S.A. | AX201: 2.94 | AY201: 3.1
A202: 98 | B202: Atrio Seguros S.A. | C202: 7156471.9 | D202: 2916554.4 | E202: 886486.77 | F202: 1674163.7 | G202: 2200030.2 | H202: 28641.42 | I202: 3899266 | J202: 1289307.5 | K202: 2470332.4 | L202: 1583845.6 | M202: 3400995.3 | N202: 4430205.4 | O202: 8017091.7 | P202: -7651368.1 | Q202: 6371484.1 | R202: -1279884.1 | S202: 1308525.5 | T202: 4699.18 | U202: 2989.55 | V202: 0 | W202: 0 | X202: 2057320.8 | Y202: 35673.26 | Z202: 113589.32 | AA202: 150937.95 | AB202: 6045.64 | AC202: 0 | AD202: 0 | AE202: 0 | AF202: 450237.86 | AG202: 4984840.9 | AH202: 5316692.2 | AI202: 10301311 | AJ202: 2284219.3 | AK202: 0 | AL202: 1428933.6 | AM202: 1.5784378 | AN202: 860877.9 | AO202: 813285.83 | AP202: 3762597.4 | AQ202: 7539771.6 | AS202: 44347 | AT202: MAYO | AU202: Positivo | AV202: 2021 | AW202: ATRIO S.A. | AX202: 2.94 | AY202: 3.1
A203: 1 | B203: Ávila C.A., de Seguros | C203: 750292.86 | D203: 59443.9 | E203: 1144.86 | F203: 158440.48 | G203: 134755.49 | H203: 21202.14 | I203: 53172.48 | J203: 224545.91 | K203: 172584.12 | L203: 171439.27 | M203: 332052.69 | N203: 2.05 | O203: 417010.08 | P203: -19357.09 | Q203: -19105.53 | R203: -38462.62 | S203: 59664.76 | T203: 7026.56 | U203: 0 | V203: 0 | W203: 0 | X203: 70645.13 | Y203: 2695.36 | Z203: 14873.89 | AA203: 397.99 | AB203: 18.43 | AC203: 0 | AD203: 0 | AE203: 0 | AF203: 21.26 | AG203: 503491.98 | AH203: 1146.91 | AI203: 504366.22 | AJ203: 87356.14 | AK203: 0 | AL203: -119411.64 | AM203: 0.30809602 | AN203: 77236.14 | AO203: 81204.34 | AP203: 334429.68 | AQ203: 60590.81 | AS203: 44347 | AT203: MAYO | AU203: Positivo | AV203: 2021 | AW203: ÁVILA C.A. | AX203: 2.94 | AY203: 3.1
A204: 109 | B204: Banesco Seguros C.A. | C204: 9487927.7 | D204: 5013817.1 | E204: 3420835.3 | F204: 877048.85 | G204: 1504292.1 | H204: -1244601.5 | I204: 34362863 | J204: 4066980.4 | K204: 6257615.2 | L204: 1697938.7 | M204: 974549.77 | N204: 8576042.4 | O204: 10270351 | P204: -8177581 | Q204: 4247701.6 | R204: -3929879.4 | S204: 2685277.9 | T204: 66918.46 | U204: 0 | V204: 0 | W204: 55040.57 | X204: 3749104.9 | Y204: 27341.97 | Z204: 186.92 | AA204: 211303.08 | AB204: 2054.88 | AC204: 0 | AD204: 0 | AE204: 0 | AF204: 944899.14 | AG204: 2672488.5 | AH204: 11996878 | AI204: 14659470 | AJ204: 4389119 | AK204: 0 | AL204: 28105248 | AM204: 5.4913673 | AN204: 496126.14 | AO204: 380922.71 | AP204: 7710397 | AQ204: 13506637 | AS204: 44347 | AT204: MAYO | AU204: Negativo | AV204: 2021 | AW204: BANESCO C.A. | AX204: 2.94 | AY204: 3.1
... A224: 91 | B224: Multinacional de Seguros C.A. | C224: 249348.43 | D224: 7275.24 | E224: 10004.6 | F224: 24145.35 | G224: 415057.82 | H224: -2157967.8 | I224: 64976983 | J224: 12223130 | K224: 42587.21 | L224: 32136.28 | M224: 0 | N224: 429716.63 | O224: 113606.33 | P224: -310736.31 | Q224: 304208.72 | R224: -6527.59 | S224: -2151440.2 | T224: 6.48 | U224: 0 | V224: 0 | W224: 0 | X224: 120768.02 | Y224: 2704.77 | Z224: 42854.48 | AA224: 858590.87 | AB224: 1265567.4 | AC224: 0 | AD224: 0 | AE224: 0 | AF224: 102497.22 | AG224: 32136.28 | AH224: 439721.23 | AI224: 471826.24 | AJ224: 358219.91 | AK224: 0 | AL224: 64934396 | AM224: 1525.7394 | AN224: 24145.35 | AO224: 0 | AP224: 219162.21 | AQ224: 90695.36 | AS224: 44347 | AT224: MAYO | AU224: Negativo | AV224: 2021 | AW224: MULTINACIONAL C.A. | AX224: 2.94 | AY224: 3.1
A225: 73 | B225: Mundial de Seguros,C.A. | C225: 0 | D225: -57637 | E225: 0 | F225: 0 | G225: 161796.64 | H225: -471057.08 | I225: 32329.21 | J225: 317088.81 | K225: 0 | L225: 0 | M225: 0 | N225: 0 | O225: -1427.87 | P225: -102731.77 | Q225: -49885.39 | R225: -152617.16 | S225: -318439.92 | T225: 1.87 | U225: 0 | V225: 0 | W225: 0 | X225: 299536.81 | Y225: 3301.97 | Z225: 24.45 | AA225: 44.63 | AB225: 4.87 | AC225: 0 | AD225: 0 | AE225: 0 | AF225: 614602.68 | AG225: 0 | AH225: 0 | AI225: 0 | AJ225: 1427.87 | AK225: 0 | AL225: 32329.21 | AN225: 0 | AO225: 0 | AP225: 1427.87 | AQ225: -57637 | AS225: 44347 | AT225: MAYO | AU225: Negativo | AV225: 2021 | AW225: MUNDIAL C.A. | AX225: 2.94 | AY225: 3.1
A226: 46 | B226: Nuevo Mundo S.A., Seguros | C226: 1038295.1 | D226: 355529.31 | E226: 208859.62 | F226: 207632.71 | G226: 313677.86 | H226: 26923.92 | I226: 9127136.4 | J226: 1229266.5 | K226: 993768.61 | L226: 784907.6 | M226: 27522.9 | N226: 0 | O226: 663855.31 | P226: -502400.12 | Q226: -14096.24 | R226: -516496.36 | S226: 543420.27 | T226: 184510.86 | U226: 0 | V226: 0 | W226: 0 | X226: 375439.4 | Y226: 6401.59 | Z226: 1748.77 | AA226: 5677.56 | AB226: 2702.07 | AC226: 0 | AD226: 0 | AE226: 0 | AF226: 0 | AG226: 812430.51 | AH226: 208859.62 | AI226: 1020737.2 | AJ226: 356881.85 | AK226: 0 | AL226: 8133367.8 | AM226: 9.1843678 | AN226: 123630.9 | AO226: 84001.81 | AP226: 461625.34 | AQ226: 442714.87 | AS226: 44347 | AT226: MAYO | AU226: Positivo | AV226: 2021 | AW226: NUEVO MUNDO S.A. | AX226: 2.94 | AY226: 3.1
A227: 51 | B227: Occidental C.A., Seguros | C227: 1316719.1 | D227: 172429.16 | E227: 1341283.8 | F227: 143608.28 | G227: 1481246.3 | H227: 882063.87 | I227: 10269994 | J227: 18661254 | K227: 1919509.9 | L227: 578226.04 | M227: 305610.05 | N227: 169556.3 | O227: 1686359 | P227: -2166923.7 | Q227: -3867.05 | R227: -2170790.7 | S227: 3052854.6 | T227: 0.57 | U227: 0 | V227: 0 | W227: 0 | X227: 13490532 | Y227: 25733.45 | Z227: 34175.79 | AA227: 1883703.8 | AB227: 3219.94 | AC227: 0 | AD227: 0 | AE227: 0 | AF227: 8490845.4 | AG227: 883836.09 | AH227: 1510840.1 | AI227: 2394547.2 | AJ227: 708188.16 | AK227: 0 | AL227: 8350484.1 | AM227: 5.350321 | AN227: 93689.79 | AO227: 49918.47 | AP227: 646689.77 | AQ227: 1188758.9 | AS227: 44347 | AT227: MAYO | AU227: Positivo | AV227: 2021 | AW227: OCCIDENTAL C.A. | AX227: 2.94 | AY227: 3.1
A228: 117 | B228: Oceánica de Seguros, C.A. | C228: 20038956 | D228: 12967674 | E228: 340759.03 | F228: 2687909.2 | G228: 5205569.5 | H228: 101.77 | I228: 13169744 | J228: 2860646.8 | K228: 1085215.2 | L228: 744456.19 | M228: 11709461 | N228: 9040562.7 | O228: 13465366 | P228: -14287563 | Q228: 14273504 | R228: -14058.54 | S228: 14160.32 | T228: 1904.11 | U228: 0 | V228: 0 | W228: 34276.8 | X228: 2486809 | Y228: 51830.2 | Z228: 384402.73 | AA228: 1034352.1 | AB228: 17763.79 | AC228: 0 | AD228: 0 | AE228: 0 | AF228: 1020480.8 | AG228: 12453917 | AH228: 9381321.7 | AI228: 21834215 | AJ228: 8368848.5 | AK228: 0 | AL228: 12084529 | AM228: 12.135606 | AN228: 2562451.1 | AO228: 125458.1 | AP228: 13840019 | AQ228: 20234103 | AS228: 44347 | AT228: MAYO | AU228: Positivo | AV228: 2021 | AW228: OCEÁNICA C.A. | AX228: 2.94 | AY228: 3.1
A229: 78 | B229: Oriental de Seguros C.A. | C229: 52964.28 | D229: 0 | E229: 3.21 | F229: 8324.38 | G229: 79840.6 | H229: 54208.99 | I229: 1330713.9 | J229: 155574.04 | K229: 19381.44 | L229: 19378.22 | M229: 44037.94 | N229: 0 | O229: 31412.95 | P229: -66613.65 | Q229: 1221.19 | R229: -65392.46 | S229: 119601.44 | T229: 22663.11 | U229: 15.83 | V229: 0 | W229: 0 | X229: 101642.99 | Y229: 1572.65 | Z229: 2239.31 | AA229: 435.24 | AB229: 11.38 | AC229: 0 | AD229: 0 | AE229: 0 | AF229: 461.91 | AG229: 63416.17 | AH229: 3.21 | AI229: 63408.35 | AJ229: 31995.4 | AK229: 0 | AL229: 1311332.5 | AM229: 68.659187 | AN229: 6717.17 | AO229: 1607.21 | AP229: 21553.39 | AQ229: 2.07 | AS229: 44347 | AT229: MAYO | AU229: Positivo | AV229: 2021 | AW229: ORIENTAL C.A. | AX229: 2.94 | AY229: 3.1
A230: 80 | B230: Pirámide C.A., Seguros | C230: 49876482 | D230: 25510173 | E230: 1322833.4 | F230: 5428381.7 | G230: 13328060 | H230: 7710.08 | I230: 29129547 | J230: 30710829 | K230: 2240132.6 | L230: 917299.19 | M230: 19032046 | N230: 2.190542e+08 | O230: 1.6333185e+08 | P230: -1.5772199e+08 | Q230: 1.5589161e+08 | R230: -1830375.2 | S230: 1838085.3 | T230: 2091.52 | U230: 0 | V230: 0 | W230: 128894.38 | X230: 17514946 | Y230: 194713.98 | Z230: 725912.86 | AA230: 14202453 | AB230: 45037.44 | AC230: 0 | AD230: 0 | AE230: 0 | AF230: 639729.52 | AG230: 19949345 | AH230: 2.2037703e+08 | AI230: 2.4030867e+08 | AJ230: 76976819 | AK230: 0 | AL230: 26889414 | AM230: 13.003492 | AN230: 4543778.1 | AO230: 884603.59 | AP230: 35589998 | AQ230: 1.7455554e+08 | AS230: 44347 | AT230: MAYO | AU230: Positivo | AV230: 2021 | AW230: PIRÁMIDE C.A. | AX230: 2.94 | AY230: 3.1
A231: 2 | B231: Previsora, C.N.A. de Seguros | C231: 1008138.6 | D231: 9766.94 | E231: 3504.38 | F231: 1393.81 | G231: 624686.98 | H231: 312295.54 | I231: 5210768.6 | J231: 4382063.1 | K231: 49895.95 | L231: 46391.57 | M231: 64.74 | N231: 3.19 | O231: 33534.86 | P231: 338756.05 | Q231: -249929.71 | R231: 88826.34 | S231: 223469.21 | T231: 13033.89 | U231: 0 | V231: 0 | W231: 271145.65 | X231: 6900.42 | Y231: 12667.36 | Z231: 339.09 | AA231: 49348.75 | AB231: 0 | AC231: 0 | AD231: 0 | AE231: 0 | AF231: 5255.54 | AG231: 46456.31 | AH231: 3507.57 | AI231: 49905.99 | AJ231: 16371.13 | AK231: 0 | AL231: 5160872.6 | AM231: 104.4327 | AN231: 1393.81 | AO231: 0 | AP231: 974525.15 | AQ231: 9688.32 | AS231: 44347 | AT231: MAYO | AU231: Positivo | AV231: 2021 | AW231: PREVISORA C.N.A. | AX231: 2.94 | AY231: 3.1
A232: 115 | B232: Seguros Seguramiga C.A. | C232: 114.44 | D232: 0 | E232: 0 | F232: 0 | G232: 43272.45 | H232: 246254.57 | I232: 138213.2 | J232: 453181.66 | K232: 96.13 | L232: 96.13 | M232: 0 | N232: 0 | O232: 81.38 | P232: -43239.39 | Q232: 0 | R232: -43239.39 | S232: 289493.95 | T232: 14.27 | U232: 0 | V232: 0 | W232: 0 | X232: 291360.83 | Y232: 883.11 | Z232: 447.13 | AA232: 0 | AB232: 0.02 | AC232: 0 | AD232: 0 | AE232: 550.9 | AF232: 0 | AG232: 96.13 | AH232: 0 | AI232: 95.76 | AJ232: 14.38 | AK232: 0 | AL232: 138117.07 | AM232: 1437.7738 | AN232: 0 | AO232: 0 | AP232: 33.07 | AQ232: 0 | AS232: 44347 | AT232: MAYO | AU232: Positivo | AV232: 2021 | AW232: SEGURAMIGA C.A. | AX232: 2.94 | AY232: 3.1
A233: 106 | B233: Proseguros, S.A. | C233: 715672.62 | D233: 34.02 | E233: 4294.92 | F233: 89056.66 | G233: 194822.29 | H233: 105.37 | I233: 396625.86 | J233: 115265.02 | K233: 154798.6 | L233: 150651.17 | M233: 315865.59 | N233: 9.01 | O233: 406441.13 | P233: 25318.52 | Q233: 27868.21 | R233: 53186.73 | S233: -53081.36 | T233: 3.72 | U233: 0 | V233: 0 | W233: 0 | X233: 104804.17 | Y233: 3850.32 | Z233: 2097.84 | AA233: 12111 | AB233: 982.26 | AC233: 0 | AD233: 0 | AE233: 0 | AF233: 138847.82 | AG233: 466369.28 | AH233: 4303.93 | AI233: 470618.39 | AJ233: 64177.26 | AK233: 0 | AL233: 241827.26 | AM233: 2.5622057 | AN233: 60790.94 | AO233: 28265.72 | AP233: 313524.09 | AQ233: 4326.62 | AS233: 44347 | AT233: MAYO | AU233: Positivo | AV233: 2021 | AW233: PROSEGUROS S.A. | AX233: 2.94 | AY233: 3.1
A234: 118 | B234: Qualitas C.A., Seguros | C234: 5296207.2 | D234: 1112880 | E234: 206612.33 | F234: 281967.55 | G234: 940177.59 | H234: 10734.57 | I234: 3842197.4 | J234: 869494.16 | K234: 824036.24 | L234: 617423.9 | M234: 1705925.5 | N234: 1647501.1 | O234: 3407477.3 | P234: -446295.26 | Q234: 649397.87 | R234: 203102.61 | S234: -192368.02 | T234: 90.84 | U234: 0 | V234: 0 | W234: 3851.41 | X234: 176450.3 | Y234: 14831.5 | Z234: 17588.73 | AA234: 316012.16 | AB234: 2667.16 | AC234: 0 | AD234: 0 | AE234: 21655.04 | AF234: 5.98 | AG234: 2323349.4 | AH234: 1854113.4 | AI234: 4177410.1 | AJ234: 769932.79 | AK234: 0 | AL234: 3018161.2 | AM234: 4.6626559 | AN234: 180224.41 | AO234: 101743.15 | AP234: 3477255.5 | AQ234: 2701405.6 | AS234: 44347 | AT234: MAYO | AU234: Positivo | AV234: 2021 | AW234: QUALITAS C.A. | AX234: 2.94 | AY234: 3.1
A235: 29 | B235: Real Seguros, S.A. | C235: 7385888.9 | D235: 639946.11 | E235: 97941.87 | F235: 1245351.8 | G235: 1194032 | H235: 644678.02 | I235: 11632015 | J235: 7124140.3 | K235: 1291827.1 | L235: 1193885.2 | M235: 2914366.1 | N235: 331484.6 | O235: 3441231.1 | P235: 865327.92 | Q235: -1692664.5 | R235: -827336.58 | S235: 1472014.6 | T235: 751239.72 | U235: 0 | V235: 0 | W235: 0 | X235: 3554110.2 | Y235: 24354.79 | Z235: 37249.89 | AA235: 100.78 | AB235: 8888.24 | AC235: 0 | AD235: 0 | AE235: 0 | AF235: 2762741.7 | AG235: 4108251.4 | AH235: 429426.47 | AI235: 4530081.5 | AJ235: 1088850.4 | AK235: 0 | AL235: 10340188 | AM235: 9.0043124 | AN235: 929215.55 | AO235: 316136.2 | AP235: 4063240.9 | AQ235: 758529.21 | AS235: 44347 | AT235: MAYO | AU235: Positivo | AV235: 2021 | AW235: REAL S.A. | AX235: 2.94 | AY235: 3.1
A236: 111 | B236: Universal de Seguros C.A. | C236: 386010.36 | D236: 30518.22 | E236: 271785.28 | F236: 36859.08 | G236: 232634.34 | H236: 6450.86 | I236: 609033.57 | J236: 141232.07 | K236: 428381.44 | L236: 156596.16 | M236: 0 | N236: 0 | O236: 160307.53 | P236: -74308.81 | Q236: -8621.51 | R236: -82930.32 | S236: 89381.19 | T236: 2465.36 | U236: 0 | V236: 0 | W236: 860.17 | X236: 110860.45 | Y236: 4735.88 | Z236: 5444.66 | AA236: 7357.03 | AB236: 294.96 | AC236: 0 | AD236: 0 | AE236: 0 | AF236: 6972.26 | AG236: 156596.17 | AH236: 271785.28 | AI236: 428354.77 | AJ236: 268047.24 | AK236: 0 | AL236: 180652.13 | AM236: 1.4217086 | AN236: 21410.59 | AO236: 15448.5 | AP236: 401614.77 | AQ236: 206430.15 | AS236: 44347 | AT236: MAYO | AU236: Positivo | AV236: 2021 | AW236: UNIVERSAL C.A. | AX236: 2.94 | AY236: 3.1
A237: 83 | B237: Universitas, C.A. Seguros | C237: 23401396 | D237: 4872389.9 | E237: 4197080.4 | F237: 4717822.1 | G237: 9784747.8 | H237: 586470 | I237: 16159724 | J237: 1111872.8 | K237: 12436943 | L237: 8239863 | M237: 7519710 | N237: 2286207.9 | O237: 11693452 | P237: -7667016.3 | Q237: -2717350 | R237: -10384366 | S237: 10970836 | T237: 27133.2 | U237: 0 | V237: 0 | W237: 1332076.6 | X237: 14324754 | Y237: 143944.27 | Z237: 316986.66 | AA237: 506135.86 | AB237: 51792.28 | AC237: 0 | AD237: 0 | AE237: 0 | AF237: 3694268.7 | AG237: 15759573 | AH237: 6483288.3 | AI237: 22234917 | AJ237: 10541465 | AK237: 0 | AL237: 3722780.7 | AM237: 1.2993324 | AN237: 2995735.3 | AO237: 1722086.8 | AP237: 15128445 | AQ237: 8292891 | AS237: 44347 | AT237: MAYO | AU237: Positivo | AV237: 2021 | AW237: UNIVERSITAS C.A. | AX237: 2.94 | AY237: 3.1
... A239: 24 | B239: Venezuela C.A., Seguros | C239: 1433202.4 | D239: 553153.17 | E239: 140369 | F239: 153479.48 | G239: 796870.81 | H239: 585010.24 | I239: 2180563.3 | J239: 3393085 | K239: 884601.64 | L239: 714598.02 | M239: 261589.28 | N239: 7655.44 | O239: 901257.75 | P239: -971558.85 | Q239: 15949.39 | R239: -955609.46 | S239: 1540619.7 | T239: 83145.33 | U239: 0 | V239: 0 | W239: 281864.37 | X239: 1796085.8 | Y239: 13150.16 | Z239: 71381.48 | AA239: 179167.73 | AB239: 5471.99 | AC239: 0 | AD239: 0 | AE239: 0 | AF239: 351304.49 | AG239: 976187.29 | AH239: 148024.44 | AI239: 1122126.5 | AJ239: 241520.75 | AK239: 20652.01 | AL239: 1295961.7 | AM239: 2.4650229 | AN239: 141667.78 | AO239: 11811.69 | AP239: 653207.44 | AQ239: 674415.98 | AS239: 44347 | AT239: MAYO | AU239: Positivo | AV239: 2021 | AW239: VENEZUELA C.A. | AX239: 2.94 | AY239: 3.1
A240: 124 | B240: Vértice, C.A Seguros | C240: 0 | D240: 0 | E240: 0 | F240: 0 | G240: 50931.4 | H240: -85431.28 | I240: 5629.54 | J240: 0 | K240: 0 | L240: 0 | M240: 0 | N240: 0 | O240: 0 | P240: -50931.4 | Q240: 0 | R240: -50931.4 | S240: -34499.88 | T240: 0 | U240: 0 | V240: 0 | W240: 0 | X240: 843.4 | Y240: 1039.42 | Z240: 9.69 | AA240: 0 | AB240: 250.4 | AC240: 0 | AD240: 0 | AE240: 0 | AF240: 34043.77 | AG240: 0 | AH240: 0 | AI240: 0 | AJ240: 0 | AK240: 0 | AL240: 5629.54 | AN240: 0 | AO240: 0 | AP240: 0 | AQ240: 0 | AS240: 44347 | AT240: MAYO | AU240: Negativo | AV240: 2021 | AW240: VÉRTICE, C.A. | AX240: 2.94 | AY240: 3.1
...

Sheet Cuadro_1
B1: REPÚBLICA BOLIVARIANA DE VENEZUELA
B2: MINISTERIO DEL PODER POPULAR DE ECONOMíA Y FINANZAS
B3: SUPERINTENDENCIA DE LA ACTIVIDAD ASEGURADORA
B4: DIRECCIÓN ACTUARIAL / ÁREA DE INVESTIGACIÓN, TRABAJOS ESPECIALES Y ESTADÍSTICAS
B6: INFORMACIÓN FINANCIERA ANALÍTICA MENSUAL DEL MERCADO ASEGURADOR VENEZOLANO
B7: ="ACUMULADA A"&" "&UPPER(J8)&" DE "&L8 -> ACUMULADA A AGOSTO DE 2025
B8: CUADRO DE RESULTADOS | I8: Mes | J8: Agosto | K8: Año | L8: 2025
B9: (En Miles de Bs.)
B10: # | C10: Empresas de Seguros | D10: Resultado Técnico Bruto (1) | E10: Resultado del Reaseguro Cedido (2) | F10: Resultado Técnico Neto (3) = (1) + (2) | G10: Resultado de la Gestión General (4) | H10: Saldo de Operaciones (5) = (3) + (4)
C11: Primas Netas Cobradas
B13: 1 | C13: Adriática de Seguros, C.A. | D13: =SUMIFS(IFM[[ResultadoTecnicoBruto]:[ResultadoTecnicoBruto]],IFM[[Nombre Empresa]:[Nombre Empresa]],$C13,IFM[[MES]:[MES]],$J$8,IFM[[AÑO]:[AÑO]],$L$8)/1000 -> 0 | E13: =SUMIFS(IFM[[ResultadodelReaseguroCedido]:[ResultadodelReaseguroCedido]],IFM[[Nombre Empresa]:[Nombre Empresa]],$C13,IFM[[MES]:[MES]],$J$8,IFM[[AÑO]:[AÑO]],$L$8)/1000 -> 0 | F13: =+D13+E13 -> 0 | G13: =SUMIFS(IFM[[ResultadodeGestionGeneral]:[ResultadodeGestionGeneral]],IFM[[Nombre Empresa]:[Nombre Empresa]],$C13,IFM[[MES]:[MES]],$J$8,IFM[[AÑO]:[AÑO]],$L$8)/1000 -> 0 | H13: =+F13+G13 -> 0
B14: 2 | C14: Altamira C.A., Seguros | D14: =SUMIFS(IFM[[ResultadoTecnicoBruto]:[ResultadoTecnicoBruto]],IFM[[Nombre Empresa]:[Nombre Empresa]],$C14,IFM[[MES]:[MES]],$J$8,IFM[[AÑO]:[AÑO]],$L$8)/1000 -> 99837.316 | E14: =SUMIFS(IFM[[ResultadodelReaseguroCedido]:[ResultadodelReaseguroCedido]],IFM[[Nombre Empresa]:[Nombre Empresa]],$C14,IFM[[MES]:[MES]],$J$8,IFM[[AÑO]:[AÑO]],$L$8)/1000 -> -37905.508 | F14: =+D14+E14 -> 61931.808 | G14: =SUMIFS(IFM[[ResultadodeGestionGeneral]:[ResultadodeGestionGeneral]],IFM[[Nombre Empresa]:[Nombre Empresa]],$C14,IFM[[MES]:[MES]],$J$8,IFM[[AÑO]:[AÑO]],$L$8)/1000 -> -61335.808 | H14: =+F14+G14 -> 595.99998
B15: 3 | C15: American International, C.A. de Seguros | D15: =SUMIFS(IFM[[ResultadoTecnicoBruto]:[ResultadoTecnicoBruto]],IFM[[Nombre Empresa]:[Nombre Empresa]],$C15,IFM[[MES]:[MES]],$J$8,IFM[[AÑO]:[AÑO]],$L$8)/1000 -> -76031.499 | E15: =SUMIFS(IFM[[ResultadodelReaseguroCedido]:[ResultadodelReaseguroCedido]],IFM[[Nombre Empresa]:[Nombre Empresa]],$C15,IFM[[MES]:[MES]],$J$8,IFM[[AÑO]:[AÑO]],$L$8)/1000 -> 6946.8243 | F15: =+D15+E15 -> -69084.674 | G15: =SUMIFS(IFM[[ResultadodeGestionGeneral]:[ResultadodeGestionGeneral]],IFM[[Nombre Empresa]:[Nombre Empresa]],$C15,IFM[[MES]:[MES]],$J$8,IFM[[AÑO]:[AÑO]],$L$8)/1000 -> 4963.4637 | H15: =+F15+G15 -> -64121.211
B16: 4 | C16: Andes C.A., Seguros | D16: =SUMIFS(IFM[[ResultadoTecnicoBruto]:[ResultadoTecnicoBruto]],IFM[[Nombre Empresa]:[Nombre Empresa]],$C16,IFM[[MES]:[MES]],$J$8,IFM[[AÑO]:[AÑO]],$L$8)/1000 -> -41158.738 | E16: =SUMIFS(IFM[[ResultadodelReaseguroCedido]:[ResultadodelReaseguroCedido]],IFM[[Nombre Empresa]:[Nombre Empresa]],$C16,IFM[[MES]:[MES]],$J$8,IFM[[AÑO]:[AÑO]],$L$8)/1000 -> -718.88787 | F16: =+D16+E16 -> -41877.625 | G16: =SUMIFS(IFM[[ResultadodeGestionGeneral]:[ResultadodeGestionGeneral]],IFM[[Nombre Empresa]:[Nombre Empresa]],$C16,IFM[[MES]:[MES]],$J$8,IFM[[AÑO]:[AÑO]],$L$8)/1000 -> 3965.5963 | H16: =+F16+G16 -> -37912.029
B17: 5 | C17: Aseguradora Nacional Unida Uniseguros, S.A. | D17: =SUMIFS(IFM[[ResultadoTecnicoBruto]:[ResultadoTecnicoBruto]],IFM[[Nombre Empresa]:[Nombre Empresa]],$C17,IFM[[MES]:[MES]],$J$8,IFM[[AÑO]:[AÑO]],$L$8)/1000 -> -15905.946 | E17: =SUMIFS(IFM[[ResultadodelReaseguroCedido]:[ResultadodelReaseguroCedido]],IFM[[Nombre Empresa]:[Nombre Empresa]],$C17,IFM[[MES]:[MES]],$J$8,IFM[[AÑO]:[AÑO]],$L$8)/1000 -> -17448.406 | F17: =+D17+E17 -> -33354.352 | G17: =SUMIFS(IFM[[ResultadodeGestionGeneral]:[ResultadodeGestionGeneral]],IFM[[Nombre Empresa]:[Nombre Empresa]],$C17,IFM[[MES]:[MES]],$J$8,IFM[[AÑO]:[AÑO]],$L$8)/1000 -> 33800.622 | H17: =+F17+G17 -> 446.26961
B18: 6 | C18: Atrio Seguros S.A. | D18: =SUMIFS(IFM[[ResultadoTecnicoBruto]:[ResultadoTecnicoBruto]],IFM[[Nombre Empresa]:[Nombre Empresa]],$C18,IFM[[MES]:[MES]],$J$8,IFM[[AÑO]:[AÑO]],$L$8)/1000 -> -1152.9353 | E18: =SUMIFS(IFM[[ResultadodelReaseguroCedido]:[ResultadodelReaseguroCedido]],IFM[[Nombre Empresa]:[Nombre Empresa]],$C18,IFM[[MES]:[MES]],$J$8,IFM[[AÑO]:[AÑO]],$L$8)/1000 -> 9106.4357 | F18: =+D18+E18 -> 7953.5004 | G18: =SUMIFS(IFM[[ResultadodeGestionGeneral]:[ResultadodeGestionGeneral]],IFM[[Nombre Empresa]:[Nombre Empresa]],$C18,IFM[[MES]:[MES]],$J$8,IFM[[AÑO]:[AÑO]],$L$8)/1000 -> -7422.1486 | H18: =+F18+G18 -> 531.35183
B19: 7 | C19: Ávila C.A., de Seguros | D19: =SUMIFS(IFM[[ResultadoTecnicoBruto]:[ResultadoTecnicoBruto]],IFM[[Nombre Empresa]:[Nombre Empresa]],$C19,IFM[[MES]:[MES]],$J$8,IFM[[AÑO]:[AÑO]],$L$8)/1000 -> 0 | E19: =SUMIFS(IFM[[ResultadodelReaseguroCedido]:[ResultadodelReaseguroCedido]],IFM[[Nombre Empresa]:[Nombre Empresa]],$C19,IFM[[MES]:[MES]],$J$8,IFM[[AÑO]:[AÑO]],$L$8)/1000 -> 0 | F19: =+D19+E19 -> 0 | G19: =SUMIFS(IFM[[ResultadodeGestionGeneral]:[ResultadodeGestionGeneral]],IFM[[Nombre Empresa]:[Nombre Empresa]],$C19,IFM[[MES]:[MES]],$J$8,IFM[[AÑO]:[AÑO]],$L$8)/1000 -> 0 | H19: =+F19+G19 -> 0
B20: 8 | C20: Banesco Seguros C.A. | D20: =SUMIFS(IFM[[ResultadoTecnicoBruto]:[ResultadoTecnicoBruto]],IFM[[Nombre Empresa]:[Nombre Empresa]],$C20,IFM[[MES]:[MES]],$J$8,IFM[[AÑO]:[AÑO]],$L$8)/1000 -> 198086.65 | E20: =SUMIFS(IFM[[ResultadodelReaseguroCedido]:[ResultadodelReaseguroCedido]],IFM[[Nombre Empresa]:[Nombre Empresa]],$C20,IFM[[MES]:[MES]],$J$8,IFM[[AÑO]:[AÑO]],$L$8)/1000 -> -104975.64 | F20: =+D20+E20 -> 93111.014 | G20: =SUMIFS(IFM[[ResultadodeGestionGeneral]:[ResultadodeGestionGeneral]],IFM[[Nombre Empresa]:[Nombre Empresa]],$C20,IFM[[MES]:[MES]],$J$8,IFM[[AÑO]:[AÑO]],$L$8)/1000 -> 769269.41 | H20: =+F20+G20 -> 862380.42
B21: 9 | C21: BBVA Seguros,C.A. | D21: =SUMIFS(IFM[[ResultadoTecnicoBruto]:[ResultadoTecnicoBruto]],IFM[[Nombre Empresa]:[Nombre Empresa]],$C21,IFM[[MES]:[MES]],$J$8,IFM[[AÑO]:[AÑO]],$L$8)/1000 -> -9339.3269 | E21: =SUMIFS(IFM[[ResultadodelReaseguroCedido]:[ResultadodelReaseguroCedido]],IFM[[Nombre Empresa]:[Nombre Empresa]],$C21,IFM[[MES]:[MES]],$J$8,IFM[[AÑO]:[AÑO]],$L$8)/1000 -> -158.75959 | F21: =+D21+E21 -> -9498.0865 | G21: =SUMIFS(IFM[[ResultadodeGestionGeneral]:[ResultadodeGestionGeneral]],IFM[[Nombre Empresa]:[Nombre Empresa]],$C21,IFM[[MES]:[MES]],$J$8,IFM[[AÑO]:[AÑO]],$L$8)/1000 -> 298920.74 | H21: =+F21+G21 -> 289422.65
B22: 10 | C22: Bolivariana de Seguros y Reaseguros, S.A. | D22: =SUMIFS(IFM[[ResultadoTecnicoBruto]:[ResultadoTecnicoBruto]],IFM[[Nombre Empresa]:[Nombre Empresa]],$C22,IFM[[MES]:[MES]],$J$8,IFM[[AÑO]:[AÑO]],$L$8)/1000 -> 1182.1549 | E22: =SUMIFS(IFM[[ResultadodelReaseguroCedido]:[ResultadodelReaseguroCedido]],IFM[[Nombre Empresa]:[Nombre Empresa]],$C22,IFM[[MES]:[MES]],$J$8,IFM[[AÑO]:[AÑO]],$L$8)/1000 -> -1271.4396 | F22: =+D22+E22 -> -89.28468 | G22: =SUMIFS(IFM[[ResultadodeGestionGeneral]:[ResultadodeGestionGeneral]],IFM[[Nombre Empresa]:[Nombre Empresa]],$C22,IFM[[MES]:[MES]],$J$8,IFM[[AÑO]:[AÑO]],$L$8)/1000 -> 2492.5392 | H22: =+F22+G22 -> 2403.2545
B23: 11 | C23: Capital, C.A. Seguros | D23: =SUMIFS(IFM[[ResultadoTecnicoBruto]:[ResultadoTecnicoBruto]],IFM[[Nombre Empresa]:[Nombre Empresa]],$C23,IFM[[MES]:[MES]],$J$8,IFM[[AÑO]:[AÑO]],$L$8)/1000 -> 1191697.9 | E23: =SUMIFS(IFM[[ResultadodelReaseguroCedido]:[ResultadodelReaseguroCedido]],IFM[[Nombre Empresa]:[Nombre Empresa]],$C23,IFM[[MES]:[MES]],$J$8,IFM[[AÑO]:[AÑO]],$L$8)/1000 -> -1190020.6 | F23: =+D23+E23 -> 1677.2486 | G23: =SUMIFS(IFM[[ResultadodeGestionGeneral]:[ResultadodeGestionGeneral]],IFM[[Nombre Empresa]:[Nombre Empresa]],$C23,IFM[[MES]:[MES]],$J$8,IFM[[AÑO]:[AÑO]],$L$8)/1000 -> 1801.3056 | H23: =+F23+G23 -> 3478.5542
B24: 12 | C24: Carabobo C.A., Seguros | D24: =SUMIFS(IFM[[ResultadoTecnicoBruto]:[ResultadoTecnicoBruto]],IFM[[Nombre Empresa]:[Nombre Empresa]],$C24,IFM[[MES]:[MES]],$J$8,IFM[[AÑO]:[AÑO]],$L$8)/1000 -> 0 | E24: =SUMIFS(IFM[[ResultadodelReaseguroCedido]:[ResultadodelReaseguroCedido]],IFM[[Nombre Empresa]:[Nombre Empresa]],$C24,IFM[[MES]:[MES]],$J$8,IFM[[AÑO]:[AÑO]],$L$8)/1000 -> 0 | F24: =+D24+E24 -> 0 | G24: =SUMIFS(IFM[[ResultadodeGestionGeneral]:[ResultadodeGestionGeneral]],IFM[[Nombre Empresa]:[Nombre Empresa]],$C24,IFM[[MES]:[MES]],$J$8,IFM[[AÑO]:[AÑO]],$L$8)/1000 -> 0 | H24: =+F24+G24 -> 0
... B63: 51 | C63: Zuma Seguros, C.A. | D63: =SUMIFS(IFM[[ResultadoTecnicoBruto]:[ResultadoTecnicoBruto]],IFM[[Nombre Empresa]:[Nombre Empresa]],$C63,IFM[[MES]:[MES]],$J$8,IFM[[AÑO]:[AÑO]],$L$8)/1000 -> -48686.512 | E63: =SUMIFS(IFM[[ResultadodelReaseguroCedido]:[ResultadodelReaseguroCedido]],IFM[[Nombre Empresa]:[Nombre Empresa]],$C63,IFM[[MES]:[MES]],$J$8,IFM[[AÑO]:[AÑO]],$L$8)/1000 -> -3438.8231 | F63: =+D63+E63 -> -52125.336 | G63: =SUMIFS(IFM[[ResultadodeGestionGeneral]:[ResultadodeGestionGeneral]],IFM[[Nombre Empresa]:[Nombre Empresa]],$C63,IFM[[MES]:[MES]],$J$8,IFM[[AÑO]:[AÑO]],$L$8)/1000 -> 14232.579 | H63: =+F63+G63 -> -37892.757
C64: TOTAL (En Miles de Bs.) | D64: =SUM(D13:D63) -> -2086969.9 | E64: =SUM(E13:E63) -> -2797256.3 | F64: =SUM(F13:F63) -> -4884226.3 | G64: =SUM(G13:G63) -> 7350269.8 | H64: =SUM(H13:H63) -> 2466043.5
C66: Fuente: (SEFA) Estados Financieros Analíticos Mensuales. Empresas de Seguros. | H66: Actualizado: 09/07/2025
C67: 1/ A la fecha han consignado los estados financieros analiticos 43 empresas de seguros. 2/ Faltan por procesar los estados financieros analiticos las siguientes empresas: Adriática de Seguros, C.A., Ávila de Seguros C.A., Bolivariana de Seguros y Reaseguros, S.A., Seguros Guayana, Multinacional de Seguros C.A., Interbank Seguros S.A, La Regional C.A., y Seguros Carabobo C.A.
C69: (1) Es el proveniente de la operación técnica del seguro, sin considerar el resultado del reaseguro cedido ni las operaciones de la gestión financiera y resulta de la diferencia entre todos los ingresos de carácter técnico y los egresos por este mismo concepto, sin contemplar las cuentas del reaseguro cedido. Si el resultado es negativo, existe pérdida técnica bruta; caso contrario, existirá utilidad técnica bruta. (2) Es el proveniente de las operaciones de reaseguro cedido efectuadas por la empresa aseguradora y resulta de la diferencia entre los ingresos por reaseguro cedido y los egresos por este mismo concepto. Si los egresos de la empresa por reaseguro cedido son mayores que sus respectivos ingresos, el resultado tendrá saldo negativo; caso contrario el resultado tendrá saldo positivo. (3) Es el proveniente del ejercicio de la actividad aseguradora propiamente dicha, considerando el resultado del reaseguro cedido pero sin incluir las operaciones de la gestión financiera. Resulta de la diferencia entre todos los ingresos de carácter técnico y los egresos por este mismo concepto, incluyendo las operaciones del reaseguro cedido. Constituye también la suma entre el Resultado Técnico Bruto y el Resultado del Reaseguro Cedido. Si el resultado es negativo, existe pérdida técnica neta; caso contrario, existirá utilidad técnica neta. (4) Es el proveniente de las operaciones de la gestión financiera de la empresa aseguradora y resulta de la diferencia entre los ingresos de la gestión general y los egresos por este mismo concepto. Si los ingresos de la empresa por gestión general son menores que sus respectivos egresos, existirá pérdida financiera; caso contrario, existirá utilidad financiera. (5) Es el saldo positivo o negativo que resulta de todas las operaciones de la empresa de seguros al final del periodo evaluado. Resulta de sumar el Resultado Técnico Neto y el Resultado de la Gestión General, obteniéndose el Saldo de Operaciones Positivo o Negativo (Utilidad o Pérdida) de la empresa. Se le llama Resultado del Ejercicio toda vez que refleja el resultado de las operaciones de la empresa al cierre de cada mes del año en estudio.
C71: INFORMACIÓN PRELIMINAR NO AUDITADA POR LA SUPERINTENDENCIA DE LA ACTIVIDAD ASEGURADORA

Sheet Cuadro_2
B1: REPÚBLICA BOLIVARIANA DE VENEZUELA
B2: MINISTERIO DEL PODER POPULAR DE ECONOMíA Y FINANZAS
B3: SUPERINTENDENCIA DE LA ACTIVIDAD ASEGURADORA
B4: DIRECCIÓN ACTUARIAL / ÁREA DE INVESTIGACIÓN, TRABAJOS ESPECIALES Y ESTADÍSTICAS
B6: RESUMEN DE LA INFORMACIÓN FINANCIERA ANALÍTICA MENSUAL DEL MERCADO ASEGURADOR VENEZOLANO
B7: =+Cuadro_1!B7 -> ACUMULADA A AGOSTO DE 2025
B8: (En Miles de Bs.)
B9: # | C9: Empresas de Seguros | D9: Primas Netas Cobradas (1) | E9: Siniestros Pagados (Netos de Salvamento) (2) | F9: Reservas para Prestaciones y Siniestros Pendientes Brutas (3) | G9: Reservas para Prestaciones y Siniestros Pendientes (Netas de Reaseguradores Inscritos) (4) | H9: Siniestros Totales ( 2 + 3 ) (5) | I9: Comisiones (6) | J9: Gastos de Adquisición (7) | K9: Gastos de Administración (8)
A10: =+D10 -> 0 | B10: 1 | C10: Adriática de Seguros, C.A. | D10: =SUMIFS(IFM[[PrimasNetasCobradas]:[PrimasNetasCobradas]],IFM[[Nombre Empresa]:[Nombre Empresa]],$C10,IFM[[MES]:[MES]],Cuadro_1!$J$8,IFM[[AÑO]:[AÑO]],Cuadro_1!$L$8)/1000 -> 0 | E10: =SUMIFS(IFM[[SiniestrosPagados_NetosdeSalvamento]:[SiniestrosPagados_NetosdeSalvamento]],IFM[[Nombre Empresa]:[Nombre Empresa]],$C10,IFM[[MES]:[MES]],Cuadro_1!$J$8,IFM[[AÑO]:[AÑO]],Cuadro_1!$L$8)/1000 -> 0 | F10: =SUMIFS(IFM[[ReservasdeSiniestrosPendientesBrutas]:[ReservasdeSiniestrosPendientesBrutas]],IFM[[Nombre Empresa]:[Nombre Empresa]],$C10,IFM[[MES]:[MES]],Cuadro_1!$J$8,IFM[[AÑO]:[AÑO]],Cuadro_1!$L$8)/1000 -> 0 | G10: =SUMIFS(IFM[[SiniestrosPendientes]:[SiniestrosPendientes]],IFM[[Nombre Empresa]:[Nombre Empresa]],$C10,IFM[[MES]:[MES]],Cuadro_1!$J$8,IFM[[AÑO]:[AÑO]],Cuadro_1!$L$8)/1000 -> 0 | H10: =+E10+F10 -> 0 | I10: =SUMIFS(IFM[[Comisiones]:[Comisiones]],IFM[[Nombre Empresa]:[Nombre Empresa]],$C10,IFM[[MES]:[MES]],Cuadro_1!$J$8,IFM[[AÑO]:[AÑO]],Cuadro_1!$L$8)/1000 -> 0 | J10: =SUMIFS(IFM[[GastosdeAdquision]:[GastosdeAdquision]],IFM[[Nombre Empresa]:[Nombre Empresa]],$C10,IFM[[MES]:[MES]],Cuadro_1!$J$8,IFM[[AÑO]:[AÑO]],Cuadro_1!$L$8)/1000 -> 0 | K10: =SUMIFS(IFM[[Gastosdeadministracion]:[Gastosdeadministracion]],IFM[[Nombre Empresa]:[Nombre Empresa]],$C10,IFM[[MES]:[MES]],Cuadro_1!$J$8,IFM[[AÑO]:[AÑO]],Cuadro_1!$L$8)/1000 -> 0
A11: =+D11 -> 935942.49 | B11: 2 | C11: Altamira C.A., Seguros | D11: =SUMIFS(IFM[[PrimasNetasCobradas]:[PrimasNetasCobradas]],IFM[[Nombre Empresa]:[Nombre Empresa]],$C11,IFM[[MES]:[MES]],Cuadro_1!$J$8,IFM[[AÑO]:[AÑO]],Cuadro_1!$L$8)/1000 -> 935942.49 | E11: =SUMIFS(IFM[[SiniestrosPagados_NetosdeSalvamento]:[SiniestrosPagados_NetosdeSalvamento]],IFM[[Nombre Empresa]:[Nombre Empresa]],$C11,IFM[[MES]:[MES]],Cuadro_1!$J$8,IFM[[AÑO]:[AÑO]],Cuadro_1!$L$8)/1000 -> 188094.14 | F11: =SUMIFS(IFM[[ReservasdeSiniestrosPendientesBrutas]:[ReservasdeSiniestrosPendientesBrutas]],IFM[[Nombre Empresa]:[Nombre Empresa]],$C11,IFM[[MES]:[MES]],Cuadro_1!$J$8,IFM[[AÑO]:[AÑO]],Cuadro_1!$L$8)/1000 -> 273280.78 | G11: =SUMIFS(IFM[[SiniestrosPendientes]:[SiniestrosPendientes]],IFM[[Nombre Empresa]:[Nombre Empresa]],$C11,IFM[[MES]:[MES]],Cuadro_1!$J$8,IFM[[AÑO]:[AÑO]],Cuadro_1!$L$8)/1000 -> 50745.732 | H11: =+E11+F11 -> 461374.92 | I11: =SUMIFS(IFM[[Comisiones]:[Comisiones]],IFM[[Nombre Empresa]:[Nombre Empresa]],$C11,IFM[[MES]:[MES]],Cuadro_1!$J$8,IFM[[AÑO]:[AÑO]],Cuadro_1!$L$8)/1000 -> 44119.99 | J11: =SUMIFS(IFM[[GastosdeAdquision]:[GastosdeAdquision]],IFM[[Nombre Empresa]:[Nombre Empresa]],$C11,IFM[[MES]:[MES]],Cuadro_1!$J$8,IFM[[AÑO]:[AÑO]],Cuadro_1!$L$8)/1000 -> 94248.242 | K11: =SUMIFS(IFM[[Gastosdeadministracion]:[Gastosdeadministracion]],IFM[[Nombre Empresa]:[Nombre Empresa]],$C11,IFM[[MES]:[MES]],Cuadro_1!$J$8,IFM[[AÑO]:[AÑO]],Cuadro_1!$L$8)/1000 -> 350655.41
A12: =+D12 -> 18956.308 | B12: 3 | C12: American International, C.A. de Seguros | D12: =SUMIFS(IFM[[PrimasNetasCobradas]:[PrimasNetasCobradas]],IFM[[Nombre Empresa]:[Nombre Empresa]],$C12,IFM[[MES]:[MES]],Cuadro_1!$J$8,IFM[[AÑO]:[AÑO]],Cuadro_1!$L$8)/1000 -> 18956.308 | E12: =SUMIFS(IFM[[SiniestrosPagados_NetosdeSalvamento]:[SiniestrosPagados_NetosdeSalvamento]],IFM[[Nombre Empresa]:[Nombre Empresa]],$C12,IFM[[MES]:[MES]],Cuadro_1!$J$8,IFM[[AÑO]:[AÑO]],Cuadro_1!$L$8)/1000 -> 27305.047 | F12: =SUMIFS(IFM[[ReservasdeSiniestrosPendientesBrutas]:[ReservasdeSiniestrosPendientesBrutas]],IFM[[Nombre Empresa]:[Nombre Empresa]],$C12,IFM[[MES]:[MES]],Cuadro_1!$J$8,IFM[[AÑO]:[AÑO]],Cuadro_1!$L$8)/1000 -> 2728.2512 | G12: =SUMIFS(IFM[[SiniestrosPendientes]:[SiniestrosPendientes]],IFM[[Nombre Empresa]:[Nombre Empresa]],$C12,IFM[[MES]:[MES]],Cuadro_1!$J$8,IFM[[AÑO]:[AÑO]],Cuadro_1!$L$8)/1000 -> 0.64086 | H12: =+E12+F12 -> 30033.298 | I12: =SUMIFS(IFM[[Comisiones]:[Comisiones]],IFM[[Nombre Empresa]:[Nombre Empresa]],$C12,IFM[[MES]:[MES]],Cuadro_1!$J$8,IFM[[AÑO]:[AÑO]],Cuadro_1!$L$8)/1000 -> 1528.7746 | J12: =SUMIFS(IFM[[GastosdeAdquision]:[GastosdeAdquision]],IFM[[Nombre Empresa]:[Nombre Empresa]],$C12,IFM[[MES]:[MES]],Cuadro_1!$J$8,IFM[[AÑO]:[AÑO]],Cuadro_1!$L$8)/1000 -> 0 | K12: =SUMIFS(IFM[[Gastosdeadministracion]:[Gastosdeadministracion]],IFM[[Nombre Empresa]:[Nombre Empresa]],$C12,IFM[[MES]:[MES]],Cuadro_1!$J$8,IFM[[AÑO]:[AÑO]],Cuadro_1!$L$8)/1000 -> 66352.154
A13: =+D13 -> 100359.11 | B13: 4 | C13: Andes C.A., Seguros | D13: =SUMIFS(IFM[[PrimasNetasCobradas]:[PrimasNetasCobradas]],IFM[[Nombre Empresa]:[Nombre Empresa]],$C13,IFM[[MES]:[MES]],Cuadro_1!$J$8,IFM[[AÑO]:[AÑO]],Cuadro_1!$L$8)/1000 -> 100359.11 | E13: =SUMIFS(IFM[[SiniestrosPagados_NetosdeSalvamento]:[SiniestrosPagados_NetosdeSalvamento]],IFM[[Nombre Empresa]:[Nombre Empresa]],$C13,IFM[[MES]:[MES]],Cuadro_1!$J$8,IFM[[AÑO]:[AÑO]],Cuadro_1!$L$8)/1000 -> 10818.564 | F13: =SUMIFS(IFM[[ReservasdeSiniestrosPendientesBrutas]:[ReservasdeSiniestrosPendientesBrutas]],IFM[[Nombre Empresa]:[Nombre Empresa]],$C13,IFM[[MES]:[MES]],Cuadro_1!$J$8,IFM[[AÑO]:[AÑO]],Cuadro_1!$L$8)/1000 -> 15098.06 | G13: =SUMIFS(IFM[[SiniestrosPendientes]:[SiniestrosPendientes]],IFM[[Nombre Empresa]:[Nombre Empresa]],$C13,IFM[[MES]:[MES]],Cuadro_1!$J$8,IFM[[AÑO]:[AÑO]],Cuadro_1!$L$8)/1000 -> 15098.06 | H13: =+E13+F13 -> 25916.624 | I13: =SUMIFS(IFM[[Comisiones]:[Comisiones]],IFM[[Nombre Empresa]:[Nombre Empresa]],$C13,IFM[[MES]:[MES]],Cuadro_1!$J$8,IFM[[AÑO]:[AÑO]],Cuadro_1!$L$8)/1000 -> 11083.146 | J13: =SUMIFS(IFM[[GastosdeAdquision]:[GastosdeAdquision]],IFM[[Nombre Empresa]:[Nombre Empresa]],$C13,IFM[[MES]:[MES]],Cuadro_1!$J$8,IFM[[AÑO]:[AÑO]],Cuadro_1!$L$8)/1000 -> 8539.0285 | K13: =SUMIFS(IFM[[Gastosdeadministracion]:[Gastosdeadministracion]],IFM[[Nombre Empresa]:[Nombre Empresa]],$C13,IFM[[MES]:[MES]],Cuadro_1!$J$8,IFM[[AÑO]:[AÑO]],Cuadro_1!$L$8)/1000 -> 72529.982
A14: =+D14 -> 74294.113 | B14: 5 | C14: Aseguradora Nacional Unida Uniseguros, S.A. | D14: =SUMIFS(IFM[[PrimasNetasCobradas]:[PrimasNetasCobradas]],IFM[[Nombre Empresa]:[Nombre Empresa]],$C14,IFM[[MES]:[MES]],Cuadro_1!$J$8,IFM[[AÑO]:[AÑO]],Cuadro_1!$L$8)/1000 -> 74294.113 | E14: =SUMIFS(IFM[[SiniestrosPagados_NetosdeSalvamento]:[SiniestrosPagados_NetosdeSalvamento]],IFM[[Nombre Empresa]:[Nombre Empresa]],$C14,IFM[[MES]:[MES]],Cuadro_1!$J$8,IFM[[AÑO]:[AÑO]],Cuadro_1!$L$8)/1000 -> 17148.987 | F14: =SUMIFS(IFM[[ReservasdeSiniestrosPendientesBrutas]:[ReservasdeSiniestrosPendientesBrutas]],IFM[[Nombre Empresa]:[Nombre Empresa]],$C14,IFM[[MES]:[MES]],Cuadro_1!$J$8,IFM[[AÑO]:[AÑO]],Cuadro_1!$L$8)/1000 -> 10935.352 | G14: =SUMIFS(IFM[[SiniestrosPendientes]:[SiniestrosPendientes]],IFM[[Nombre Empresa]:[Nombre Empresa]],$C14,IFM[[MES]:[MES]],Cuadro_1!$J$8,IFM[[AÑO]:[AÑO]],Cuadro_1!$L$8)/1000 -> 1418.4021 | H14: =+E14+F14 -> 28084.338 | I14: =SUMIFS(IFM[[Comisiones]:[Comisiones]],IFM[[Nombre Empresa]:[Nombre Empresa]],$C14,IFM[[MES]:[MES]],Cuadro_1!$J$8,IFM[[AÑO]:[AÑO]],Cuadro_1!$L$8)/1000 -> 8348.5602 | J14: =SUMIFS(IFM[[GastosdeAdquision]:[GastosdeAdquision]],IFM[[Nombre Empresa]:[Nombre Empresa]],$C14,IFM[[MES]:[MES]],Cuadro_1!$J$8,IFM[[AÑO]:[AÑO]],Cuadro_1!$L$8)/1000 -> 9040.4409 | K14: =SUMIFS(IFM[[Gastosdeadministracion]:[Gastosdeadministracion]],IFM[[Nombre Empresa]:[Nombre Empresa]],$C14,IFM[[MES]:[MES]],Cuadro_1!$J$8,IFM[[AÑO]:[AÑO]],Cuadro_1!$L$8)/1000 -> 46304.778
A15: =+D15 -> 217229.65 | B15: 6 | C15: Atrio Seguros S.A. | D15: =SUMIFS(IFM[[PrimasNetasCobradas]:[PrimasNetasCobradas]],IFM[[Nombre Empresa]:[Nombre Empresa]],$C15,IFM[[MES]:[MES]],Cuadro_1!$J$8,IFM[[AÑO]:[AÑO]],Cuadro_1!$L$8)/1000 -> 217229.65 | E15: =SUMIFS(IFM[[SiniestrosPagados_NetosdeSalvamento]:[SiniestrosPagados_NetosdeSalvamento]],IFM[[Nombre Empresa]:[Nombre Empresa]],$C15,IFM[[MES]:[MES]],Cuadro_1!$J$8,IFM[[AÑO]:[AÑO]],Cuadro_1!$L$8)/1000 -> 41051.31 | F15: =SUMIFS(IFM[[ReservasdeSiniestrosPendientesBrutas]:[ReservasdeSiniestrosPendientesBrutas]],IFM[[Nombre Empresa]:[Nombre Empresa]],$C15,IFM[[MES]:[MES]],Cuadro_1!$J$8,IFM[[AÑO]:[AÑO]],Cuadro_1!$L$8)/1000 -> 35272.619 | G15: =SUMIFS(IFM[[SiniestrosPendientes]:[SiniestrosPendientes]],IFM[[Nombre Empresa]:[Nombre Empresa]],$C15,IFM[[MES]:[MES]],Cuadro_1!$J$8,IFM[[AÑO]:[AÑO]],Cuadro_1!$L$8)/1000 -> 24144.992 | H15: =+E15+F15 -> 76323.93 | I15: =SUMIFS(IFM[[Comisiones]:[Comisiones]],IFM[[Nombre Empresa]:[Nombre Empresa]],$C15,IFM[[MES]:[MES]],Cuadro_1!$J$8,IFM[[AÑO]:[AÑO]],Cuadro_1!$L$8)/1000 -> 27942.193 | J15: =SUMIFS(IFM[[GastosdeAdquision]:[GastosdeAdquision]],IFM[[Nombre Empresa]:[Nombre Empresa]],$C15,IFM[[MES]:[MES]],Cuadro_1!$J$8,IFM[[AÑO]:[AÑO]],Cuadro_1!$L$8)/1000 -> 16002.289 | K15: =SUMIFS(IFM[[Gastosdeadministracion]:[Gastosdeadministracion]],IFM[[Nombre Empresa]:[Nombre Empresa]],$C15,IFM[[MES]:[MES]],Cuadro_1!$J$8,IFM[[AÑO]:[AÑO]],Cuadro_1!$L$8)/1000 -> 84569.755
A16: =+D16 -> 0 | B16: 7 | C16: Ávila C.A., de Seguros | D16: =SUMIFS(IFM[[PrimasNetasCobradas]:[PrimasNetasCobradas]],IFM[[Nombre Empresa]:[Nombre Empresa]],$C16,IFM[[MES]:[MES]],Cuadro_1!$J$8,IFM[[AÑO]:[AÑO]],Cuadro_1!$L$8)/1000 -> 0 | E16: =SUMIFS(IFM[[SiniestrosPagados_NetosdeSalvamento]:[SiniestrosPagados_NetosdeSalvamento]],IFM[[Nombre Empresa]:[Nombre Empresa]],$C16,IFM[[MES]:[MES]],Cuadro_1!$J$8,IFM[[AÑO]:[AÑO]],Cuadro_1!$L$8)/1000 -> 0 | F16: =SUMIFS(IFM[[ReservasdeSiniestrosPendientesBrutas]:[ReservasdeSiniestrosPendientesBrutas]],IFM[[Nombre Empresa]:[Nombre Empresa]],$C16,IFM[[MES]:[MES]],Cuadro_1!$J$8,IFM[[AÑO]:[AÑO]],Cuadro_1!$L$8)/1000 -> 0 | G16: =SUMIFS(IFM[[SiniestrosPendientes]:[SiniestrosPendientes]],IFM[[Nombre Empresa]:[Nombre Empresa]],$C16,IFM[[MES]:[MES]],Cuadro_1!$J$8,IFM[[AÑO]:[AÑO]],Cuadro_1!$L$8)/1000 -> 0 | H16: =+E16+F16 -> 0 | I16: =SUMIFS(IFM[[Comisiones]:[Comisiones]],IFM[[Nombre Empresa]:[Nombre Empresa]],$C16,IFM[[MES]:[MES]],Cuadro_1!$J$8,IFM[[AÑO]:[AÑO]],Cuadro_1!$L$8)/1000 -> 0 | J16: =SUMIFS(IFM[[GastosdeAdquision]:[GastosdeAdquision]],IFM[[Nombre Empresa]:[Nombre Empresa]],$C16,IFM[[MES]:[MES]],Cuadro_1!$J$8,IFM[[AÑO]:[AÑO]],Cuadro_1!$L$8)/1000 -> 0 | K16: =SUMIFS(IFM[[Gastosdeadministracion]:[Gastosdeadministracion]],IFM[[Nombre Empresa]:[Nombre Empresa]],$C16,IFM[[MES]:[MES]],Cuadro_1!$J$8,IFM[[AÑO]:[AÑO]],Cuadro_1!$L$8)/1000 -> 0
A17: =+D17 -> 1408959.8 | B17: 8 | C17: Banesco Seguros C.A. | D17: =SUMIFS(IFM[[PrimasNetasCobradas]:[PrimasNetasCobradas]],IFM[[Nombre Empresa]:[Nombre Empresa]],$C17,IFM[[MES]:[MES]],Cuadro_1!$J$8,IFM[[AÑO]:[AÑO]],Cuadro_1!$L$8)/1000 -> 1408959.8 | E17: =SUMIFS(IFM[[SiniestrosPagados_NetosdeSalvamento]:[SiniestrosPagados_NetosdeSalvamento]],IFM[[Nombre Empresa]:[Nombre Empresa]],$C17,IFM[[MES]:[MES]],Cuadro_1!$J$8,IFM[[AÑO]:[AÑO]],Cuadro_1!$L$8)/1000 -> 386450.89 | F17: =SUMIFS(IFM[[ReservasdeSiniestrosPendientesBrutas]:[ReservasdeSiniestrosPendientesBrutas]],IFM[[Nombre Empresa]:[Nombre Empresa]],$C17,IFM[[MES]:[MES]],Cuadro_1!$J$8,IFM[[AÑO]:[AÑO]],Cuadro_1!$L$8)/1000 -> 162821.98 | G17: =SUMIFS(IFM[[SiniestrosPendientes]:[SiniestrosPendientes]],IFM[[Nombre Empresa]:[Nombre Empresa]],$C17,IFM[[MES]:[MES]],Cuadro_1!$J$8,IFM[[AÑO]:[AÑO]],Cuadro_1!$L$8)/1000 -> 162821.94 | H17: =+E17+F17 -> 549272.87 | I17: =SUMIFS(IFM[[Comisiones]:[Comisiones]],IFM[[Nombre Empresa]:[Nombre Empresa]],$C17,IFM[[MES]:[MES]],Cuadro_1!$J$8,IFM[[AÑO]:[AÑO]],Cuadro_1!$L$8)/1000 -> 134974.12 | J17: =SUMIFS(IFM[[GastosdeAdquision]:[GastosdeAdquision]],IFM[[Nombre Empresa]:[Nombre Empresa]],$C17,IFM[[MES]:[MES]],Cuadro_1!$J$8,IFM[[AÑO]:[AÑO]],Cuadro_1!$L$8)/1000 -> 43396.879 | K17: =SUMIFS(IFM[[Gastosdeadministracion]:[Gastosdeadministracion]],IFM[[Nombre Empresa]:[Nombre Empresa]],$C17,IFM[[MES]:[MES]],Cuadro_1!$J$8,IFM[[AÑO]:[AÑO]],Cuadro_1!$L$8)/1000 -> 391681.86
A18: =+D18 -> 88404.835 | B18: 9 | C18: BBVA Seguros,C.A. | D18: =SUMIFS(IFM[[PrimasNetasCobradas]:[PrimasNetasCobradas]],IFM[[Nombre Empresa]:[Nombre Empresa]],$C18,IFM[[MES]:[MES]],Cuadro_1!$J$8,IFM[[AÑO]:[AÑO]],Cuadro_1!$L$8)/1000 -> 88404.835 | E18: =SUMIFS(IFM[[SiniestrosPagados_NetosdeSalvamento]:[SiniestrosPagados_NetosdeSalvamento]],IFM[[Nombre Empresa]:[Nombre Empresa]],$C18,IFM[[MES]:[MES]],Cuadro_1!$J$8,IFM[[AÑO]:[AÑO]],Cuadro_1!$L$8)/1000 -> 20588.473 | F18: =SUMIFS(IFM[[ReservasdeSiniestrosPendientesBrutas]:[ReservasdeSiniestrosPendientesBrutas]],IFM[[Nombre Empresa]:[Nombre Empresa]],$C18,IFM[[MES]:[MES]],Cuadro_1!$J$8,IFM[[AÑO]:[AÑO]],Cuadro_1!$L$8)/1000 -> 2515.952 | G18: =SUMIFS(IFM[[SiniestrosPendientes]:[SiniestrosPendientes]],IFM[[Nombre Empresa]:[Nombre Empresa]],$C18,IFM[[MES]:[MES]],Cuadro_1!$J$8,IFM[[AÑO]:[AÑO]],Cuadro_1!$L$8)/1000 -> 2515.952 | H18: =+E18+F18 -> 23104.425 | I18: =SUMIFS(IFM[[Comisiones]:[Comisiones]],IFM[[Nombre Empresa]:[Nombre Empresa]],$C18,IFM[[MES]:[MES]],Cuadro_1!$J$8,IFM[[AÑO]:[AÑO]],Cuadro_1!$L$8)/1000 -> 0 | J18: =SUMIFS(IFM[[GastosdeAdquision]:[GastosdeAdquision]],IFM[[Nombre Empresa]:[Nombre Empresa]],$C18,IFM[[MES]:[MES]],Cuadro_1!$J$8,IFM[[AÑO]:[AÑO]],Cuadro_1!$L$8)/1000 -> 0 | K18: =SUMIFS(IFM[[Gastosdeadministracion]:[Gastosdeadministracion]],IFM[[Nombre Empresa]:[Nombre Empresa]],$C18,IFM[[MES]:[MES]],Cuadro_1!$J$8,IFM[[AÑO]:[AÑO]],Cuadro_1!$L$8)/1000 -> 67525.167
A19: =+D19 -> 3139.5409 | B19: 10 | C19: Bolivariana de Seguros y Reaseguros, S.A. | D19: =SUMIFS(IFM[[PrimasNetasCobradas]:[PrimasNetasCobradas]],IFM[[Nombre Empresa]:[Nombre Empresa]],$C19,IFM[[MES]:[MES]],Cuadro_1!$J$8,IFM[[AÑO]:[AÑO]],Cuadro_1!$L$8)/1000 -> 3139.5409 | E19: =SUMIFS(IFM[[SiniestrosPagados_NetosdeSalvamento]:[SiniestrosPagados_NetosdeSalvamento]],IFM[[Nombre Empresa]:[Nombre Empresa]],$C19,IFM[[MES]:[MES]],Cuadro_1!$J$8,IFM[[AÑO]:[AÑO]],Cuadro_1!$L$8)/1000 -> 0 | F19: =SUMIFS(IFM[[ReservasdeSiniestrosPendientesBrutas]:[ReservasdeSiniestrosPendientesBrutas]],IFM[[Nombre Empresa]:[Nombre Empresa]],$C19,IFM[[MES]:[MES]],Cuadro_1!$J$8,IFM[[AÑO]:[AÑO]],Cuadro_1!$L$8)/1000 -> 0.06961 | G19: =SUMIFS(IFM[[SiniestrosPendientes]:[SiniestrosPendientes]],IFM[[Nombre Empresa]:[Nombre Empresa]],$C19,IFM[[MES]:[MES]],Cuadro_1!$J$8,IFM[[AÑO]:[AÑO]],Cuadro_1!$L$8)/1000 -> 0.06961 | H19: =+E19+F19 -> 0.06961 | I19: =SUMIFS(IFM[[Comisiones]:[Comisiones]],IFM[[Nombre Empresa]:[Nombre Empresa]],$C19,IFM[[MES]:[MES]],Cuadro_1!$J$8,IFM[[AÑO]:[AÑO]],Cuadro_1!$L$8)/1000 -> 0 | J19: =SUMIFS(IFM[[GastosdeAdquision]:[GastosdeAdquision]],IFM[[Nombre Empresa]:[Nombre Empresa]],$C19,IFM[[MES]:[MES]],Cuadro_1!$J$8,IFM[[AÑO]:[AÑO]],Cuadro_1!$L$8)/1000 -> 0 | K19: =SUMIFS(IFM[[Gastosdeadministracion]:[Gastosdeadministracion]],IFM[[Nombre Empresa]:[Nombre Empresa]],$C19,IFM[[MES]:[MES]],Cuadro_1!$J$8,IFM[[AÑO]:[AÑO]],Cuadro_1!$L$8)/1000 -> 924.5732
A20: =+D20 -> 749200.81 | B20: 11 | C20: Capital, C.A. Seguros | D20: =SUMIFS(IFM[[PrimasNetasCobradas]:[PrimasNetasCobradas]],IFM[[Nombre Empresa]:[Nombre Empresa]],$C20,IFM[[MES]:[MES]],Cuadro_1!$J$8,IFM[[AÑO]:[AÑO]],Cuadro_1!$L$8)/1000 -> 749200.81 | E20: =SUMIFS(IFM[[SiniestrosPagados_NetosdeSalvamento]:[SiniestrosPagados_NetosdeSalvamento]],IFM[[Nombre Empresa]:[Nombre Empresa]],$C20,IFM[[MES]:[MES]],Cuadro_1!$J$8,IFM[[AÑO]:[AÑO]],Cuadro_1!$L$8)/1000 -> 3112.3281 | F20: =SUMIFS(IFM[[ReservasdeSiniestrosPendientesBrutas]:[ReservasdeSiniestrosPendientesBrutas]],IFM[[Nombre Empresa]:[Nombre Empresa]],$C20,IFM[[MES]:[MES]],Cuadro_1!$J$8,IFM[[AÑO]:[AÑO]],Cuadro_1!$L$8)/1000 -> 650.76523 | G20: =SUMIFS(IFM[[SiniestrosPendientes]:[SiniestrosPendientes]],IFM[[Nombre Empresa]:[Nombre Empresa]],$C20,IFM[[MES]:[MES]],Cuadro_1!$J$8,IFM[[AÑO]:[AÑO]],Cuadro_1!$L$8)/1000 -> 78.77739 | H20: =+E20+F20 -> 3763.0934 | I20: =SUMIFS(IFM[[Comisiones]:[Comisiones]],IFM[[Nombre Empresa]:[Nombre Empresa]],$C20,IFM[[MES]:[MES]],Cuadro_1!$J$8,IFM[[AÑO]:[AÑO]],Cuadro_1!$L$8)/1000 -> 498.51526 | J20: =SUMIFS(IFM[[GastosdeAdquision]:[GastosdeAdquision]],IFM[[Nombre Empresa]:[Nombre Empresa]],$C20,IFM[[MES]:[MES]],Cuadro_1!$J$8,IFM[[AÑO]:[AÑO]],Cuadro_1!$L$8)/1000 -> 62.2884 | K20: =SUMIFS(IFM[[Gastosdeadministracion]:[Gastosdeadministracion]],IFM[[Nombre Empresa]:[Nombre Empresa]],$C20,IFM[[MES]:[MES]],Cuadro_1!$J$8,IFM[[AÑO]:[AÑO]],Cuadro_1!$L$8)/1000 -> 81511.237
A21: =+D21 -> 0 | B21: 12 | C21: Carabobo C.A., Seguros | D21: =SUMIFS(IFM[[PrimasNetasCobradas]:[PrimasNetasCobradas]],IFM[[Nombre Empresa]:[Nombre Empresa]],$C21,IFM[[MES]:[MES]],Cuadro_1!$J$8,IFM[[AÑO]:[AÑO]],Cuadro_1!$L$8)/1000 -> 0 | E21: =SUMIFS(IFM[[SiniestrosPagados_NetosdeSalvamento]:[SiniestrosPagados_NetosdeSalvamento]],IFM[[Nombre Empresa]:[Nombre Empresa]],$C21,IFM[[MES]:[MES]],Cuadro_1!$J$8,IFM[[AÑO]:[AÑO]],Cuadro_1!$L$8)/1000 -> 0 | F21: =SUMIFS(IFM[[ReservasdeSiniestrosPendientesBrutas]:[ReservasdeSiniestrosPendientesBrutas]],IFM[[Nombre Empresa]:[Nombre Empresa]],$C21,IFM[[MES]:[MES]],Cuadro_1!$J$8,IFM[[AÑO]:[AÑO]],Cuadro_1!$L$8)/1000 -> 0 | G21: =SUMIFS(IFM[[SiniestrosPendientes]:[SiniestrosPendientes]],IFM[[Nombre Empresa]:[Nombre Empresa]],$C21,IFM[[MES]:[MES]],Cuadro_1!$J$8,IFM[[AÑO]:[AÑO]],Cuadro_1!$L$8)/1000 -> 0 | H21: =+E21+F21 -> 0 | I21: =SUMIFS(IFM[[Comisiones]:[Comisiones]],IFM[[Nombre Empresa]:[Nombre Empresa]],$C21,IFM[[MES]:[MES]],Cuadro_1!$J$8,IFM[[AÑO]:[AÑO]],Cuadro_1!$L$8)/1000 -> 0 | J21: =SUMIFS(IFM[[GastosdeAdquision]:[GastosdeAdquision]],IFM[[Nombre Empresa]:[Nombre Empresa]],$C21,IFM[[MES]:[MES]],Cuadro_1!$J$8,IFM[[AÑO]:[AÑO]],Cuadro_1!$L$8)/1000 -> 0 | K21: =SUMIFS(IFM[[Gastosdeadministracion]:[Gastosdeadministracion]],IFM[[Nombre Empresa]:[Nombre Empresa]],$C21,IFM[[MES]:[MES]],Cuadro_1!$J$8,IFM[[AÑO]:[AÑO]],Cuadro_1!$L$8)/1000 -> 0
... A60: =+D60 -> 116943.26 | B60: 51 | C60: Zuma Seguros, C.A. | D60: =SUMIFS(IFM[[PrimasNetasCobradas]:[PrimasNetasCobradas]],IFM[[Nombre Empresa]:[Nombre Empresa]],$C60,IFM[[MES]:[MES]],Cuadro_1!$J$8,IFM[[AÑO]:[AÑO]],Cuadro_1!$L$8)/1000 -> 116943.26 | E60: =SUMIFS(IFM[[SiniestrosPagados_NetosdeSalvamento]:[SiniestrosPagados_NetosdeSalvamento]],IFM[[Nombre Empresa]:[Nombre Empresa]],$C60,IFM[[MES]:[MES]],Cuadro_1!$J$8,IFM[[AÑO]:[AÑO]],Cuadro_1!$L$8)/1000 -> 54.095 | F60: =SUMIFS(IFM[[ReservasdeSiniestrosPendientesBrutas]:[ReservasdeSiniestrosPendientesBrutas]],IFM[[Nombre Empresa]:[Nombre Empresa]],$C60,IFM[[MES]:[MES]],Cuadro_1!$J$8,IFM[[AÑO]:[AÑO]],Cuadro_1!$L$8)/1000 -> 1.03 | G60: =SUMIFS(IFM[[SiniestrosPendientes]:[SiniestrosPendientes]],IFM[[Nombre Empresa]:[Nombre Empresa]],$C60,IFM[[MES]:[MES]],Cuadro_1!$J$8,IFM[[AÑO]:[AÑO]],Cuadro_1!$L$8)/1000 -> 1.03 | H60: =+E60+F60 -> 55.125 | I60: =SUMIFS(IFM[[Comisiones]:[Comisiones]],IFM[[Nombre Empresa]:[Nombre Empresa]],$C60,IFM[[MES]:[MES]],Cuadro_1!$J$8,IFM[[AÑO]:[AÑO]],Cuadro_1!$L$8)/1000 -> 15759.16 | J60: =SUMIFS(IFM[[GastosdeAdquision]:[GastosdeAdquision]],IFM[[Nombre Empresa]:[Nombre Empresa]],$C60,IFM[[MES]:[MES]],Cuadro_1!$J$8,IFM[[AÑO]:[AÑO]],Cuadro_1!$L$8)/1000 -> 16337.263 | K60: =SUMIFS(IFM[[Gastosdeadministracion]:[Gastosdeadministracion]],IFM[[Nombre Empresa]:[Nombre Empresa]],$C60,IFM[[MES]:[MES]],Cuadro_1!$J$8,IFM[[AÑO]:[AÑO]],Cuadro_1!$L$8)/1000 -> 89860.103
C61: TOTAL (En Miles de Bs.) | D61: =SUM(D10:D60) -> 65676102 | E61: =SUM(E10:E60) -> 25508260 | F61: =SUM(F10:F60) -> 12919620 | G61: =SUM(G10:G60) -> 4052066.2 | H61: =SUM(H10:H60) -> 38427879 | I61: =SUM(I10:I60) -> 5755298.3 | J61: =SUM(J10:J60) -> 3279522.1 | K61: =SUM(K10:K60) -> 14428628
C63: Fuente: (SEFA) Estados Financieros Analíticos Mensuales. Empresas de Seguros. | K63: Actualizado: 09/07/2025
C64: 1/ A la fecha han consignado los estados financieros analiticos 43 empresas de seguros. 2/ Faltan por procesar los estados financieros analiticos las siguientes empresas: Adriática de Seguros, C.A., Ávila de Seguros C.A., Bolivariana de Seguros y Reaseguros, S.A., Seguros Guayana, Multinacional de Seguros C.A., Interbank Seguros S.A, La Regional C.A., y Seguros Carabobo C.A.
C66: (1) Es el conjunto de aportaciones económicas percibidas por la empresa de seguros de parte de sus tomadores de pólizas en contraprestación por la cobertura de riesgo asumida, durante un periodo determinado. Este monto se refleja neto de anulaciones de pólizas y devoluciones de primas. (2) Representa el monto total de los siniestros cuyas consecuencias económicas han sido completamente indemnizadas o reparadas por la empresa aseguradora, durante un periodo determinado. Este monto se refleja neto de salvamento de siniestros, entendiéndose como tal, lo que resta de los bienes asegurados después del siniestro y que tenga valor económico para la empresa de seguros. (3) Representa la provisión que la empresa de seguros constituye con el fin de garantizar el cumplimiento de prestaciones derivadas de la materialización de siniestros ocurridos durante un período determinado, y que efectivamente no han sido indemnizadas. (4) Se refiere a las Reservas para Prestaciones y Siniestros Pendientes Brutas, netas de la porción correspondiente a riesgos cedidos a Reaseguradores inscritos en el Registro de Reaseguradores que lleva este Organismo. (5) Se refiere a la suma de los Siniestros Pagados más las Reservas para Prestaciones y Siniestros Pendientes Brutas. (6) En esta cuenta se registran los gastos incurridos por la empresa aseguradora para hacer frente al costo de la intermediación de seguros, derivado del pago de comisiones. (7) En esta cuenta se registran los gastos incurridos por la empresa aseguradora para hacer frente al costo de la intermediación de seguros, derivado del pago de bonificaciones a sus productores de seguros. (8) En esta cuenta se refleja el monto total que desembolsa la empresa aseguradora para hacer frente al costo de sus gastos administrativos totales, representados por los gastos de personal y los gastos generales derivados del desarrollo de su actividad de seguros.
C68: INFORMACIÓN PRELIMINAR NO AUDITADA POR LA SUPERINTENDENCIA DE LA ACTIVIDAD ASEGURADORA

Sheet Cuadro_3
B1: REPÚBLICA BOLIVARIANA DE VENEZUELA
B2: MINISTERIO DEL PODER POPULAR DE ECONOMíA Y FINANZAS
B3: SUPERINTENDENCIA DE LA ACTIVIDAD ASEGURADORA
B4: DIRECCIÓN ACTUARIAL / ÁREA DE INVESTIGACIÓN, TRABAJOS ESPECIALES Y ESTADÍSTICAS
B6: INFORMACIÓN FINANCIERA ANALÍTICA MENSUAL DEL MERCADO ASEGURADOR VENEZOLANO
B7: ACUMULADA AL 30 DE JUNIO DE 2025 | C7: =+Cuadro_1!B7 -> ACUMULADA A AGOSTO DE 2025
B8: ÍNDICES POR EMPRESA
B10: # | C10: Empresas de Seguros | D10: Siniestros Pagados Vs. Primas Netas Cobradas (%) (1) | E10: Reservas para Prestaciones y Siniestros Pendientes Brutas Vs. Primas Netas Cobradas (%) (2) | F10: Siniestros Incurridos Vs Prima Devengada (%) (3) | G10: Comisiones Vs. Primas Netas Cobradas (%) (4) | H10: Gastos de Adquisición Vs. Primas Netas Cobradas (%) (5) | I10: Gastos de Administración Vs. Primas Netas Cobradas (%) (6) | J10: Costo del Reaseguro Vs. Prima Devengada (%) (7) | K10: Tasa Combinada (%) (8) | L10: Índice de Cobertura de Reservas (9)
B13: 1 | C13: Adriática de Seguros, C.A. | D13: =IFERROR((SUMIFS(IFM[[SiniestrosPagados_NetosdeSalvamento]:[SiniestrosPagados_NetosdeSalvamento]],IFM[[Nombre Empresa]:[Nombre Empresa]],$C13,IFM[[MES]:[MES]],Cuadro_1!$J$8,IFM[[AÑO]:[AÑO]],Cuadro_1!$L$8)/SUMIFS(IFM[[PrimasNetasCobradas]:[PrimasNetasCobradas]],IFM[[Nombre Empresa]:[Nombre Empresa]],$C13,IFM[[MES]:[MES]],Cuadro_1!$J$8,IFM[[AÑO]:[AÑO]],Cuadro_1!$L$8)*100),0) -> 0 | E13: =IFERROR((SUMIFS(IFM[[ReservasdeSiniestrosPendientesBrutas]:[ReservasdeSiniestrosPendientesBrutas]],IFM[[Nombre Empresa]:[Nombre Empresa]],$C13,IFM[[MES]:[MES]],Cuadro_1!$J$8,IFM[[AÑO]:[AÑO]],Cuadro_1!$L$8)/SUMIFS(IFM[[PrimasNetasCobradas]:[PrimasNetasCobradas]],IFM[[Nombre Empresa]:[Nombre Empresa]],$C13,IFM[[MES]:[MES]],Cuadro_1!$J$8,IFM[[AÑO]:[AÑO]],Cuadro_1!$L$8)*100),0) -> 0 | F13: =IFERROR((SUMIFS(IFM[[TotalGenralSI]:[TotalGenralSI]],IFM[[Nombre Empresa]:[Nombre Empresa]],$C13,IFM[[MES]:[MES]],Cuadro_1!$J$8,IFM[[AÑO]:[AÑO]],Cuadro_1!$L$8)/SUMIFS(IFM[[Total GeneralPDev]:[Total GeneralPDev]],IFM[[Nombre Empresa]:[Nombre Empresa]],$C13,IFM[[MES]:[MES]],Cuadro_1!$J$8,IFM[[AÑO]:[AÑO]],Cuadro_1!$L$8)*100),0) -> 0 | G13: =IFERROR((SUMIFS(IFM[[Comisiones]:[Comisiones]],IFM[[Nombre Empresa]:[Nombre Empresa]],$C13,IFM[[MES]:[MES]],Cuadro_1!$J$8,IFM[[AÑO]:[AÑO]],Cuadro_1!$L$8)/SUMIFS(IFM[[PrimasNetasCobradas]:[PrimasNetasCobradas]],IFM[[Nombre Empresa]:[Nombre Empresa]],$C13,IFM[[MES]:[MES]],Cuadro_1!$J$8,IFM[[AÑO]:[AÑO]],Cuadro_1!$L$8)*100),0) -> 0 | H13: =IFERROR((SUMIFS(IFM[[GastosdeAdquision]:[GastosdeAdquision]],IFM[[Nombre Empresa]:[Nombre Empresa]],$C13,IFM[[MES]:[MES]],Cuadro_1!$J$8,IFM[[AÑO]:[AÑO]],Cuadro_1!$L$8)/SUMIFS(IFM[[PrimasNetasCobradas]:[PrimasNetasCobradas]],IFM[[Nombre Empresa]:[Nombre Empresa]],$C13,IFM[[MES]:[MES]],Cuadro_1!$J$8,IFM[[AÑO]:[AÑO]],Cuadro_1!$L$8)*100),0) -> 0 | I13: =IFERROR((SUMIFS(IFM[[Gastosdeadministracion]:[Gastosdeadministracion]],IFM[[Nombre Empresa]:[Nombre Empresa]],$C13,IFM[[MES]:[MES]],Cuadro_1!$J$8,IFM[[AÑO]:[AÑO]],Cuadro_1!$L$8)/SUMIFS(IFM[[PrimasNetasCobradas]:[PrimasNetasCobradas]],IFM[[Nombre Empresa]:[Nombre Empresa]],$C13,IFM[[MES]:[MES]],Cuadro_1!$J$8,IFM[[AÑO]:[AÑO]],Cuadro_1!$L$8)*100),0) -> 0 | J13: =IFERROR((SUMIFS(IFM[[ResultadodelReaseguroCedido]:[ResultadodelReaseguroCedido]],IFM[[Nombre Empresa]:[Nombre Empresa]],$C13,IFM[[MES]:[MES]],Cuadro_1!$J$8,IFM[[AÑO]:[AÑO]],Cuadro_1!$L$8)/SUMIFS(IFM[[Total GeneralPDev]:[Total GeneralPDev]],IFM[[Nombre Empresa]:[Nombre Empresa]],$C13,IFM[[MES]:[MES]],Cuadro_1!$J$8,IFM[[AÑO]:[AÑO]],Cuadro_1!$L$8)*-100),0) -> 0 | K13: =SUM(F13:J13) -> 0 | L13: =IFERROR((SUMIFS(IFM[[InversionesAptas]:[InversionesAptas]],IFM[[Nombre Empresa]:[Nombre Empresa]],$C13,IFM[[MES]:[MES]],Cuadro_1!$J$8,IFM[[AÑO]:[AÑO]],Cuadro_1!$L$8)/SUMIFS(IFM[[ReservasTecnicas]:[ReservasTecnicas]],IFM[[Nombre Empresa]:[Nombre Empresa]],$C13,IFM[[MES]:[MES]],Cuadro_1!$J$8,IFM[[AÑO]:[AÑO]],Cuadro_1!$L$8)),0) -> 0
B14: 2 | C14: Altamira C.A., Seguros | D14: =IFERROR((SUMIFS(IFM[[SiniestrosPagados_NetosdeSalvamento]:[SiniestrosPagados_NetosdeSalvamento]],IFM[[Nombre Empresa]:[Nombre Empresa]],$C14,IFM[[MES]:[MES]],Cuadro_1!$J$8,IFM[[AÑO]:[AÑO]],Cuadro_1!$L$8)/SUMIFS(IFM[[PrimasNetasCobradas]:[PrimasNetasCobradas]],IFM[[Nombre Empresa]:[Nombre Empresa]],$C14,IFM[[MES]:[MES]],Cuadro_1!$J$8,IFM[[AÑO]:[AÑO]],Cuadro_1!$L$8)*100),0) -> 20.096762 | E14: =IFERROR((SUMIFS(IFM[[ReservasdeSiniestrosPendientesBrutas]:[ReservasdeSiniestrosPendientesBrutas]],IFM[[Nombre Empresa]:[Nombre Empresa]],$C14,IFM[[MES]:[MES]],Cuadro_1!$J$8,IFM[[AÑO]:[AÑO]],Cuadro_1!$L$8)/SUMIFS(IFM[[PrimasNetasCobradas]:[PrimasNetasCobradas]],IFM[[Nombre Empresa]:[Nombre Empresa]],$C14,IFM[[MES]:[MES]],Cuadro_1!$J$8,IFM[[AÑO]:[AÑO]],Cuadro_1!$L$8)*100),0) -> 29.198459 | F14: =IFERROR((SUMIFS(IFM[[TotalGenralSI]:[TotalGenralSI]],IFM[[Nombre Empresa]:[Nombre Empresa]],$C14,IFM[[MES]:[MES]],Cuadro_1!$J$8,IFM[[AÑO]:[AÑO]],Cuadro_1!$L$8)/SUMIFS(IFM[[Total GeneralPDev]:[Total GeneralPDev]],IFM[[Nombre Empresa]:[Nombre Empresa]],$C14,IFM[[MES]:[MES]],Cuadro_1!$J$8,IFM[[AÑO]:[AÑO]],Cuadro_1!$L$8)*100),0) -> 32.144134 | G14: =IFERROR((SUMIFS(IFM[[Comisiones]:[Comisiones]],IFM[[Nombre Empresa]:[Nombre Empresa]],$C14,IFM[[MES]:[MES]],Cuadro_1!$J$8,IFM[[AÑO]:[AÑO]],Cuadro_1!$L$8)/SUMIFS(IFM[[PrimasNetasCobradas]:[PrimasNetasCobradas]],IFM[[Nombre Empresa]:[Nombre Empresa]],$C14,IFM[[MES]:[MES]],Cuadro_1!$J$8,IFM[[AÑO]:[AÑO]],Cuadro_1!$L$8)*100),0) -> 4.7139638 | H14: =IFERROR((SUMIFS(IFM[[GastosdeAdquision]:[GastosdeAdquision]],IFM[[Nombre Empresa]:[Nombre Empresa]],$C14,IFM[[MES]:[MES]],Cuadro_1!$J$8,IFM[[AÑO]:[AÑO]],Cuadro_1!$L$8)/SUMIFS(IFM[[PrimasNetasCobradas]:[PrimasNetasCobradas]],IFM[[Nombre Empresa]:[Nombre Empresa]],$C14,IFM[[MES]:[MES]],Cuadro_1!$J$8,IFM[[AÑO]:[AÑO]],Cuadro_1!$L$8)*100),0) -> 10.069875 | I14: =IFERROR((SUMIFS(IFM[[Gastosdeadministracion]:[Gastosdeadministracion]],IFM[[Nombre Empresa]:[Nombre Empresa]],$C14,IFM[[MES]:[MES]],Cuadro_1!$J$8,IFM[[AÑO]:[AÑO]],Cuadro_1!$L$8)/SUMIFS(IFM[[PrimasNetasCobradas]:[PrimasNetasCobradas]],IFM[[Nombre Empresa]:[Nombre Empresa]],$C14,IFM[[MES]:[MES]],Cuadro_1!$J$8,IFM[[AÑO]:[AÑO]],Cuadro_1!$L$8)*100),0) -> 37.465487 | J14: =IFERROR((SUMIFS(IFM[[ResultadodelReaseguroCedido]:[ResultadodelReaseguroCedido]],IFM[[Nombre Empresa]:[Nombre Empresa]],$C14,IFM[[MES]:[MES]],Cuadro_1!$J$8,IFM[[AÑO]:[AÑO]],Cuadro_1!$L$8)/SUMIFS(IFM[[Total GeneralPDev]:[Total GeneralPDev]],IFM[[Nombre Empresa]:[Nombre Empresa]],$C14,IFM[[MES]:[MES]],Cuadro_1!$J$8,IFM[[AÑO]:[AÑO]],Cuadro_1!$L$8)*-100),0) -> 4.3449269 | K14: =SUM(F14:J14) -> 88.738387 | L14: =IFERROR((SUMIFS(IFM[[InversionesAptas]:[InversionesAptas]],IFM[[Nombre Empresa]:[Nombre Empresa]],$C14,IFM[[MES]:[MES]],Cuadro_1!$J$8,IFM[[AÑO]:[AÑO]],Cuadro_1!$L$8)/SUMIFS(IFM[[ReservasTecnicas]:[ReservasTecnicas]],IFM[[Nombre Empresa]:[Nombre Empresa]],$C14,IFM[[MES]:[MES]],Cuadro_1!$J$8,IFM[[AÑO]:[AÑO]],Cuadro_1!$L$8)),0) -> 2.5448307
B15: 3 | C15: American International, C.A. de Seguros | D15: =IFERROR((SUMIFS(IFM[[SiniestrosPagados_NetosdeSalvamento]:[SiniestrosPagados_NetosdeSalvamento]],IFM[[Nombre Empresa]:[Nombre Empresa]],$C15,IFM[[MES]:[MES]],Cuadro_1!$J$8,IFM[[AÑO]:[AÑO]],Cuadro_1!$L$8)/SUMIFS(IFM[[PrimasNetasCobradas]:[PrimasNetasCobradas]],IFM[[Nombre Empresa]:[Nombre Empresa]],$C15,IFM[[MES]:[MES]],Cuadro_1!$J$8,IFM[[AÑO]:[AÑO]],Cuadro_1!$L$8)*100),0) -> 144.04201 | E15: =IFERROR((SUMIFS(IFM[[ReservasdeSiniestrosPendientesBrutas]:[ReservasdeSiniestrosPendientesBrutas]],IFM[[Nombre Empresa]:[Nombre Empresa]],$C15,IFM[[MES]:[MES]],Cuadro_1!$J$8,IFM[[AÑO]:[AÑO]],Cuadro_1!$L$8)/SUMIFS(IFM[[PrimasNetasCobradas]:[PrimasNetasCobradas]],IFM[[Nombre Empresa]:[Nombre Empresa]],$C15,IFM[[MES]:[MES]],Cuadro_1!$J$8,IFM[[AÑO]:[AÑO]],Cuadro_1!$L$8)*100),0) -> 14.392313 | F15: =IFERROR((SUMIFS(IFM[[TotalGenralSI]:[TotalGenralSI]],IFM[[Nombre Empresa]:[Nombre Empresa]],$C15,IFM[[MES]:[MES]],Cuadro_1!$J$8,IFM[[AÑO]:[AÑO]],Cuadro_1!$L$8)/SUMIFS(IFM[[Total GeneralPDev]:[Total GeneralPDev]],IFM[[Nombre Empresa]:[Nombre Empresa]],$C15,IFM[[MES]:[MES]],Cuadro_1!$J$8,IFM[[AÑO]:[AÑO]],Cuadro_1!$L$8)*100),0) -> 143.44318 | G15: =IFERROR((SUMIFS(IFM[[Comisiones]:[Comisiones]],IFM[[Nombre Empresa]:[Nombre Empresa]],$C15,IFM[[MES]:[MES]],Cuadro_1!$J$8,IFM[[AÑO]:[AÑO]],Cuadro_1!$L$8)/SUMIFS(IFM[[PrimasNetasCobradas]:[PrimasNetasCobradas]],IFM[[Nombre Empresa]:[Nombre Empresa]],$C15,IFM[[MES]:[MES]],Cuadro_1!$J$8,IFM[[AÑO]:[AÑO]],Cuadro_1!$L$8)*100),0) -> 8.0647274 | H15: =IFERROR((SUMIFS(IFM[[GastosdeAdquision]:[GastosdeAdquision]],IFM[[Nombre Empresa]:[Nombre Empresa]],$C15,IFM[[MES]:[MES]],Cuadro_1!$J$8,IFM[[AÑO]:[AÑO]],Cuadro_1!$L$8)/SUMIFS(IFM[[PrimasNetasCobradas]:[PrimasNetasCobradas]],IFM[[Nombre Empresa]:[Nombre Empresa]],$C15,IFM[[MES]:[MES]],Cuadro_1!$J$8,IFM[[AÑO]:[AÑO]],Cuadro_1!$L$8)*100),0) -> 0 | I15: =IFERROR((SUMIFS(IFM[[Gastosdeadministracion]:[Gastosdeadministracion]],IFM[[Nombre Empresa]:[Nombre Empresa]],$C15,IFM[[MES]:[MES]],Cuadro_1!$J$8,IFM[[AÑO]:[AÑO]],Cuadro_1!$L$8)/SUMIFS(IFM[[PrimasNetasCobradas]:[PrimasNetasCobradas]],IFM[[Nombre Empresa]:[Nombre Empresa]],$C15,IFM[[MES]:[MES]],Cuadro_1!$J$8,IFM[[AÑO]:[AÑO]],Cuadro_1!$L$8)*100),0) -> 350.02677 | J15: =IFERROR((SUMIFS(IFM[[ResultadodelReaseguroCedido]:[ResultadodelReaseguroCedido]],IFM[[Nombre Empresa]:[Nombre Empresa]],$C15,IFM[[MES]:[MES]],Cuadro_1!$J$8,IFM[[AÑO]:[AÑO]],Cuadro_1!$L$8)/SUMIFS(IFM[[Total GeneralPDev]:[Total GeneralPDev]],IFM[[Nombre Empresa]:[Nombre Empresa]],$C15,IFM[[MES]:[MES]],Cuadro_1!$J$8,IFM[[AÑO]:[AÑO]],Cuadro_1!$L$8)*-100),0) -> -37.027118 | K15: =SUM(F15:J15) -> 464.50756 | L15: =IFERROR((SUMIFS(IFM[[InversionesAptas]:[InversionesAptas]],IFM[[Nombre Empresa]:[Nombre Empresa]],$C15,IFM[[MES]:[MES]],Cuadro_1!$J$8,IFM[[AÑO]:[AÑO]],Cuadro_1!$L$8)/SUMIFS(IFM[[ReservasTecnicas]:[ReservasTecnicas]],IFM[[Nombre Empresa]:[Nombre Empresa]],$C15,IFM[[MES]:[MES]],Cuadro_1!$J$8,IFM[[AÑO]:[AÑO]],Cuadro_1!$L$8)),0) -> 288384.37
B16: 4 | C16: Andes C.A., Seguros | D16: =IFERROR((SUMIFS(IFM[[SiniestrosPagados_NetosdeSalvamento]:[SiniestrosPagados_NetosdeSalvamento]],IFM[[Nombre Empresa]:[Nombre Empresa]],$C16,IFM[[MES]:[MES]],Cuadro_1!$J$8,IFM[[AÑO]:[AÑO]],Cuadro_1!$L$8)/SUMIFS(IFM[[PrimasNetasCobradas]:[PrimasNetasCobradas]],IFM[[Nombre Empresa]:[Nombre Empresa]],$C16,IFM[[MES]:[MES]],Cuadro_1!$J$8,IFM[[AÑO]:[AÑO]],Cuadro_1!$L$8)*100),0) -> 10.779852 | E16: =IFERROR((SUMIFS(IFM[[ReservasdeSiniestrosPendientesBrutas]:[ReservasdeSiniestrosPendientesBrutas]],IFM[[Nombre Empresa]:[Nombre Empresa]],$C16,IFM[[MES]:[MES]],Cuadro_1!$J$8,IFM[[AÑO]:[AÑO]],Cuadro_1!$L$8)/SUMIFS(IFM[[PrimasNetasCobradas]:[PrimasNetasCobradas]],IFM[[Nombre Empresa]:[Nombre Empresa]],$C16,IFM[[MES]:[MES]],Cuadro_1!$J$8,IFM[[AÑO]:[AÑO]],Cuadro_1!$L$8)*100),0) -> 15.044035 | F16: =IFERROR((SUMIFS(IFM[[TotalGenralSI]:[TotalGenralSI]],IFM[[Nombre Empresa]:[Nombre Empresa]],$C16,IFM[[MES]:[MES]],Cuadro_1!$J$8,IFM[[AÑO]:[AÑO]],Cuadro_1!$L$8)/SUMIFS(IFM[[Total GeneralPDev]:[Total GeneralPDev]],IFM[[Nombre Empresa]:[Nombre Empresa]],$C16,IFM[[MES]:[MES]],Cuadro_1!$J$8,IFM[[AÑO]:[AÑO]],Cuadro_1!$L$8)*100),0) -> 19.337165 | G16: =IFERROR((SUMIFS(IFM[[Comisiones]:[Comisiones]],IFM[[Nombre Empresa]:[Nombre Empresa]],$C16,IFM[[MES]:[MES]],Cuadro_1!$J$8,IFM[[AÑO]:[AÑO]],Cuadro_1!$L$8)/SUMIFS(IFM[[PrimasNetasCobradas]:[PrimasNetasCobradas]],IFM[[Nombre Empresa]:[Nombre Empresa]],$C16,IFM[[MES]:[MES]],Cuadro_1!$J$8,IFM[[AÑO]:[AÑO]],Cuadro_1!$L$8)*100),0) -> 11.043488 | H16: =IFERROR((SUMIFS(IFM[[GastosdeAdquision]:[GastosdeAdquision]],IFM[[Nombre Empresa]:[Nombre Empresa]],$C16,IFM[[MES]:[MES]],Cuadro_1!$J$8,IFM[[AÑO]:[AÑO]],Cuadro_1!$L$8)/SUMIFS(IFM[[PrimasNetasCobradas]:[PrimasNetasCobradas]],IFM[[Nombre Empresa]:[Nombre Empresa]],$C16,IFM[[MES]:[MES]],Cuadro_1!$J$8,IFM[[AÑO]:[AÑO]],Cuadro_1!$L$8)*100),0) -> 8.5084735 | I16: =IFERROR((SUMIFS(IFM[[Gastosdeadministracion]:[Gastosdeadministracion]],IFM[[Nombre Empresa]:[Nombre Empresa]],$C16,IFM[[MES]:[MES]],Cuadro_1!$J$8,IFM[[AÑO]:[AÑO]],Cuadro_1!$L$8)/SUMIFS(IFM[[PrimasNetasCobradas]:[PrimasNetasCobradas]],IFM[[Nombre Empresa]:[Nombre Empresa]],$C16,IFM[[MES]:[MES]],Cuadro_1!$J$8,IFM[[AÑO]:[AÑO]],Cuadro_1!$L$8)*100),0) -> 72.27045 | J16: =IFERROR((SUMIFS(IFM[[ResultadodelReaseguroCedido]:[ResultadodelReaseguroCedido]],IFM[[Nombre Empresa]:[Nombre Empresa]],$C16,IFM[[MES]:[MES]],Cuadro_1!$J$8,IFM[[AÑO]:[AÑO]],Cuadro_1!$L$8)/SUMIFS(IFM[[Total GeneralPDev]:[Total GeneralPDev]],IFM[[Nombre Empresa]:[Nombre Empresa]],$C16,IFM[[MES]:[MES]],Cuadro_1!$J$8,IFM[[AÑO]:[AÑO]],Cuadro_1!$L$8)*-100),0) -> 1.0842946 | K16: =SUM(F16:J16) -> 112.24387 | L16: =IFERROR((SUMIFS(IFM[[InversionesAptas]:[InversionesAptas]],IFM[[Nombre Empresa]:[Nombre Empresa]],$C16,IFM[[MES]:[MES]],Cuadro_1!$J$8,IFM[[AÑO]:[AÑO]],Cuadro_1!$L$8)/SUMIFS(IFM[[ReservasTecnicas]:[ReservasTecnicas]],IFM[[Nombre Empresa]:[Nombre Empresa]],$C16,IFM[[MES]:[MES]],Cuadro_1!$J$8,IFM[[AÑO]:[AÑO]],Cuadro_1!$L$8)),0) -> 3.5752839
B17: 5 | C17: Aseguradora Nacional Unida Uniseguros, S.A. | D17: =IFERROR((SUMIFS(IFM[[SiniestrosPagados_NetosdeSalvamento]:[SiniestrosPagados_NetosdeSalvamento]],IFM[[Nombre Empresa]:[Nombre Empresa]],$C17,IFM[[MES]:[MES]],Cuadro_1!$J$8,IFM[[AÑO]:[AÑO]],Cuadro_1!$L$8)/SUMIFS(IFM[[PrimasNetasCobradas]:[PrimasNetasCobradas]],IFM[[Nombre Empresa]:[Nombre Empresa]],$C17,IFM[[MES]:[MES]],Cuadro_1!$J$8,IFM[[AÑO]:[AÑO]],Cuadro_1!$L$8)*100),0) -> 23.082565 | E17: =IFERROR((SUMIFS(IFM[[ReservasdeSiniestrosPendientesBrutas]:[ReservasdeSiniestrosPendientesBrutas]],IFM[[Nombre Empresa]:[Nombre Empresa]],$C17,IFM[[MES]:[MES]],Cuadro_1!$J$8,IFM[[AÑO]:[AÑO]],Cuadro_1!$L$8)/SUMIFS(IFM[[PrimasNetasCobradas]:[PrimasNetasCobradas]],IFM[[Nombre Empresa]:[Nombre Empresa]],$C17,IFM[[MES]:[MES]],Cuadro_1!$J$8,IFM[[AÑO]:[AÑO]],Cuadro_1!$L$8)*100),0) -> 14.719001 | F17: =IFERROR((SUMIFS(IFM[[TotalGenralSI]:[TotalGenralSI]],IFM[[Nombre Empresa]:[Nombre Empresa]],$C17,IFM[[MES]:[MES]],Cuadro_1!$J$8,IFM[[AÑO]:[AÑO]],Cuadro_1!$L$8)/SUMIFS(IFM[[Total GeneralPDev]:[Total GeneralPDev]],IFM[[Nombre Empresa]:[Nombre Empresa]],$C17,IFM[[MES]:[MES]],Cuadro_1!$J$8,IFM[[AÑO]:[AÑO]],Cuadro_1!$L$8)*100),0) -> 22.003833 | G17: =IFERROR((SUMIFS(IFM[[Comisiones]:[Comisiones]],IFM[[Nombre Empresa]:[Nombre Empresa]],$C17,IFM[[MES]:[MES]],Cuadro_1!$J$8,IFM[[AÑO]:[AÑO]],Cuadro_1!$L$8)/SUMIFS(IFM[[PrimasNetasCobradas]:[PrimasNetasCobradas]],IFM[[Nombre Empresa]:[Nombre Empresa]],$C17,IFM[[MES]:[MES]],Cuadro_1!$J$8,IFM[[AÑO]:[AÑO]],Cuadro_1!$L$8)*100),0) -> 11.237176 | H17: =IFERROR((SUMIFS(IFM[[GastosdeAdquision]:[GastosdeAdquision]],IFM[[Nombre Empresa]:[Nombre Empresa]],$C17,IFM[[MES]:[MES]],Cuadro_1!$J$8,IFM[[AÑO]:[AÑO]],Cuadro_1!$L$8)/SUMIFS(IFM[[PrimasNetasCobradas]:[PrimasNetasCobradas]],IFM[[Nombre Empresa]:[Nombre Empresa]],$C17,IFM[[MES]:[MES]],Cuadro_1!$J$8,IFM[[AÑO]:[AÑO]],Cuadro_1!$L$8)*100),0) -> 12.168449 | I17: =IFERROR((SUMIFS(IFM[[Gastosdeadministracion]:[Gastosdeadministracion]],IFM[[Nombre Empresa]:[Nombre Empresa]],$C17,IFM[[MES]:[MES]],Cuadro_1!$J$8,IFM[[AÑO]:[AÑO]],Cuadro_1!$L$8)/SUMIFS(IFM[[PrimasNetasCobradas]:[PrimasNetasCobradas]],IFM[[Nombre Empresa]:[Nombre Empresa]],$C17,IFM[[MES]:[MES]],Cuadro_1!$J$8,IFM[[AÑO]:[AÑO]],Cuadro_1!$L$8)*100),0) -> 62.326309 | J17: =IFERROR((SUMIFS(IFM[[ResultadodelReaseguroCedido]:[ResultadodelReaseguroCedido]],IFM[[Nombre Empresa]:[Nombre Empresa]],$C17,IFM[[MES]:[MES]],Cuadro_1!$J$8,IFM[[AÑO]:[AÑO]],Cuadro_1!$L$8)/SUMIFS(IFM[[Total GeneralPDev]:[Total GeneralPDev]],IFM[[Nombre Empresa]:[Nombre Empresa]],$C17,IFM[[MES]:[MES]],Cuadro_1!$J$8,IFM[[AÑO]:[AÑO]],Cuadro_1!$L$8)*-100),0) -> 28.063606 | K17: =SUM(F17:J17) -> 135.79937 | L17: =IFERROR((SUMIFS(IFM[[InversionesAptas]:[InversionesAptas]],IFM[[Nombre Empresa]:[Nombre Empresa]],$C17,IFM[[MES]:[MES]],Cuadro_1!$J$8,IFM[[AÑO]:[AÑO]],Cuadro_1!$L$8)/SUMIFS(IFM[[ReservasTecnicas]:[ReservasTecnicas]],IFM[[Nombre Empresa]:[Nombre Empresa]],$C17,IFM[[MES]:[MES]],Cuadro_1!$J$8,IFM[[AÑO]:[AÑO]],Cuadro_1!$L$8)),0) -> 21.768935
B18: 6 | C18: Atrio Seguros S.A. | D18: =IFERROR((SUMIFS(IFM[[SiniestrosPagados_NetosdeSalvamento]:[SiniestrosPagados_NetosdeSalvamento]],IFM[[Nombre Empresa]:[Nombre Empresa]],$C18,IFM[[MES]:[MES]],Cuadro_1!$J$8,IFM[[AÑO]:[AÑO]],Cuadro_1!$L$8)/SUMIFS(IFM[[PrimasNetasCobradas]:[PrimasNetasCobradas]],IFM[[Nombre Empresa]:[Nombre Empresa]],$C18,IFM[[MES]:[MES]],Cuadro_1!$J$8,IFM[[AÑO]:[AÑO]],Cuadro_1!$L$8)*100),0) -> 18.897655 | E18: =IFERROR((SUMIFS(IFM[[ReservasdeSiniestrosPendientesBrutas]:[ReservasdeSiniestrosPendientesBrutas]],IFM[[Nombre Empresa]:[Nombre Empresa]],$C18,IFM[[MES]:[MES]],Cuadro_1!$J$8,IFM[[AÑO]:[AÑO]],Cuadro_1!$L$8)/SUMIFS(IFM[[PrimasNetasCobradas]:[PrimasNetasCobradas]],IFM[[Nombre Empresa]:[Nombre Empresa]],$C18,IFM[[MES]:[MES]],Cuadro_1!$J$8,IFM[[AÑO]:[AÑO]],Cuadro_1!$L$8)*100),0) -> 16.237479 | F18: =IFERROR((SUMIFS(IFM[[TotalGenralSI]:[TotalGenralSI]],IFM[[Nombre Empresa]:[Nombre Empresa]],$C18,IFM[[MES]:[MES]],Cuadro_1!$J$8,IFM[[AÑO]:[AÑO]],Cuadro_1!$L$8)/SUMIFS(IFM[[Total GeneralPDev]:[Total GeneralPDev]],IFM[[Nombre Empresa]:[Nombre Empresa]],$C18,IFM[[MES]:[MES]],Cuadro_1!$J$8,IFM[[AÑO]:[AÑO]],Cuadro_1!$L$8)*100),0) -> 19.454919 | G18: =IFERROR((SUMIFS(IFM[[Comisiones]:[Comisiones]],IFM[[Nombre Empresa]:[Nombre Empresa]],$C18,IFM[[MES]:[MES]],Cuadro_1!$J$8,IFM[[AÑO]:[AÑO]],Cuadro_1!$L$8)/SUMIFS(IFM[[PrimasNetasCobradas]:[PrimasNetasCobradas]],IFM[[Nombre Empresa]:[Nombre Empresa]],$C18,IFM[[MES]:[MES]],Cuadro_1!$J$8,IFM[[AÑO]:[AÑO]],Cuadro_1!$L$8)*100),0) -> 12.862974 | H18: =IFERROR((SUMIFS(IFM[[GastosdeAdquision]:[GastosdeAdquision]],IFM[[Nombre Empresa]:[Nombre Empresa]],$C18,IFM[[MES]:[MES]],Cuadro_1!$J$8,IFM[[AÑO]:[AÑO]],Cuadro_1!$L$8)/SUMIFS(IFM[[PrimasNetasCobradas]:[PrimasNetasCobradas]],IFM[[Nombre Empresa]:[Nombre Empresa]],$C18,IFM[[MES]:[MES]],Cuadro_1!$J$8,IFM[[AÑO]:[AÑO]],Cuadro_1!$L$8)*100),0) -> 7.3665308 | I18: =IFERROR((SUMIFS(IFM[[Gastosdeadministracion]:[Gastosdeadministracion]],IFM[[Nombre Empresa]:[Nombre Empresa]],$C18,IFM[[MES]:[MES]],Cuadro_1!$J$8,IFM[[AÑO]:[AÑO]],Cuadro_1!$L$8)/SUMIFS(IFM[[PrimasNetasCobradas]:[PrimasNetasCobradas]],IFM[[Nombre Empresa]:[Nombre Empresa]],$C18,IFM[[MES]:[MES]],Cuadro_1!$J$8,IFM[[AÑO]:[AÑO]],Cuadro_1!$L$8)*100),0) -> 38.931036 | J18: =IFERROR((SUMIFS(IFM[[ResultadodelReaseguroCedido]:[ResultadodelReaseguroCedido]],IFM[[Nombre Empresa]:[Nombre Empresa]],$C18,IFM[[MES]:[MES]],Cuadro_1!$J$8,IFM[[AÑO]:[AÑO]],Cuadro_1!$L$8)/SUMIFS(IFM[[Total GeneralPDev]:[Total GeneralPDev]],IFM[[Nombre Empresa]:[Nombre Empresa]],$C18,IFM[[MES]:[MES]],Cuadro_1!$J$8,IFM[[AÑO]:[AÑO]],Cuadro_1!$L$8)*-100),0) -> -5.4340044 | K18: =SUM(F18:J18) -> 73.181455 | L18: =IFERROR((SUMIFS(IFM[[InversionesAptas]:[InversionesAptas]],IFM[[Nombre Empresa]:[Nombre Empresa]],$C18,IFM[[MES]:[MES]],Cuadro_1!$J$8,IFM[[AÑO]:[AÑO]],Cuadro_1!$L$8)/SUMIFS(IFM[[ReservasTecnicas]:[ReservasTecnicas]],IFM[[Nombre Empresa]:[Nombre Empresa]],$C18,IFM[[MES]:[MES]],Cuadro_1!$J$8,IFM[[AÑO]:[AÑO]],Cuadro_1!$L$8)),0) -> 1.5110872
B19: 7 | C19: Ávila C.A., de Seguros | D19: =IFERROR((SUMIFS(IFM[[SiniestrosPagados_NetosdeSalvamento]:[SiniestrosPagados_NetosdeSalvamento]],IFM[[Nombre Empresa]:[Nombre Empresa]],$C19,IFM[[MES]:[MES]],Cuadro_1!$J$8,IFM[[AÑO]:[AÑO]],Cuadro_1!$L$8)/SUMIFS(IFM[[PrimasNetasCobradas]:[PrimasNetasCobradas]],IFM[[Nombre Empresa]:[Nombre Empresa]],$C19,IFM[[MES]:[MES]],Cuadro_1!$J$8,IFM[[AÑO]:[AÑO]],Cuadro_1!$L$8)*100),0) -> 0 | E19: =IFERROR((SUMIFS(IFM[[ReservasdeSiniestrosPendientesBrutas]:[ReservasdeSiniestrosPendientesBrutas]],IFM[[Nombre Empresa]:[Nombre Empresa]],$C19,IFM[[MES]:[MES]],Cuadro_1!$J$8,IFM[[AÑO]:[AÑO]],Cuadro_1!$L$8)/SUMIFS(IFM[[PrimasNetasCobradas]:[PrimasNetasCobradas]],IFM[[Nombre Empresa]:[Nombre Empresa]],$C19,IFM[[MES]:[MES]],Cuadro_1!$J$8,IFM[[AÑO]:[AÑO]],Cuadro_1!$L$8)*100),0) -> 0 | F19: =IFERROR((SUMIFS(IFM[[TotalGenralSI]:[TotalGenralSI]],IFM[[Nombre Empresa]:[Nombre Empresa]],$C19,IFM[[MES]:[MES]],Cuadro_1!$J$8,IFM[[AÑO]:[AÑO]],Cuadro_1!$L$8)/SUMIFS(IFM[[Total GeneralPDev]:[Total GeneralPDev]],IFM[[Nombre Empresa]:[Nombre Empresa]],$C19,IFM[[MES]:[MES]],Cuadro_1!$J$8,IFM[[AÑO]:[AÑO]],Cuadro_1!$L$8)*100),0) -> 0 | G19: =IFERROR((SUMIFS(IFM[[Comisiones]:[Comisiones]],IFM[[Nombre Empresa]:[Nombre Empresa]],$C19,IFM[[MES]:[MES]],Cuadro_1!$J$8,IFM[[AÑO]:[AÑO]],Cuadro_1!$L$8)/SUMIFS(IFM[[PrimasNetasCobradas]:[PrimasNetasCobradas]],IFM[[Nombre Empresa]:[Nombre Empresa]],$C19,IFM[[MES]:[MES]],Cuadro_1!$J$8,IFM[[AÑO]:[AÑO]],Cuadro_1!$L$8)*100),0) -> 0 | H19: =IFERROR((SUMIFS(IFM[[GastosdeAdquision]:[GastosdeAdquision]],IFM[[Nombre Empresa]:[Nombre Empresa]],$C19,IFM[[MES]:[MES]],Cuadro_1!$J$8,IFM[[AÑO]:[AÑO]],Cuadro_1!$L$8)/SUMIFS(IFM[[PrimasNetasCobradas]:[PrimasNetasCobradas]],IFM[[Nombre Empresa]:[Nombre Empresa]],$C19,IFM[[MES]:[MES]],Cuadro_1!$J$8,IFM[[AÑO]:[AÑO]],Cuadro_1!$L$8)*100),0) -> 0 | I19: =IFERROR((SUMIFS(IFM[[Gastosdeadministracion]:[Gastosdeadministracion]],IFM[[Nombre Empresa]:[Nombre Empresa]],$C19,IFM[[MES]:[MES]],Cuadro_1!$J$8,IFM[[AÑO]:[AÑO]],Cuadro_1!$L$8)/SUMIFS(IFM[[PrimasNetasCobradas]:[PrimasNetasCobradas]],IFM[[Nombre Empresa]:[Nombre Empresa]],$C19,IFM[[MES]:[MES]],Cuadro_1!$J$8,IFM[[AÑO]:[AÑO]],Cuadro_1!$L$8)*100),0) -> 0 | J19: =IFERROR((SUMIFS(IFM[[ResultadodelReaseguroCedido]:[ResultadodelReaseguroCedido]],IFM[[Nombre Empresa]:[Nombre Empresa]],$C19,IFM[[MES]:[MES]],Cuadro_1!$J$8,IFM[[AÑO]:[AÑO]],Cuadro_1!$L$8)/SUMIFS(IFM[[Total GeneralPDev]:[Total GeneralPDev]],IFM[[Nombre Empresa]:[Nombre Empresa]],$C19,IFM[[MES]:[MES]],Cuadro_1!$J$8,IFM[[AÑO]:[AÑO]],Cuadro_1!$L$8)*-100),0) -> 0 | K19: =SUM(F19:J19) -> 0 | L19: =IFERROR((SUMIFS(IFM[[InversionesAptas]:[InversionesAptas]],IFM[[Nombre Empresa]:[Nombre Empresa]],$C19,IFM[[MES]:[MES]],Cuadro_1!$J$8,IFM[[AÑO]:[AÑO]],Cuadro_1!$L$8)/SUMIFS(IFM[[ReservasTecnicas]:[ReservasTecnicas]],IFM[[Nombre Empresa]:[Nombre Empresa]],$C19,IFM[[MES]:[MES]],Cuadro_1!$J$8,IFM[[AÑO]:[AÑO]],Cuadro_1!$L$8)),0) -> 0
B20: 8 | C20: Banesco Seguros C.A. | D20: =IFERROR((SUMIFS(IFM[[SiniestrosPagados_NetosdeSalvamento]:[SiniestrosPagados_NetosdeSalvamento]],IFM[[Nombre Empresa]:[Nombre Empresa]],$C20,IFM[[MES]:[MES]],Cuadro_1!$J$8,IFM[[AÑO]:[AÑO]],Cuadro_1!$L$8)/SUMIFS(IFM[[PrimasNetasCobradas]:[PrimasNetasCobradas]],IFM[[Nombre Empresa]:[Nombre Empresa]],$C20,IFM[[MES]:[MES]],Cuadro_1!$J$8,IFM[[AÑO]:[AÑO]],Cuadro_1!$L$8)*100),0) -> 27.428099 | E20: =IFERROR((SUMIFS(IFM[[ReservasdeSiniestrosPendientesBrutas]:[ReservasdeSiniestrosPendientesBrutas]],IFM[[Nombre Empresa]:[Nombre Empresa]],$C20,IFM[[MES]:[MES]],Cuadro_1!$J$8,IFM[[AÑO]:[AÑO]],Cuadro_1!$L$8)/SUMIFS(IFM[[PrimasNetasCobradas]:[PrimasNetasCobradas]],IFM[[Nombre Empresa]:[Nombre Empresa]],$C20,IFM[[MES]:[MES]],Cuadro_1!$J$8,IFM[[AÑO]:[AÑO]],Cuadro_1!$L$8)*100),0) -> 11.556183 | F20: =IFERROR((SUMIFS(IFM[[TotalGenralSI]:[TotalGenralSI]],IFM[[Nombre Empresa]:[Nombre Empresa]],$C20,IFM[[MES]:[MES]],Cuadro_1!$J$8,IFM[[AÑO]:[AÑO]],Cuadro_1!$L$8)/SUMIFS(IFM[[Total GeneralPDev]:[Total GeneralPDev]],IFM[[Nombre Empresa]:[Nombre Empresa]],$C20,IFM[[MES]:[MES]],Cuadro_1!$J$8,IFM[[AÑO]:[AÑO]],Cuadro_1!$L$8)*100),0) -> 35.704457 | G20: =IFERROR((SUMIFS(IFM[[Comisiones]:[Comisiones]],IFM[[Nombre Empresa]:[Nombre Empresa]],$C20,IFM[[MES]:[MES]],Cuadro_1!$J$8,IFM[[AÑO]:[AÑO]],Cuadro_1!$L$8)/SUMIFS(IFM[[PrimasNetasCobradas]:[PrimasNetasCobradas]],IFM[[Nombre Empresa]:[Nombre Empresa]],$C20,IFM[[MES]:[MES]],Cuadro_1!$J$8,IFM[[AÑO]:[AÑO]],Cuadro_1!$L$8)*100),0) -> 9.5796998 | H20: =IFERROR((SUMIFS(IFM[[GastosdeAdquision]:[GastosdeAdquision]],IFM[[Nombre Empresa]:[Nombre Empresa]],$C20,IFM[[MES]:[MES]],Cuadro_1!$J$8,IFM[[AÑO]:[AÑO]],Cuadro_1!$L$8)/SUMIFS(IFM[[PrimasNetasCobradas]:[PrimasNetasCobradas]],IFM[[Nombre Empresa]:[Nombre Empresa]],$C20,IFM[[MES]:[MES]],Cuadro_1!$J$8,IFM[[AÑO]:[AÑO]],Cuadro_1!$L$8)*100),0) -> 3.0800651 | I20: =IFERROR((SUMIFS(IFM[[Gastosdeadministracion]:[Gastosdeadministracion]],IFM[[Nombre Empresa]:[Nombre Empresa]],$C20,IFM[[MES]:[MES]],Cuadro_1!$J$8,IFM[[AÑO]:[AÑO]],Cuadro_1!$L$8)/SUMIFS(IFM[[PrimasNetasCobradas]:[PrimasNetasCobradas]],IFM[[Nombre Empresa]:[Nombre Empresa]],$C20,IFM[[MES]:[MES]],Cuadro_1!$J$8,IFM[[AÑO]:[AÑO]],Cuadro_1!$L$8)*100),0) -> 27.799363 | J20: =IFERROR((SUMIFS(IFM[[ResultadodelReaseguroCedido]:[ResultadodelReaseguroCedido]],IFM[[Nombre Empresa]:[Nombre Empresa]],$C20,IFM[[MES]:[MES]],Cuadro_1!$J$8,IFM[[AÑO]:[AÑO]],Cuadro_1!$L$8)/SUMIFS(IFM[[Total GeneralPDev]:[Total GeneralPDev]],IFM[[Nombre Empresa]:[Nombre Empresa]],$C20,IFM[[MES]:[MES]],Cuadro_1!$J$8,IFM[[AÑO]:[AÑO]],Cuadro_1!$L$8)*-100),0) -> 8.786559 | K20: =SUM(F20:J20) -> 84.950145 | L20: =IFERROR((SUMIFS(IFM[[InversionesAptas]:[InversionesAptas]],IFM[[Nombre Empresa]:[Nombre Empresa]],$C20,IFM[[MES]:[MES]],Cuadro_1!$J$8,IFM[[AÑO]:[AÑO]],Cuadro_1!$L$8)/SUMIFS(IFM[[ReservasTecnicas]:[ReservasTecnicas]],IFM[[Nombre Empresa]:[Nombre Empresa]],$C20,IFM[[MES]:[MES]],Cuadro_1!$J$8,IFM[[AÑO]:[AÑO]],Cuadro_1!$L$8)),0) -> 5.3670878
B21: 9 | C21: BBVA Seguros,C.A. | D21: =IFERROR((SUMIFS(IFM[[SiniestrosPagados_NetosdeSalvamento]:[SiniestrosPagados_NetosdeSalvamento]],IFM[[Nombre Empresa]:[Nombre Empresa]],$C21,IFM[[MES]:[MES]],Cuadro_1!$J$8,IFM[[AÑO]:[AÑO]],Cuadro_1!$L$8)/SUMIFS(IFM[[PrimasNetasCobradas]:[PrimasNetasCobradas]],IFM[[Nombre Empresa]:[Nombre Empresa]],$C21,IFM[[MES]:[MES]],Cuadro_1!$J$8,IFM[[AÑO]:[AÑO]],Cuadro_1!$L$8)*100),0) -> 23.288854 | E21: =IFERROR((SUMIFS(IFM[[ReservasdeSiniestrosPendientesBrutas]:[ReservasdeSiniestrosPendientesBrutas]],IFM[[Nombre Empresa]:[Nombre Empresa]],$C21,IFM[[MES]:[MES]],Cuadro_1!$J$8,IFM[[AÑO]:[AÑO]],Cuadro_1!$L$8)/SUMIFS(IFM[[PrimasNetasCobradas]:[PrimasNetasCobradas]],IFM[[Nombre Empresa]:[Nombre Empresa]],$C21,IFM[[MES]:[MES]],Cuadro_1!$J$8,IFM[[AÑO]:[AÑO]],Cuadro_1!$L$8)*100),0) -> 2.8459439 | F21: =IFERROR((SUMIFS(IFM[[TotalGenralSI]:[TotalGenralSI]],IFM[[Nombre Empresa]:[Nombre Empresa]],$C21,IFM[[MES]:[MES]],Cuadro_1!$J$8,IFM[[AÑO]:[AÑO]],Cuadro_1!$L$8)/SUMIFS(IFM[[Total GeneralPDev]:[Total GeneralPDev]],IFM[[Nombre Empresa]:[Nombre Empresa]],$C21,IFM[[MES]:[MES]],Cuadro_1!$J$8,IFM[[AÑO]:[AÑO]],Cuadro_1!$L$8)*100),0) -> 26.930125 | G21: =IFERROR((SUMIFS(IFM[[Comisiones]:[Comisiones]],IFM[[Nombre Empresa]:[Nombre Empresa]],$C21,IFM[[MES]:[MES]],Cuadro_1!$J$8,IFM[[AÑO]:[AÑO]],Cuadro_1!$L$8)/SUMIFS(IFM[[PrimasNetasCobradas]:[PrimasNetasCobradas]],IFM[[Nombre Empresa]:[Nombre Empresa]],$C21,IFM[[MES]:[MES]],Cuadro_1!$J$8,IFM[[AÑO]:[AÑO]],Cuadro_1!$L$8)*100),0) -> 0 | H21: =IFERROR((SUMIFS(IFM[[GastosdeAdquision]:[GastosdeAdquision]],IFM[[Nombre Empresa]:[Nombre Empresa]],$C21,IFM[[MES]:[MES]],Cuadro_1!$J$8,IFM[[AÑO]:[AÑO]],Cuadro_1!$L$8)/SUMIFS(IFM[[PrimasNetasCobradas]:[PrimasNetasCobradas]],IFM[[Nombre Empresa]:[Nombre Empresa]],$C21,IFM[[MES]:[MES]],Cuadro_1!$J$8,IFM[[AÑO]:[AÑO]],Cuadro_1!$L$8)*100),0) -> 0 | I21: =IFERROR((SUMIFS(IFM[[Gastosdeadministracion]:[Gastosdeadministracion]],IFM[[Nombre Empresa]:[Nombre Empresa]],$C21,IFM[[MES]:[MES]],Cuadro_1!$J$8,IFM[[AÑO]:[AÑO]],Cuadro_1!$L$8)/SUMIFS(IFM[[PrimasNetasCobradas]:[PrimasNetasCobradas]],IFM[[Nombre Empresa]:[Nombre Empresa]],$C21,IFM[[MES]:[MES]],Cuadro_1!$J$8,IFM[[AÑO]:[AÑO]],Cuadro_1!$L$8)*100),0) -> 76.381758 | J21: =IFERROR((SUMIFS(IFM[[ResultadodelReaseguroCedido]:[ResultadodelReaseguroCedido]],IFM[[Nombre Empresa]:[Nombre Empresa]],$C21,IFM[[MES]:[MES]],Cuadro_1!$J$8,IFM[[AÑO]:[AÑO]],Cuadro_1!$L$8)/SUMIFS(IFM[[Total GeneralPDev]:[Total GeneralPDev]],IFM[[Nombre Empresa]:[Nombre Empresa]],$C21,IFM[[MES]:[MES]],Cuadro_1!$J$8,IFM[[AÑO]:[AÑO]],Cuadro_1!$L$8)*-100),0) -> 0.19937056 | K21: =SUM(F21:J21) -> 103.51125 | L21: =IFERROR((SUMIFS(IFM[[InversionesAptas]:[InversionesAptas]],IFM[[Nombre Empresa]:[Nombre Empresa]],$C21,IFM[[MES]:[MES]],Cuadro_1!$J$8,IFM[[AÑO]:[AÑO]],Cuadro_1!$L$8)/SUMIFS(IFM[[ReservasTecnicas]:[ReservasTecnicas]],IFM[[Nombre Empresa]:[Nombre Empresa]],$C21,IFM[[MES]:[MES]],Cuadro_1!$J$8,IFM[[AÑO]:[AÑO]],Cuadro_1!$L$8)),0) -> 1.3369648
B22: 10 | C22: Bolivariana de Seguros y Reaseguros, S.A. | D22: =IFERROR((SUMIFS(IFM[[SiniestrosPagados_NetosdeSalvamento]:[SiniestrosPagados_NetosdeSalvamento]],IFM[[Nombre Empresa]:[Nombre Empresa]],$C22,IFM[[MES]:[MES]],Cuadro_1!$J$8,IFM[[AÑO]:[AÑO]],Cuadro_1!$L$8)/SUMIFS(IFM[[PrimasNetasCobradas]:[PrimasNetasCobradas]],IFM[[Nombre Empresa]:[Nombre Empresa]],$C22,IFM[[MES]:[MES]],Cuadro_1!$J$8,IFM[[AÑO]:[AÑO]],Cuadro_1!$L$8)*100),0) -> 0 | E22: =IFERROR((SUMIFS(IFM[[ReservasdeSiniestrosPendientesBrutas]:[ReservasdeSiniestrosPendientesBrutas]],IFM[[Nombre Empresa]:[Nombre Empresa]],$C22,IFM[[MES]:[MES]],Cuadro_1!$J$8,IFM[[AÑO]:[AÑO]],Cuadro_1!$L$8)/SUMIFS(IFM[[PrimasNetasCobradas]:[PrimasNetasCobradas]],IFM[[Nombre Empresa]:[Nombre Empresa]],$C22,IFM[[MES]:[MES]],Cuadro_1!$J$8,IFM[[AÑO]:[AÑO]],Cuadro_1!$L$8)*100),0) -> 0.0022172032 | F22: =IFERROR((SUMIFS(IFM[[TotalGenralSI]:[TotalGenralSI]],IFM[[Nombre Empresa]:[Nombre Empresa]],$C22,IFM[[MES]:[MES]],Cuadro_1!$J$8,IFM[[AÑO]:[AÑO]],Cuadro_1!$L$8)/SUMIFS(IFM[[Total GeneralPDev]:[Total GeneralPDev]],IFM[[Nombre Empresa]:[Nombre Empresa]],$C22,IFM[[MES]:[MES]],Cuadro_1!$J$8,IFM[[AÑO]:[AÑO]],Cuadro_1!$L$8)*100),0) -> 0 | G22: =IFERROR((SUMIFS(IFM[[Comisiones]:[Comisiones]],IFM[[Nombre Empresa]:[Nombre Empresa]],$C22,IFM[[MES]:[MES]],Cuadro_1!$J$8,IFM[[AÑO]:[AÑO]],Cuadro_1!$L$8)/SUMIFS(IFM[[PrimasNetasCobradas]:[PrimasNetasCobradas]],IFM[[Nombre Empresa]:[Nombre Empresa]],$C22,IFM[[MES]:[MES]],Cuadro_1!$J$8,IFM[[AÑO]:[AÑO]],Cuadro_1!$L$8)*100),0) -> 0 | H22: =IFERROR((SUMIFS(IFM[[GastosdeAdquision]:[GastosdeAdquision]],IFM[[Nombre Empresa]:[Nombre Empresa]],$C22,IFM[[MES]:[MES]],Cuadro_1!$J$8,IFM[[AÑO]:[AÑO]],Cuadro_1!$L$8)/SUMIFS(IFM[[PrimasNetasCobradas]:[PrimasNetasCobradas]],IFM[[Nombre Empresa]:[Nombre Empresa]],$C22,IFM[[MES]:[MES]],Cuadro_1!$J$8,IFM[[AÑO]:[AÑO]],Cuadro_1!$L$8)*100),0) -> 0 | I22: =IFERROR((SUMIFS(IFM[[Gastosdeadministracion]:[Gastosdeadministracion]],IFM[[Nombre Empresa]:[Nombre Empresa]],$C22,IFM[[MES]:[MES]],Cuadro_1!$J$8,IFM[[AÑO]:[AÑO]],Cuadro_1!$L$8)/SUMIFS(IFM[[PrimasNetasCobradas]:[PrimasNetasCobradas]],IFM[[Nombre Empresa]:[Nombre Empresa]],$C22,IFM[[MES]:[MES]],Cuadro_1!$J$8,IFM[[AÑO]:[AÑO]],Cuadro_1!$L$8)*100),0) -> 29.449312 | J22: =IFERROR((SUMIFS(IFM[[ResultadodelReaseguroCedido]:[ResultadodelReaseguroCedido]],IFM[[Nombre Empresa]:[Nombre Empresa]],$C22,IFM[[MES]:[MES]],Cuadro_1!$J$8,IFM[[AÑO]:[AÑO]],Cuadro_1!$L$8)/SUMIFS(IFM[[Total GeneralPDev]:[Total GeneralPDev]],IFM[[Nombre Empresa]:[Nombre Empresa]],$C22,IFM[[MES]:[MES]],Cuadro_1!$J$8,IFM[[AÑO]:[AÑO]],Cuadro_1!$L$8)*-100),0) -> 60.351385 | K22: =SUM(F22:J22) -> 89.800698 | L22: =IFERROR((SUMIFS(IFM[[InversionesAptas]:[InversionesAptas]],IFM[[Nombre Empresa]:[Nombre Empresa]],$C22,IFM[[MES]:[MES]],Cuadro_1!$J$8,IFM[[AÑO]:[AÑO]],Cuadro_1!$L$8)/SUMIFS(IFM[[ReservasTecnicas]:[ReservasTecnicas]],IFM[[Nombre Empresa]:[Nombre Empresa]],$C22,IFM[[MES]:[MES]],Cuadro_1!$J$8,IFM[[AÑO]:[AÑO]],Cuadro_1!$L$8)),0) -> 6211.0473
B23: 11 | C23: Capital, C.A. Seguros | D23: =IFERROR((SUMIFS(IFM[[SiniestrosPagados_NetosdeSalvamento]:[SiniestrosPagados_NetosdeSalvamento]],IFM[[Nombre Empresa]:[Nombre Empresa]],$C23,IFM[[MES]:[MES]],Cuadro_1!$J$8,IFM[[AÑO]:[AÑO]],Cuadro_1!$L$8)/SUMIFS(IFM[[PrimasNetasCobradas]:[PrimasNetasCobradas]],IFM[[Nombre Empresa]:[Nombre Empresa]],$C23,IFM[[MES]:[MES]],Cuadro_1!$J$8,IFM[[AÑO]:[AÑO]],Cuadro_1!$L$8)*100),0) -> 0.41541975 | E23: =IFERROR((SUMIFS(IFM[[ReservasdeSiniestrosPendientesBrutas]:[ReservasdeSiniestrosPendientesBrutas]],IFM[[Nombre Empresa]:[Nombre Empresa]],$C23,IFM[[MES]:[MES]],Cuadro_1!$J$8,IFM[[AÑO]:[AÑO]],Cuadro_1!$L$8)/SUMIFS(IFM[[PrimasNetasCobradas]:[PrimasNetasCobradas]],IFM[[Nombre Empresa]:[Nombre Empresa]],$C23,IFM[[MES]:[MES]],Cuadro_1!$J$8,IFM[[AÑO]:[AÑO]],Cuadro_1!$L$8)*100),0) -> 0.086861255 | F23: =IFERROR((SUMIFS(IFM[[TotalGenralSI]:[TotalGenralSI]],IFM[[Nombre Empresa]:[Nombre Empresa]],$C23,IFM[[MES]:[MES]],Cuadro_1!$J$8,IFM[[AÑO]:[AÑO]],Cuadro_1!$L$8)/SUMIFS(IFM[[Total GeneralPDev]:[Total GeneralPDev]],IFM[[Nombre Empresa]:[Nombre Empresa]],$C23,IFM[[MES]:[MES]],Cuadro_1!$J$8,IFM[[AÑO]:[AÑO]],Cuadro_1!$L$8)*100),0) -> 0.22209403 | G23: =IFERROR((SUMIFS(IFM[[Comisiones]:[Comisiones]],IFM[[Nombre Empresa]:[Nombre Empresa]],$C23,IFM[[MES]:[MES]],Cuadro_1!$J$8,IFM[[AÑO]:[AÑO]],Cuadro_1!$L$8)/SUMIFS(IFM[[PrimasNetasCobradas]:[PrimasNetasCobradas]],IFM[[Nombre Empresa]:[Nombre Empresa]],$C23,IFM[[MES]:[MES]],Cuadro_1!$J$8,IFM[[AÑO]:[AÑO]],Cuadro_1!$L$8)*100),0) -> 0.066539605 | H23: =IFERROR((SUMIFS(IFM[[GastosdeAdquision]:[GastosdeAdquision]],IFM[[Nombre Empresa]:[Nombre Empresa]],$C23,IFM[[MES]:[MES]],Cuadro_1!$J$8,IFM[[AÑO]:[AÑO]],Cuadro_1!$L$8)/SUMIFS(IFM[[PrimasNetasCobradas]:[PrimasNetasCobradas]],IFM[[Nombre Empresa]:[Nombre Empresa]],$C23,IFM[[MES]:[MES]],Cuadro_1!$J$8,IFM[[AÑO]:[AÑO]],Cuadro_1!$L$8)*100),0) -> 0.0083139792 | I23: =IFERROR((SUMIFS(IFM[[Gastosdeadministracion]:[Gastosdeadministracion]],IFM[[Nombre Empresa]:[Nombre Empresa]],$C23,IFM[[MES]:[MES]],Cuadro_1!$J$8,IFM[[AÑO]:[AÑO]],Cuadro_1!$L$8)/SUMIFS(IFM[[PrimasNetasCobradas]:[PrimasNetasCobradas]],IFM[[Nombre Empresa]:[Nombre Empresa]],$C23,IFM[[MES]:[MES]],Cuadro_1!$J$8,IFM[[AÑO]:[AÑO]],Cuadro_1!$L$8)*100),0) -> 10.879758 | J23: =IFERROR((SUMIFS(IFM[[ResultadodelReaseguroCedido]:[ResultadodelReaseguroCedido]],IFM[[Nombre Empresa]:[Nombre Empresa]],$C23,IFM[[MES]:[MES]],Cuadro_1!$J$8,IFM[[AÑO]:[AÑO]],Cuadro_1!$L$8)/SUMIFS(IFM[[Total GeneralPDev]:[Total GeneralPDev]],IFM[[Nombre Empresa]:[Nombre Empresa]],$C23,IFM[[MES]:[MES]],Cuadro_1!$J$8,IFM[[AÑO]:[AÑO]],Cuadro_1!$L$8)*-100),0) -> 93.21752 | K23: =SUM(F23:J23) -> 104.39423 | L23: =IFERROR((SUMIFS(IFM[[InversionesAptas]:[InversionesAptas]],IFM[[Nombre Empresa]:[Nombre Empresa]],$C23,IFM[[MES]:[MES]],Cuadro_1!$J$8,IFM[[AÑO]:[AÑO]],Cuadro_1!$L$8)/SUMIFS(IFM[[ReservasTecnicas]:[ReservasTecnicas]],IFM[[Nombre Empresa]:[Nombre Empresa]],$C23,IFM[[MES]:[MES]],Cuadro_1!$J$8,IFM[[AÑO]:[AÑO]],Cuadro_1!$L$8)),0) -> 8.9460862
B24: 12 | C24: Carabobo C.A., Seguros | D24: =IFERROR((SUMIFS(IFM[[SiniestrosPagados_NetosdeSalvamento]:[SiniestrosPagados_NetosdeSalvamento]],IFM[[Nombre Empresa]:[Nombre Empresa]],$C24,IFM[[MES]:[MES]],Cuadro_1!$J$8,IFM[[AÑO]:[AÑO]],Cuadro_1!$L$8)/SUMIFS(IFM[[PrimasNetasCobradas]:[PrimasNetasCobradas]],IFM[[Nombre Empresa]:[Nombre Empresa]],$C24,IFM[[MES]:[MES]],Cuadro_1!$J$8,IFM[[AÑO]:[AÑO]],Cuadro_1!$L$8)*100),0) -> 0 | E24: =IFERROR((SUMIFS(IFM[[ReservasdeSiniestrosPendientesBrutas]:[ReservasdeSiniestrosPendientesBrutas]],IFM[[Nombre Empresa]:[Nombre Empresa]],$C24,IFM[[MES]:[MES]],Cuadro_1!$J$8,IFM[[AÑO]:[AÑO]],Cuadro_1!$L$8)/SUMIFS(IFM[[PrimasNetasCobradas]:[PrimasNetasCobradas]],IFM[[Nombre Empresa]:[Nombre Empresa]],$C24,IFM[[MES]:[MES]],Cuadro_1!$J$8,IFM[[AÑO]:[AÑO]],Cuadro_1!$L$8)*100),0) -> 0 | F24: =IFERROR((SUMIFS(IFM[[TotalGenralSI]:[TotalGenralSI]],IFM[[Nombre Empresa]:[Nombre Empresa]],$C24,IFM[[MES]:[MES]],Cuadro_1!$J$8,IFM[[AÑO]:[AÑO]],Cuadro_1!$L$8)/SUMIFS(IFM[[Total GeneralPDev]:[Total GeneralPDev]],IFM[[Nombre Empresa]:[Nombre Empresa]],$C24,IFM[[MES]:[MES]],Cuadro_1!$J$8,IFM[[AÑO]:[AÑO]],Cuadro_1!$L$8)*100),0) -> 0 | G24: =IFERROR((SUMIFS(IFM[[Comisiones]:[Comisiones]],IFM[[Nombre Empresa]:[Nombre Empresa]],$C24,IFM[[MES]:[MES]],Cuadro_1!$J$8,IFM[[AÑO]:[AÑO]],Cuadro_1!$L$8)/SUMIFS(IFM[[PrimasNetasCobradas]:[PrimasNetasCobradas]],IFM[[Nombre Empresa]:[Nombre Empresa]],$C24,IFM[[MES]:[MES]],Cuadro_1!$J$8,IFM[[AÑO]:[AÑO]],Cuadro_1!$L$8)*100),0) -> 0 | H24: =IFERROR((SUMIFS(IFM[[GastosdeAdquision]:[GastosdeAdquision]],IFM[[Nombre Empresa]:[Nombre Empresa]],$C24,IFM[[MES]:[MES]],Cuadro_1!$J$8,IFM[[AÑO]:[AÑO]],Cuadro_1!$L$8)/SUMIFS(IFM[[PrimasNetasCobradas]:[PrimasNetasCobradas]],IFM[[Nombre Empresa]:[Nombre Empresa]],$C24,IFM[[MES]:[MES]],Cuadro_1!$J$8,IFM[[AÑO]:[AÑO]],Cuadro_1!$L$8)*100),0) -> 0 | I24: =IFERROR((SUMIFS(IFM[[Gastosdeadministracion]:[Gastosdeadministracion]],IFM[[Nombre Empresa]:[Nombre Empresa]],$C24,IFM[[MES]:[MES]],Cuadro_1!$J$8,IFM[[AÑO]:[AÑO]],Cuadro_1!$L$8)/SUMIFS(IFM[[PrimasNetasCobradas]:[PrimasNetasCobradas]],IFM[[Nombre Empresa]:[Nombre Empresa]],$C24,IFM[[MES]:[MES]],Cuadro_1!$J$8,IFM[[AÑO]:[AÑO]],Cuadro_1!$L$8)*100),0) -> 0 | J24: =IFERROR((SUMIFS(IFM[[ResultadodelReaseguroCedido]:[ResultadodelReaseguroCedido]],IFM[[Nombre Empresa]:[Nombre Empresa]],$C24,IFM[[MES]:[MES]],Cuadro_1!$J$8,IFM[[AÑO]:[AÑO]],Cuadro_1!$L$8)/SUMIFS(IFM[[Total GeneralPDev]:[Total GeneralPDev]],IFM[[Nombre Empresa]:[Nombre Empresa]],$C24,IFM[[MES]:[MES]],Cuadro_1!$J$8,IFM[[AÑO]:[AÑO]],Cuadro_1!$L$8)*-100),0) -> 0 | K24: =SUM(F24:J24) -> 0 | L24: =IFERROR((SUMIFS(IFM[[InversionesAptas]:[InversionesAptas]],IFM[[Nombre Empresa]:[Nombre Empresa]],$C24,IFM[[MES]:[MES]],Cuadro_1!$J$8,IFM[[AÑO]:[AÑO]],Cuadro_1!$L$8)/SUMIFS(IFM[[ReservasTecnicas]:[ReservasTecnicas]],IFM[[Nombre Empresa]:[Nombre Empresa]],$C24,IFM[[MES]:[MES]],Cuadro_1!$J$8,IFM[[AÑO]:[AÑO]],Cuadro_1!$L$8)),0) -> 0
... B63: 51 | C63: Zuma Seguros, C.A. | D63: =IFERROR((SUMIFS(IFM[[SiniestrosPagados_NetosdeSalvamento]:[SiniestrosPagados_NetosdeSalvamento]],IFM[[Nombre Empresa]:[Nombre Empresa]],$C63,IFM[[MES]:[MES]],Cuadro_1!$J$8,IFM[[AÑO]:[AÑO]],Cuadro_1!$L$8)/SUMIFS(IFM[[PrimasNetasCobradas]:[PrimasNetasCobradas]],IFM[[Nombre Empresa]:[Nombre Empresa]],$C63,IFM[[MES]:[MES]],Cuadro_1!$J$8,IFM[[AÑO]:[AÑO]],Cuadro_1!$L$8)*100),0) -> 0.046257474 | E63: =IFERROR((SUMIFS(IFM[[ReservasdeSiniestrosPendientesBrutas]:[ReservasdeSiniestrosPendientesBrutas]],IFM[[Nombre Empresa]:[Nombre Empresa]],$C63,IFM[[MES]:[MES]],Cuadro_1!$J$8,IFM[[AÑO]:[AÑO]],Cuadro_1!$L$8)/SUMIFS(IFM[[PrimasNetasCobradas]:[PrimasNetasCobradas]],IFM[[Nombre Empresa]:[Nombre Empresa]],$C63,IFM[[MES]:[MES]],Cuadro_1!$J$8,IFM[[AÑO]:[AÑO]],Cuadro_1!$L$8)*100),0) -> 0.00088076898 | F63: =IFERROR((SUMIFS(IFM[[TotalGenralSI]:[TotalGenralSI]],IFM[[Nombre Empresa]:[Nombre Empresa]],$C63,IFM[[MES]:[MES]],Cuadro_1!$J$8,IFM[[AÑO]:[AÑO]],Cuadro_1!$L$8)/SUMIFS(IFM[[Total GeneralPDev]:[Total GeneralPDev]],IFM[[Nombre Empresa]:[Nombre Empresa]],$C63,IFM[[MES]:[MES]],Cuadro_1!$J$8,IFM[[AÑO]:[AÑO]],Cuadro_1!$L$8)*100),0) -> 0.070748736 | G63: =IFERROR((SUMIFS(IFM[[Comisiones]:[Comisiones]],IFM[[Nombre Empresa]:[Nombre Empresa]],$C63,IFM[[MES]:[MES]],Cuadro_1!$J$8,IFM[[AÑO]:[AÑO]],Cuadro_1!$L$8)/SUMIFS(IFM[[PrimasNetasCobradas]:[PrimasNetasCobradas]],IFM[[Nombre Empresa]:[Nombre Empresa]],$C63,IFM[[MES]:[MES]],Cuadro_1!$J$8,IFM[[AÑO]:[AÑO]],Cuadro_1!$L$8)*100),0) -> 13.475902 | H63: =IFERROR((SUMIFS(IFM[[GastosdeAdquision]:[GastosdeAdquision]],IFM[[Nombre Empresa]:[Nombre Empresa]],$C63,IFM[[MES]:[MES]],Cuadro_1!$J$8,IFM[[AÑO]:[AÑO]],Cuadro_1!$L$8)/SUMIFS(IFM[[PrimasNetasCobradas]:[PrimasNetasCobradas]],IFM[[Nombre Empresa]:[Nombre Empresa]],$C63,IFM[[MES]:[MES]],Cuadro_1!$J$8,IFM[[AÑO]:[AÑO]],Cuadro_1!$L$8)*100),0) -> 13.970247 | I63: =IFERROR((SUMIFS(IFM[[Gastosdeadministracion]:[Gastosdeadministracion]],IFM[[Nombre Empresa]:[Nombre Empresa]],$C63,IFM[[MES]:[MES]],Cuadro_1!$J$8,IFM[[AÑO]:[AÑO]],Cuadro_1!$L$8)/SUMIFS(IFM[[PrimasNetasCobradas]:[PrimasNetasCobradas]],IFM[[Nombre Empresa]:[Nombre Empresa]],$C63,IFM[[MES]:[MES]],Cuadro_1!$J$8,IFM[[AÑO]:[AÑO]],Cuadro_1!$L$8)*100),0) -> 76.840769 | J63: =IFERROR((SUMIFS(IFM[[ResultadodelReaseguroCedido]:[ResultadodelReaseguroCedido]],IFM[[Nombre Empresa]:[Nombre Empresa]],$C63,IFM[[MES]:[MES]],Cuadro_1!$J$8,IFM[[AÑO]:[AÑO]],Cuadro_1!$L$8)/SUMIFS(IFM[[Total GeneralPDev]:[Total GeneralPDev]],IFM[[Nombre Empresa]:[Nombre Empresa]],$C63,IFM[[MES]:[MES]],Cuadro_1!$J$8,IFM[[AÑO]:[AÑO]],Cuadro_1!$L$8)*-100),0) -> 4.4134954 | K63: =SUM(F63:J63) -> 108.77116 | L63: =IFERROR((SUMIFS(IFM[[InversionesAptas]:[InversionesAptas]],IFM[[Nombre Empresa]:[Nombre Empresa]],$C63,IFM[[MES]:[MES]],Cuadro_1!$J$8,IFM[[AÑO]:[AÑO]],Cuadro_1!$L$8)/SUMIFS(IFM[[ReservasTecnicas]:[ReservasTecnicas]],IFM[[Nombre Empresa]:[Nombre Empresa]],$C63,IFM[[MES]:[MES]],Cuadro_1!$J$8,IFM[[AÑO]:[AÑO]],Cuadro_1!$L$8)),0) -> 6.7722578
B64: TOTAL (En Miles de Bs..) | C64: TOTAL | D64: =IFERROR((SUMIFS(IFM[[SiniestrosPagados_NetosdeSalvamento]:[SiniestrosPagados_NetosdeSalvamento]],IFM[[MES]:[MES]],Cuadro_1!$J$8,IFM[[AÑO]:[AÑO]],Cuadro_1!$L$8)/SUMIFS(IFM[[PrimasNetasCobradas]:[PrimasNetasCobradas]],IFM[[MES]:[MES]],Cuadro_1!$J$8,IFM[[AÑO]:[AÑO]],Cuadro_1!$L$8)*100),0) -> 38.839031 | E64: =IFERROR((SUMIFS(IFM[[ReservasdeSiniestrosPendientesBrutas]:[ReservasdeSiniestrosPendientesBrutas]],IFM[[MES]:[MES]],Cuadro_1!$J$8,IFM[[AÑO]:[AÑO]],Cuadro_1!$L$8)/SUMIFS(IFM[[PrimasNetasCobradas]:[PrimasNetasCobradas]],IFM[[MES]:[MES]],Cuadro_1!$J$8,IFM[[AÑO]:[AÑO]],Cuadro_1!$L$8)*100),0) -> 19.671491 | F64: =IFERROR((SUMIFS(IFM[[TotalGenralSI]:[TotalGenralSI]],IFM[[MES]:[MES]],Cuadro_1!$J$8,IFM[[AÑO]:[AÑO]],Cuadro_1!$L$8)/SUMIFS(IFM[[Total GeneralPDev]:[Total GeneralPDev]],IFM[[MES]:[MES]],Cuadro_1!$J$8,IFM[[AÑO]:[AÑO]],Cuadro_1!$L$8)*100),0) -> 59.655927 | G64: =IFERROR((SUMIFS(IFM[[Comisiones]:[Comisiones]],IFM[[MES]:[MES]],Cuadro_1!$J$8,IFM[[AÑO]:[AÑO]],Cuadro_1!$L$8)/SUMIFS(IFM[[PrimasNetasCobradas]:[PrimasNetasCobradas]],IFM[[MES]:[MES]],Cuadro_1!$J$8,IFM[[AÑO]:[AÑO]],Cuadro_1!$L$8)*100),0) -> 8.7630522 | H64: =IFERROR((SUMIFS(IFM[[GastosdeAdquision]:[GastosdeAdquision]],IFM[[MES]:[MES]],Cuadro_1!$J$8,IFM[[AÑO]:[AÑO]],Cuadro_1!$L$8)/SUMIFS(IFM[[PrimasNetasCobradas]:[PrimasNetasCobradas]],IFM[[MES]:[MES]],Cuadro_1!$J$8,IFM[[AÑO]:[AÑO]],Cuadro_1!$L$8)*100),0) -> 4.9934203 | I64: =IFERROR((SUMIFS(IFM[[Gastosdeadministracion]:[Gastosdeadministracion]],IFM[[MES]:[MES]],Cuadro_1!$J$8,IFM[[AÑO]:[AÑO]],Cuadro_1!$L$8)/SUMIFS(IFM[[PrimasNetasCobradas]:[PrimasNetasCobradas]],IFM[[MES]:[MES]],Cuadro_1!$J$8,IFM[[AÑO]:[AÑO]],Cuadro_1!$L$8)*100),0) -> 21.973327 | J64: =IFERROR((SUMIFS(IFM[[ResultadodelReaseguroCedido]:[ResultadodelReaseguroCedido]],IFM[[MES]:[MES]],Cuadro_1!$J$8,IFM[[AÑO]:[AÑO]],Cuadro_1!$L$8)/SUMIFS(IFM[[Total GeneralPDev]:[Total GeneralPDev]],IFM[[MES]:[MES]],Cuadro_1!$J$8,IFM[[AÑO]:[AÑO]],Cuadro_1!$L$8)*-100),0) -> 5.1907394 | K64: =SUM(F64:J64) -> 100.57647 | L64: =IFERROR((SUMIFS(IFM[[InversionesAptas]:[InversionesAptas]],IFM[[MES]:[MES]],Cuadro_1!$J$8,IFM[[AÑO]:[AÑO]],Cuadro_1!$L$8)/SUMIFS(IFM[[ReservasTecnicas]:[ReservasTecnicas]],IFM[[MES]:[MES]],Cuadro_1!$J$8,IFM[[AÑO]:[AÑO]],Cuadro_1!$L$8)),0) -> 3.3062936
B66: TOTAL (En Miles de Bs.) | C66: Fuente: (SEFA) Estados Financieros Analíticos Mensuales. Empresas de Seguros. | L66: Actualizado: 09/07/2025
C67: 1/ A la fecha han consignado los estados financieros analiticos 43 empresas de seguros. 2/ Faltan por procesar los estados financieros analiticos las siguientes empresas: Adriática de Seguros, C.A., Ávila de Seguros C.A., Bolivariana de Seguros y Reaseguros, S.A., Seguros Guayana, Multinacional de Seguros C.A., Interbank Seguros S.A, La Regional C.A., y Seguros Carabobo C.A.
C69: (1) Indica el porcentaje de las primas netas cobradas totales que la empresa aseguradora emplea para desembolsar los importes de las reclamaciones producidas por la ocurrencia de siniestros en su cartera de pólizas, para un periodo determinado. (2) Indica el porcentaje de las primas netas cobradas totales que la empresa aseguradora reserva para desembolsar los futuros importes de las reclamaciones producidas por la ocurrencia de siniestros en su cartera de pólizas, que aún no han sido indemnizadas a una fecha determinada. (3) Indica la proporción de las primas devengadas que la empresa aseguradora emplea para atender los siniestros incurridos, durante un periodo determinado. (4) Indica la proporción de las primas netas cobradas totales que la empresa aseguradora emplea para hacer frente a las comisiones de la intermediación de seguros, durante un periodo determinado. (4) Indica la proporción de las primas netas cobradas totales que la empresa aseguradora emplea para hacer frente a los gastos de adquisición, durante un periodo determinado. (6) Indica la proporción de las primas netas cobradas totales que la empresa aseguradora emplea para hacer frente al costo de sus gastos administrativos totales, representados por los gastos de personal y los gastos generales derivados del desarrollo de su actividad de seguros, durante un periodo determinado. (7) Indica la proporción de las primas devengadas que la empresa aseguradora emplea para operaciones de reaseguro cedido, durante un periodo determinado. (8) La tasa combinada, es la sumatoria de los índices relacionados con siniestros incurridos, comisiones y gastos de adquisición, gastos de administración y costo del reaseguro, si es mayor a 100% indica perdida técnica durante un periodo determinado. (9) El Índice de Cobertura de Reservas es equivalente al cociente entre las Inversiones Aptas para la Representación de las Reservas Técnicas (Cuenta 201) y las Reservas Técnicas (Cuenta 401). Si el índice es mayor o igual que 1, hay suficiencia de cobertura. Habrá insuficiencia de cobertura si el índice es menor que uno.
B71: INFORMACIÓN PRELIMINAR NO AUDITADA POR LA SUPERINTENDENCIA DE LA ACTIVIDAD ASEGURADORA

Sheet Cuadro_4
B1: REPÚBLICA BOLIVARIANA DE VENEZUELA
B2: MINISTERIO DEL PODER POPULAR DE ECONOMíA Y FINANZAS | F2: CUADRO 4
B3: SUPERINTENDENCIA DE LA ACTIVIDAD ASEGURADORA
B4: DIRECCIÓN ACTUARIAL / ÁREA DE INVESTIGACIÓN, TRABAJOS ESPECIALES Y ESTADÍSTICAS
B6: INFORMACIÓN FINANCIERA ANALÍTICA MENSUAL DEL MERCADO ASEGURADOR VENEZOLANO
B7: ACUMULADA AL 30 DE JUNIO DE 2025
B8: SALDO DE OPERACIONES POR EMPRESA
B10: Ranking | C10: Empresas de Seguros con Saldo de Operaciones Positivo (Utilidad) | D10: Saldo de Operaciones Positivo (Utilidad) (En Miles de Bs.) | E10: % Saldo de Operaciones por empresa con respecto al Saldo de Operaciones Positivo Total | F10: % Saldo de Operaciones por empresa con respecto al Saldo de Operaciones del Mercado
B13: 1 | C13: Banesco Seguros C.A. | D13: =SUMIFS(IFM[[SaldodeOperaciones]:[SaldodeOperaciones]],IFM[[Nombre Empresa]:[Nombre Empresa]],$C13,IFM[[MES]:[MES]],Cuadro_1!$J$8,IFM[[AÑO]:[AÑO]],Cuadro_1!$L$8)/1000 -> 862380.42 | E13: =+IF(D13>0,D13/$D$64,D13/$D$67)*100 -> 30.25257 | F13: =+D13/$D$68*100 -> 34.970203
B14: 2 | C14: Mapfre La Seguridad, C.A. de Seguros | D14: =SUMIFS(IFM[[SaldodeOperaciones]:[SaldodeOperaciones]],IFM[[Nombre Empresa]:[Nombre Empresa]],$C14,IFM[[MES]:[MES]],Cuadro_1!$J$8,IFM[[AÑO]:[AÑO]],Cuadro_1!$L$8)/1000 -> 284797.87 | E14: =+IF(D14>0,D14/$D$64,D14/$D$67)*100 -> 9.9907964 | F14: =+D14/$D$68*100 -> 11.548777
B15: 3 | C15: BBVA Seguros,C.A. | D15: =SUMIFS(IFM[[SaldodeOperaciones]:[SaldodeOperaciones]],IFM[[Nombre Empresa]:[Nombre Empresa]],$C15,IFM[[MES]:[MES]],Cuadro_1!$J$8,IFM[[AÑO]:[AÑO]],Cuadro_1!$L$8)/1000 -> 289422.65 | E15: =+IF(D15>0,D15/$D$64,D15/$D$67)*100 -> 10.153035 | F15: =+D15/$D$68*100 -> 11.736316
B16: 4 | C16: Venezuela C.A., Seguros | D16: =SUMIFS(IFM[[SaldodeOperaciones]:[SaldodeOperaciones]],IFM[[Nombre Empresa]:[Nombre Empresa]],$C16,IFM[[MES]:[MES]],Cuadro_1!$J$8,IFM[[AÑO]:[AÑO]],Cuadro_1!$L$8)/1000 -> 231391.68 | E16: =+IF(D16>0,D16/$D$64,D16/$D$67)*100 -> 8.1172911 | F16: =+D16/$D$68*100 -> 9.3831143
B17: 5 | C17: Caroní, S.A., Seguros | D17: =SUMIFS(IFM[[SaldodeOperaciones]:[SaldodeOperaciones]],IFM[[Nombre Empresa]:[Nombre Empresa]],$C17,IFM[[MES]:[MES]],Cuadro_1!$J$8,IFM[[AÑO]:[AÑO]],Cuadro_1!$L$8)/1000 -> 62349.864 | E17: =+IF(D17>0,D17/$D$64,D17/$D$67)*100 -> 2.1872523 | F17: =+D17/$D$68*100 -> 2.5283359
B18: 6 | C18: Caracas C.A., Seguros | D18: =SUMIFS(IFM[[SaldodeOperaciones]:[SaldodeOperaciones]],IFM[[Nombre Empresa]:[Nombre Empresa]],$C18,IFM[[MES]:[MES]],Cuadro_1!$J$8,IFM[[AÑO]:[AÑO]],Cuadro_1!$L$8)/1000 -> 125074.34 | E18: =+IF(D18>0,D18/$D$64,D18/$D$67)*100 -> 4.3876461 | F18: =+D18/$D$68*100 -> 5.0718626
B19: 7 | C19: Corporativos C.A., Seguros | D19: =SUMIFS(IFM[[SaldodeOperaciones]:[SaldodeOperaciones]],IFM[[Nombre Empresa]:[Nombre Empresa]],$C19,IFM[[MES]:[MES]],Cuadro_1!$J$8,IFM[[AÑO]:[AÑO]],Cuadro_1!$L$8)/1000 -> 81121.345 | E19: =+IF(D19>0,D19/$D$64,D19/$D$67)*100 -> 2.8457616 | F19: =+D19/$D$68*100 -> 3.2895342
B20: 8 | C20: Mundial de Seguros,C.A. | D20: =SUMIFS(IFM[[SaldodeOperaciones]:[SaldodeOperaciones]],IFM[[Nombre Empresa]:[Nombre Empresa]],$C20,IFM[[MES]:[MES]],Cuadro_1!$J$8,IFM[[AÑO]:[AÑO]],Cuadro_1!$L$8)/1000 -> 13734.183 | E20: =+IF(D20>0,D20/$D$64,D20/$D$67)*100 -> 0.48179933 | F20: =+D20/$D$68*100 -> 0.55693188
B21: 9 | C21: Mercantil C.A., Seguros | D21: =SUMIFS(IFM[[SaldodeOperaciones]:[SaldodeOperaciones]],IFM[[Nombre Empresa]:[Nombre Empresa]],$C21,IFM[[MES]:[MES]],Cuadro_1!$J$8,IFM[[AÑO]:[AÑO]],Cuadro_1!$L$8)/1000 -> 92948.227 | E21: =+IF(D21>0,D21/$D$64,D21/$D$67)*100 -> 3.2606523 | F21: =+D21/$D$68*100 -> 3.7691236
B22: 10 | C22: Latitud Seguros, C.A. | D22: =SUMIFS(IFM[[SaldodeOperaciones]:[SaldodeOperaciones]],IFM[[Nombre Empresa]:[Nombre Empresa]],$C22,IFM[[MES]:[MES]],Cuadro_1!$J$8,IFM[[AÑO]:[AÑO]],Cuadro_1!$L$8)/1000 -> 84456.414 | E22: =+IF(D22>0,D22/$D$64,D22/$D$67)*100 -> 2.9627569 | F22: =+D22/$D$68*100 -> 3.4247739
B23: 11 | C23: Vértice, C.A Seguros | D23: =SUMIFS(IFM[[SaldodeOperaciones]:[SaldodeOperaciones]],IFM[[Nombre Empresa]:[Nombre Empresa]],$C23,IFM[[MES]:[MES]],Cuadro_1!$J$8,IFM[[AÑO]:[AÑO]],Cuadro_1!$L$8)/1000 -> 41770.293 | E23: =+IF(D23>0,D23/$D$64,D23/$D$67)*100 -> 1.4653147 | F23: =+D23/$D$68*100 -> 1.6938182
B24: 12 | C24: Previsora, C.N.A. de Seguros | D24: =SUMIFS(IFM[[SaldodeOperaciones]:[SaldodeOperaciones]],IFM[[Nombre Empresa]:[Nombre Empresa]],$C24,IFM[[MES]:[MES]],Cuadro_1!$J$8,IFM[[AÑO]:[AÑO]],Cuadro_1!$L$8)/1000 -> 29302.189 | E24: =+IF(D24>0,D24/$D$64,D24/$D$67)*100 -> 1.0279298 | F24: =+D24/$D$68*100 -> 1.1882268
... B63: 51 | C63: American International, C.A. de Seguros | D63: =SUMIFS(IFM[[SaldodeOperaciones]:[SaldodeOperaciones]],IFM[[Nombre Empresa]:[Nombre Empresa]],$C63,IFM[[MES]:[MES]],Cuadro_1!$J$8,IFM[[AÑO]:[AÑO]],Cuadro_1!$L$8)/1000 -> -64121.211 | E63: =+IF(D63>0,D63/$D$64,D63/$D$67)*100 -> 16.673971 | F63: =+D63/$D$68*100 -> -2.6001654
C64: SALDO DE OPERACIONES POSITIVO TOTAL (En Miles de Bs.) | D64: =SUMIF(D13:D63,">0",D13:D63) -> 2850602.2 | E64: =SUMIF(D13:D63,">0",E13:E63) -> 100 | F64: =SUMIF(F13:F63,">0",F13:F63) -> 115.59416
B65: Ranking | C65: Empresas de Seguros con Saldo de Operaciones Negativo (Pérdida) | D65: Saldo de Operaciones Negativo (Pérdida) (En Miles de Bs.) | E65: % Saldo de Operaciones por empresa con respecto al Saldo de Operaciones Negativo Total | F65: % Saldo de Operaciones por empresa con respecto al Saldo de Operaciones del Mercado
C67: SALDO DE OPERACIONES NEGATIVO TOTAL (En Miles de Bs.) | D67: =SUMIF(D13:D63,"<0",D13:D63) -> -384558.72 | E67: =SUMIF(D13:D63,"<0",E13:E63) -> 100 | F67: =SUMIF(F13:F63,"<0",F13:F63) -> -15.594158
C68: SALDO DE OPERACIONES GLOBAL (En Miles de Bs.) | D68: =+D64+D67 -> 2466043.5 | F68: =+F64+F67 -> 100
B70: Fuente: (SEFA) Estados Financieros Analíticos Mensuales. Empresas de Seguros. | F70: Actualizado: 09/07/2025
B71: 1/ A la fecha han consignado los estados financieros analiticos 43 empresas de seguros. 2/ Faltan por procesar los estados financieros analiticos las siguientes empresas: Adriática de Seguros, C.A., Ávila de Seguros C.A., Bolivariana de Seguros y Reaseguros, S.A., Seguros Guayana, Multinacional de Seguros C.A., Interbank Seguros S.A, La Regional C.A., y Seguros Carabobo C.A.
B73: INFORMACIÓN PRELIMINAR NO AUDITADA POR LA SUPERINTENDENCIA DE LA ACTIVIDAD ASEGURADORA

Sheet Cuadro_5
B1: REPÚBLICA BOLIVARIANA DE VENEZUELA
B2: MINISTERIO DEL PODER POPULAR DE ECONOMíA Y FINANZAS
B3: SUPERINTENDENCIA DE LA ACTIVIDAD ASEGURADORA
B4: DIRECCIÓN ACTUARIAL / ÁREA DE INVESTIGACIÓN, TRABAJOS ESPECIALES Y ESTADÍSTICAS
B6: INFORMACIÓN FINANCIERA ANALÍTICA MENSUAL DEL MERCADO ASEGURADOR VENEZOLANO
B7: =+Cuadro_1!B7 -> ACUMULADA A AGOSTO DE 2025
B8: PRIMAS NETAS COBRADAS POR EMPRESA
B10: Ranking | C10: Empresas de Seguros | D10: Primas Netas Cobradas (En Miles de Bs.) | E10: Porcentaje de Participación en el mercado por compañías | F10: Porcentaje de Participación Acumulado
B13: 1 | C13: =+VLOOKUP(D13,Cuadro_2!$A$10:$D$60,3,0) -> Mercantil C.A., Seguros | D13: =+LARGE(Cuadro_2!$D$10:$D$60,B13) -> 16799619 | E13: =+D13/$D$68*100 -> 25.5795 | F13: =+E13 -> 25.5795
B14: 2 | C14: =+VLOOKUP(D14,Cuadro_2!$A$10:$D$60,3,0) -> Caracas C.A., Seguros | D14: =+LARGE(Cuadro_2!$D$10:$D$60,B14) -> 13384899 | E14: =+D14/$D$68*100 -> 20.380166 | F14: =+E14+F13 -> 45.959667
B15: 3 | C15: =+VLOOKUP(D15,Cuadro_2!$A$10:$D$60,3,0) -> Internacional, S.A. de Seguros | D15: =+LARGE(Cuadro_2!$D$10:$D$60,B15) -> 3751753.2 | E15: =+D15/$D$68*100 -> 5.712509 | F15: =+E15+F14 -> 51.672175
B16: 4 | C16: =+VLOOKUP(D16,Cuadro_2!$A$10:$D$60,3,0) -> Mapfre La Seguridad, C.A. de Seguros | D16: =+LARGE(Cuadro_2!$D$10:$D$60,B16) -> 3290679.5 | E16: =+D16/$D$68*100 -> 5.0104672 | F16: =+E16+F15 -> 56.682643
B17: 5 | C17: =+VLOOKUP(D17,Cuadro_2!$A$10:$D$60,3,0) -> Oceánica de Seguros, C.A. | D17: =+LARGE(Cuadro_2!$D$10:$D$60,B17) -> 3252053.9 | E17: =+D17/$D$68*100 -> 4.9516549 | F17: =+E17+F16 -> 61.634298
B18: 6 | C18: =+VLOOKUP(D18,Cuadro_2!$A$10:$D$60,3,0) -> Pirámide C.A., Seguros | D18: =+LARGE(Cuadro_2!$D$10:$D$60,B18) -> 2527806.4 | E18: =+D18/$D$68*100 -> 3.8488984 | F18: =+E18+F17 -> 65.483196
B19: 7 | C19: =+VLOOKUP(D19,Cuadro_2!$A$10:$D$60,3,0) -> Hispana de Seguros, S.A. | D19: =+LARGE(Cuadro_2!$D$10:$D$60,B19) -> 2284580.4 | E19: =+D19/$D$68*100 -> 3.4785566 | F19: =+E19+F18 -> 68.961753
B20: 8 | C20: =+VLOOKUP(D20,Cuadro_2!$A$10:$D$60,3,0) -> Constitución C.A., Seguros | D20: =+LARGE(Cuadro_2!$D$10:$D$60,B20) -> 2249915.5 | E20: =+D20/$D$68*100 -> 3.425775 | F20: =+E20+F19 -> 72.387528
B21: 9 | C21: =+VLOOKUP(D21,Cuadro_2!$A$10:$D$60,3,0) -> Estar Seguros, S.A. | D21: =+LARGE(Cuadro_2!$D$10:$D$60,B21) -> 1947839.2 | E21: =+D21/$D$68*100 -> 2.9658265 | F21: =+E21+F20 -> 75.353354
B22: 10 | C22: =+VLOOKUP(D22,Cuadro_2!$A$10:$D$60,3,0) -> Venezuela C.A., Seguros | D22: =+LARGE(Cuadro_2!$D$10:$D$60,B22) -> 1941906.8 | E22: =+D22/$D$68*100 -> 2.9567936 | F22: =+E22+F21 -> 78.310148
C23: TOTAL PRIMERAS 10 EMPRESAS | D23: =SUM(D13:D22) -> 51431052 | E23: =SUM(E13:E22) -> 78.310148 | F23: =+F22 -> 78.310148
B24: 11 | C24: =+VLOOKUP(D24,Cuadro_2!$A$10:$D$60,3,0) -> Latitud Seguros, C.A. | D24: =+LARGE(Cuadro_2!$D$10:$D$60,B24) -> 1742506.9 | E24: =+D24/$D$68*100 -> 2.6531827 | F24: =+E24+F23 -> 80.96333
B25: 12 | C25: =+VLOOKUP(D25,Cuadro_2!$A$10:$D$60,3,0) -> Miranda, C.A Seguros | D25: =+LARGE(Cuadro_2!$D$10:$D$60,B25) -> 1711289.5 | E25: =+D25/$D$68*100 -> 2.6056502 | F25: =+E25+F24 -> 83.56898
B26: 13 | C26: =+VLOOKUP(D26,Cuadro_2!$A$10:$D$60,3,0) -> Universitas, C.A. Seguros | D26: =+LARGE(Cuadro_2!$D$10:$D$60,B26) -> 1664437 | E26: =+D26/$D$68*100 -> 2.5343115 | F26: =+E26+F25 -> 86.103292
B27: 14 | C27: =+VLOOKUP(D27,Cuadro_2!$A$10:$D$60,3,0) -> Banesco Seguros C.A. | D27: =+LARGE(Cuadro_2!$D$10:$D$60,B27) -> 1408959.8 | E27: =+D27/$D$68*100 -> 2.1453158 | F27: =+E27+F26 -> 88.248608
B28: 15 | C28: =+VLOOKUP(D28,Cuadro_2!$A$10:$D$60,3,0) -> Real Seguros, S.A. | D28: =+LARGE(Cuadro_2!$D$10:$D$60,B28) -> 1347691.1 | E28: =+D28/$D$68*100 -> 2.0520267 | F28: =+E28+F27 -> 90.300634
B29: 16 | C29: =+VLOOKUP(D29,Cuadro_2!$A$10:$D$60,3,0) -> Altamira C.A., Seguros | D29: =+LARGE(Cuadro_2!$D$10:$D$60,B29) -> 935942.49 | E29: =+D29/$D$68*100 -> 1.4250884 | F29: =+E29+F28 -> 91.725723
B30: 17 | C30: =+VLOOKUP(D30,Cuadro_2!$A$10:$D$60,3,0) -> Mundial de Seguros,C.A. | D30: =+LARGE(Cuadro_2!$D$10:$D$60,B30) -> 880383.25 | E30: =+D30/$D$68*100 -> 1.3404926 | F30: =+E30+F29 -> 93.066215
B31: 18 | C31: =+VLOOKUP(D31,Cuadro_2!$A$10:$D$60,3,0) -> Capital, C.A. Seguros | D31: =+LARGE(Cuadro_2!$D$10:$D$60,B31) -> 749200.81 | E31: =+D31/$D$68*100 -> 1.140751 | F31: =+E31+F30 -> 94.206966
B32: 19 | C32: =+VLOOKUP(D32,Cuadro_2!$A$10:$D$60,3,0) -> Qualitas C.A., Seguros | D32: =+LARGE(Cuadro_2!$D$10:$D$60,B32) -> 567614.77 | E32: =+D32/$D$68*100 -> 0.8642638 | F32: =+E32+F31 -> 95.07123
B33: 20 | C33: =+VLOOKUP(D33,Cuadro_2!$A$10:$D$60,3,0) -> Venezolana de Seguros y Vida C.A., | D33: =+LARGE(Cuadro_2!$D$10:$D$60,B33) -> 438128.2 | E33: =+D33/$D$68*100 -> 0.66710445 | F33: =+E33+F32 -> 95.738335
C34: TOTAL SEGUNDAS 10 EMPRESAS | D34: =SUM(D24:D33) -> 11446154 | E34: =SUM(E24:E33) -> 17.428187 | F34: =+F33 -> 95.738335
B35: 21 | C35: =+VLOOKUP(D35,Cuadro_2!$A$10:$D$60,3,0) -> Horizonte, S.A. Seguros | D35: =+LARGE(Cuadro_2!$D$10:$D$60,B35) -> 391643.16 | E35: =+D35/$D$68*100 -> 0.59632523 | F35: =+E35+F34 -> 96.33466
B36: 22 | C36: =+VLOOKUP(D36,Cuadro_2!$A$10:$D$60,3,0) -> Vitalicia, S.A., Seguros | D36: =+LARGE(Cuadro_2!$D$10:$D$60,B36) -> 353668.92 | E36: =+D36/$D$68*100 -> 0.53850473 | F36: =+E36+F35 -> 96.873165
B37: 23 | C37: =+VLOOKUP(D37,Cuadro_2!$A$10:$D$60,3,0) -> Catatumbo C.A., Seguros | D37: =+LARGE(Cuadro_2!$D$10:$D$60,B37) -> 349241.25 | E37: =+D37/$D$68*100 -> 0.53176306 | F37: =+E37+F36 -> 97.404928
B38: 24 | C38: =+VLOOKUP(D38,Cuadro_2!$A$10:$D$60,3,0) -> Previsora, C.N.A. de Seguros | D38: =+LARGE(Cuadro_2!$D$10:$D$60,B38) -> 280420.57 | E38: =+D38/$D$68*100 -> 0.42697505 | F38: =+E38+F37 -> 97.831903
B39: 25 | C39: =+VLOOKUP(D39,Cuadro_2!$A$10:$D$60,3,0) -> Atrio Seguros S.A. | D39: =+LARGE(Cuadro_2!$D$10:$D$60,B39) -> 217229.65 | E39: =+D39/$D$68*100 -> 0.33075906 | F39: =+E39+F38 -> 98.162662
B40: 26 | C40: =+VLOOKUP(D40,Cuadro_2!$A$10:$D$60,3,0) -> Fe C.A., Seguros | D40: =+LARGE(Cuadro_2!$D$10:$D$60,B40) -> 172441.97 | E40: =+D40/$D$68*100 -> 0.26256425 | F40: =+E40+F39 -> 98.425226
B41: 27 | C41: =+VLOOKUP(D41,Cuadro_2!$A$10:$D$60,3,0) -> Proseguros, S.A. | D41: =+LARGE(Cuadro_2!$D$10:$D$60,B41) -> 140846.82 | E41: =+D41/$D$68*100 -> 0.21445673 | F41: =+E41+F40 -> 98.639683
B42: 28 | C42: =+VLOOKUP(D42,Cuadro_2!$A$10:$D$60,3,0) -> Zuma Seguros, C.A. | D42: =+LARGE(Cuadro_2!$D$10:$D$60,B42) -> 116943.26 | E42: =+D42/$D$68*100 -> 0.1780606 | F42: =+E42+F41 -> 98.817743
B43: 29 | C43: =+VLOOKUP(D43,Cuadro_2!$A$10:$D$60,3,0) -> Iberoamericana de Seguros C.A. | D43: =+LARGE(Cuadro_2!$D$10:$D$60,B43) -> 107965.96 | E43: =+D43/$D$68*100 -> 0.16439155 | F43: =+E43+F42 -> 98.982135
B44: 30 | C44: =+VLOOKUP(D44,Cuadro_2!$A$10:$D$60,3,0) -> Andes C.A., Seguros | D44: =+LARGE(Cuadro_2!$D$10:$D$60,B44) -> 100359.11 | E44: =+D44/$D$68*100 -> 0.15280918 | F44: =+E44+F43 -> 99.134944
C45: TOTAL TERCERAS 10 EMPRESAS | D45: =SUM(D35:D44) -> 2230760.7 | E45: =SUM(E35:E44) -> 3.3966094 | F45: =+F44 -> 99.134944
B46: 31 | C46: =+VLOOKUP(D46,Cuadro_2!$A$10:$D$60,3,0) -> Caroní, S.A., Seguros | D46: =+LARGE(Cuadro_2!$D$10:$D$60,B46) -> 94188.608 | E46: =+D46/$D$68*100 -> 0.14341382 | F46: =+E46+F45 -> 99.278358
B47: 32 | C47: =+VLOOKUP(D47,Cuadro_2!$A$10:$D$60,3,0) -> BBVA Seguros,C.A. | D47: =+LARGE(Cuadro_2!$D$10:$D$60,B47) -> 88404.835 | E47: =+D47/$D$68*100 -> 0.13460731 | F47: =+E47+F46 -> 99.412965
B48: 33 | C48: =+VLOOKUP(D48,Cuadro_2!$A$10:$D$60,3,0) -> Aseguradora Nacional Unida Uniseguros, S.A. | D48: =+LARGE(Cuadro_2!$D$10:$D$60,B48) -> 74294.113 | E48: =+D48/$D$68*100 -> 0.11312199 | F48: =+E48+F47 -> 99.526087
B49: 34 | C49: =+VLOOKUP(D49,Cuadro_2!$A$10:$D$60,3,0) -> Nuevo Mundo S.A., Seguros | D49: =+LARGE(Cuadro_2!$D$10:$D$60,B49) -> 72929.437 | E49: =+D49/$D$68*100 -> 0.1110441 | F49: =+E49+F48 -> 99.637131
B50: 35 | C50: =+VLOOKUP(D50,Cuadro_2!$A$10:$D$60,3,0) -> Corporativos C.A., Seguros | D50: =+LARGE(Cuadro_2!$D$10:$D$60,B50) -> 67602.817 | E50: =+D50/$D$68*100 -> 0.10293366 | F50: =+E50+F49 -> 99.740065
B51: 36 | C51: =+VLOOKUP(D51,Cuadro_2!$A$10:$D$60,3,0) -> Vértice, C.A Seguros | D51: =+LARGE(Cuadro_2!$D$10:$D$60,B51) -> 47424.662 | E51: =+D51/$D$68*100 -> 0.072209922 | F51: =+E51+F50 -> 99.812275
B52: 37 | C52: =+VLOOKUP(D52,Cuadro_2!$A$10:$D$60,3,0) -> Occidental C.A., Seguros | D52: =+LARGE(Cuadro_2!$D$10:$D$60,B52) -> 45423.291 | E52: =+D52/$D$68*100 -> 0.069162587 | F52: =+E52+F51 -> 99.881437
B53: 38 | C53: =+VLOOKUP(D53,Cuadro_2!$A$10:$D$60,3,0) -> Vivir Seguros C.A. | D53: =+LARGE(Cuadro_2!$D$10:$D$60,B53) -> 19062.607 | E53: =+D53/$D$68*100 -> 0.02902518 | F53: =+E53+F52 -> 99.910463
B54: 39 | C54: =+VLOOKUP(D54,Cuadro_2!$A$10:$D$60,3,0) -> American International, C.A. de Seguros | D54: =+LARGE(Cuadro_2!$D$10:$D$60,B54) -> 18956.308 | E54: =+D54/$D$68*100 -> 0.028863327 | F54: =+E54+F53 -> 99.939326
B55: 40 | C55: =+VLOOKUP(D55,Cuadro_2!$A$10:$D$60,3,0) -> Universal de Seguros C.A. | D55: =+LARGE(Cuadro_2!$D$10:$D$60,B55) -> 16291.054 | E55: =+D55/$D$68*100 -> 0.024805148 | F55: =+E55+F54 -> 99.964131
B56: 41 | C56: =+VLOOKUP(D56,Cuadro_2!$A$10:$D$60,3,0) -> Virgen del Valle C.A., Seguros | D56: =+LARGE(Cuadro_2!$D$10:$D$60,B56) -> 13676.055 | E56: =+D56/$D$68*100 -> 0.020823488 | F56: =+E56+F55 -> 99.984955
B57: 42 | C57: =IF(D57=0,"",VLOOKUP(D57,Cuadro_2!$A$10:$D$60,3,0)) -> Oriental de Seguros C.A. | D57: =+LARGE(Cuadro_2!$D$10:$D$60,B57) -> 6741.6672 | E57: =+D57/$D$68*100 -> 0.010265023 | F57: =+E57+F56 -> 99.99522
B58: 43 | C58: =IF(D58=0,"",VLOOKUP(D58,Cuadro_2!$A$10:$D$60,3,0)) -> Bolivariana de Seguros y Reaseguros, S.A. | D58: =+LARGE(Cuadro_2!$D$10:$D$60,B58) -> 3139.5409 | E58: =+D58/$D$68*100 -> 0.0047803399 | F58: =+E58+F57 -> 100
B59: 44 | C59: =IF(D59=0,"",VLOOKUP(D59,Cuadro_2!$A$10:$D$60,3,0)) | D59: =+LARGE(Cuadro_2!$D$10:$D$60,B59) -> 0 | E59: =+D59/$D$68*100 -> 0 | F59: =+E59+F58 -> 100
B60: 45 | C60: =IF(D60=0,"",VLOOKUP(D60,Cuadro_2!$A$10:$D$60,3,0)) | D60: =+LARGE(Cuadro_2!$D$10:$D$60,B60) -> 0 | E60: =+D60/$D$68*100 -> 0 | F60: =+E60+F59 -> 100
B61: 46 | C61: =IF(D61=0,"",VLOOKUP(D61,Cuadro_2!$A$10:$D$60,3,0)) | D61: =+LARGE(Cuadro_2!$D$10:$D$60,B61) -> 0 | E61: =+D61/$D$68*100 -> 0 | F61: =+E61+F60 -> 100
B62: 47 | C62: =IF(D62=0,"",VLOOKUP(D62,Cuadro_2!$A$10:$D$60,3,0)) | D62: =+LARGE(Cuadro_2!$D$10:$D$60,B62) -> 0 | E62: =+D62/$D$68*100 -> 0 | F62: =+E62+F61 -> 100
B63: 48 | C63: =IF(D63=0,"",VLOOKUP(D63,Cuadro_2!$A$10:$D$60,3,0)) | D63: =+LARGE(Cuadro_2!$D$10:$D$60,B63) -> 0 | E63: =+D63/$D$68*100 -> 0 | F63: =+E63+F62 -> 100
B64: 49 | C64: =IF(D64=0,"",VLOOKUP(D64,Cuadro_2!$A$10:$D$60,3,0)) | D64: =+LARGE(Cuadro_2!$D$10:$D$60,B64) -> 0 | E64: =+D64/$D$68*100 -> 0 | F64: =+E64+F63 -> 100
B65: 50 | C65: =IF(D65=0,"",VLOOKUP(D65,Cuadro_2!$A$10:$D$60,3,0)) | D65: =+LARGE(Cuadro_2!$D$10:$D$60,B65) -> 0 | E65: =+D65/$D$68*100 -> 0 | F65: =+E65+F64 -> 100
B66: 51 | C66: =IF(D66=0,"",VLOOKUP(D66,Cuadro_2!$A$10:$D$60,3,0)) | D66: =+LARGE(Cuadro_2!$D$10:$D$60,B66) -> 0 | E66: =+D66/$D$68*100 -> 0 | F66: =+E66+F65 -> 100
C67: TOTAL EMPRESAS RESTANTES | D67: =SUM(D46:D66) -> 568135 | E67: =SUM(E46:E66) -> 0.8650559 | F67: =+F66 -> 100
C68: TOTAL (En Miles de Bs.) | D68: =+D67+D45+D34+D23 -> 65676102 | E68: =+E67+E45+E34+E23 -> 100 | F68: -
B70: Fuente: (SEFA) Estados Financieros Analíticos Mensuales. Empresas de Seguros.
B73: INFORMACIÓN PRELIMINAR NO AUDITADA POR LA SUPERINTENDENCIA DE LA ACTIVIDAD ASEGURADORA

Sheet PNC_Ramos
A1: Cod | B1: Nombre Empresa | C1: TOTAL PNC | D1: VIDA INDIVIDUAL | E1: VIDA DESGRAVAMEN | F1: VIDA RENTA | G1: VIDA COLECTIVO | H1: VIDA FUNERARIO | I1: TOTAL VIDA | J1: ACCIDENTE INDIVIDUAL | K1: ACCIDENTE COLECTIVO | L1: ACCIDENTE ESCOLAR | M1: HCM INDIVIDUAL | N1: HCM COLECTIVO | O1: TOTAL HCM | P1: FUNERARIO | Q1: COMBINADO PERSONAS | R1: ENFERMEDADES GRAVES | S1: OTROS PERSONAS | T1: TOTAL NO VIDA | U1: INCENDIO | V1: TERREMOTO | W1: ROBO | X1: TRANSPORTE | Y1: RAMOS TECNICOS | Z1: PETROLERO | AA1: COMBINADOS | AB1: LUCRO CESANTE | AC1: AUTO CASCO | AD1: AERONAVE | AE1: NAVES | AF1: AGRARIO | AG1: PECUARIO | AH1: BANCARIO | AI1: JOYERIA | AJ1: DIVERSOS | AK1: RCV | AL1: PATRONALES | AM1: RCV EMPRESARIAL | AN1: RC GENERAL | AO1: PROFESIONAL | AP1: FIDELIDAD EMPLEADOS | AQ1: PRODUCTOS | AR1: CREDITOS | AS1: TOTAL PATRIMONIALES | AT1: TOTAL OBLIGACIONALES | AU1: FIANZA | AV1: Fecha | AW1: MES | AX1: AÑO | AY1: NombreCorto
A2: 1 | B2: Ávila C.A., de Seguros | C2: 524312.71 | D2: 0 | E2: 0 | F2: 0 | G2: 2443.67 | H2: 0 | I2: 0 | J2: -21.01 | K2: 7718.75 | L2: 0 | M2: 0 | N2: 127530.34 | O2: 127530.34 | P2: -408.43 | Q2: 0 | R2: 0 | S2: 0 | T2: 137263.32 | U2: 17978.68 | V2: 0 | W2: 0 | X2: 0 | Y2: 0 | Z2: 0 | AA2: 2636.58 | AB2: 0 | AC2: 2576.63 | AD2: 201388.85 | AE2: 245 | AF2: 0 | AG2: 0 | AH2: 0 | AI2: 0 | AJ2: 0 | AK2: 4992.7 | AL2: 27893.57 | AM2: 0 | AN2: 8311.63 | AO2: 0 | AP2: 129 | AQ2: 0 | AR2: 0 | AS2: 224825.74 | AT2: 162223.65 | AU2: 120896.75 | AV2: 44592 | AW2: ENERO | AX2: 2022 | AY2: ÁVILA C.A.
A3: 2 | B3: Previsora, C.N.A. de Seguros | C3: 40656.71 | D3: 17.51 | E3: 0 | F3: 0 | G3: 3123.6 | H3: 0 | I3: 0 | J3: 8.2 | K3: 6584.22 | L3: 0 | M3: 1463.09 | N3: 17127.92 | O3: 18591.01 | P3: 547.66 | Q3: 0 | R3: 0 | S3: 0 | T3: 28872.2 | U3: 151.29 | V3: 60.61 | W3: 45.85 | X3: 0 | Y3: 0 | Z3: 0 | AA3: 0 | AB3: 0 | AC3: 0 | AD3: 0 | AE3: 312.5 | AF3: 0 | AG3: 0 | AH3: 0 | AI3: 0 | AJ3: 0 | AK3: 6843.1 | AL3: 0 | AM3: 0 | AN3: 50 | AO3: 0 | AP3: 4321.16 | AQ3: 0 | AR3: 0 | AS3: 570.25 | AT3: 11214.26 | AU3: 0 | AV3: 44592 | AW3: ENERO | AX3: 2022 | AY3: PREVISORA C.N.A.
A4: 12 | B4: Mapfre La Seguridad, C.A. de Seguros | C4: 13494757 | D4: 36221.65 | E4: 0 | F4: 0 | G4: 28558.16 | H4: 0 | I4: 0 | J4: 16057.43 | K4: 12463.19 | L4: 0 | M4: 4501824.8 | N4: 1369495.5 | O4: 5871320.3 | P4: 86063.23 | Q4: 0 | R4: 0 | S4: 0 | T4: 6050684 | U4: 69124.79 | V4: 4397.3 | W4: 1405.59 | X4: 412807.99 | Y4: 713.65 | Z4: 0 | AA4: 217488.54 | AB4: 0 | AC4: 397398.06 | AD4: 183960.67 | AE4: 1003.52 | AF4: 0 | AG4: 0 | AH4: 0 | AI4: 0 | AJ4: 5606788.7 | AK4: 209805.2 | AL4: 22844.87 | AM4: 0 | AN4: 256146.65 | AO4: 9538.58 | AP4: 16837.92 | AQ4: 33810.74 | AR4: 0 | AS4: 6895088.8 | AT4: 548983.96 | AU4: 0 | AV4: 44592 | AW4: ENERO | AX4: 2022 | AY4: MAPFRE C.A.
A5: 13 | B5: Caracas C.A., Seguros | C5: 46299485 | D5: 5372.98 | E5: 0 | F5: 0 | G5: 69840.34 | H5: 0 | I5: 0 | J5: 1459619.3 | K5: 359364.15 | L5: 0 | M5: 30309236 | N5: 7421794.9 | O5: 37731031 | P5: 0 | Q5: 0 | R5: 0 | S5: 0 | T5: 39625228 | U5: 84731.94 | V5: 0 | W5: 176.13 | X5: 38015.96 | Y5: 5856.78 | Z5: 0 | AA5: 1633994.1 | AB5: 0 | AC5: 3333486.4 | AD5: 0 | AE5: 4590.18 | AF5: 0 | AG5: 0 | AH5: 0 | AI5: 0 | AJ5: 84690.81 | AK5: 779448.54 | AL5: 510852.29 | AM5: 0 | AN5: 183270.56 | AO5: 0 | AP5: 0 | AQ5: 0 | AR5: 0 | AS5: 5185542.3 | AT5: 1488715.4 | AU5: 15144.04 | AV5: 44592 | AW5: ENERO | AX5: 2022 | AY5: CARACAS C.A.
A6: 23 | B6: Estar Seguros, S.A. | C6: 3709116.6 | D6: 0.03 | E6: 0 | F6: 0 | G6: 0 | H6: 0 | I6: 0 | J6: 60351.2 | K6: 9958.95 | L6: 0 | M6: 394.05 | N6: 9171.88 | O6: 9565.93 | P6: 0 | Q6: 0 | R6: 0 | S6: 0 | T6: 79876.11 | U6: 1671381.4 | V6: 576876.59 | W6: 61640.7 | X6: 198273.67 | Y6: 48030.26 | Z6: 0 | AA6: 28556.41 | AB6: 24824.41 | AC6: 230079.21 | AD6: 105701.43 | AE6: 197687.95 | AF6: 0 | AG6: 0 | AH6: 0 | AI6: 0 | AJ6: 25901.83 | AK6: 155656.38 | AL6: 8758.59 | AM6: 0 | AN6: 194952.61 | AO6: 0 | AP6: 32922.66 | AQ6: 0 | AR6: 0 | AS6: 3168953.9 | AT6: 460286.62 | AU6: 67996.38 | AV6: 44592 | AW6: ENERO | AX6: 2022 | AY6: ESTAR S.A.
A7: 24 | B7: Venezuela C.A., Seguros | C7: 1411751.5 | D7: 60982.58 | E7: 0 | F7: 0 | G7: 128260.21 | H7: 0 | I7: 0 | J7: 17578.02 | K7: 134567.02 | L7: 0 | M7: 935.55 | N7: 1024353.3 | O7: 1025288.9 | P7: 27088.25 | Q7: 0 | R7: 0 | S7: 0 | T7: 1393764.9 | U7: 4437.93 | V7: 0 | W7: 0 | X7: 0 | Y7: 0 | Z7: 0 | AA7: 13816.07 | AB7: 0 | AC7: 0 | AD7: 0 | AE7: 0 | AF7: 0 | AG7: 0 | AH7: 0 | AI7: 0 | AJ7: 0 | AK7: 251.15 | AL7: 0 | AM7: 0 | AN7: -518.63 | AO7: 0 | AP7: 0 | AQ7: 0 | AR7: 0 | AS7: 18254 | AT7: -267.48 | AU7: 0 | AV7: 44592 | AW7: ENERO | AX7: 2022 | AY7: VENEZUELA C.A.
A8: 25 | B8: BBVA Seguros,C.A. | C8: 570726.63 | D8: 155863.72 | E8: 0 | F8: 0 | G8: 0 | H8: 0 | I8: 0 | J8: 0 | K8: 0 | L8: 0 | M8: 0 | N8: 0 | O8: 0 | P8: 414402.79 | Q8: 0 | R8: 0 | S8: 0 | T8: 570266.51 | U8: 0 | V8: 0 | W8: 0 | X8: 0 | Y8: 0 | Z8: 0 | AA8: 0 | AB8: 0 | AC8: 460.12 | AD8: 0 | AE8: 0 | AF8: 0 | AG8: 0 | AH8: 0 | AI8: 0 | AJ8: 0 | AK8: 0 | AL8: 0 | AM8: 0 | AN8: 0 | AO8: 0 | AP8: 0 | AQ8: 0 | AR8: 0 | AS8: 460.12 | AT8: 0 | AU8: 0 | AV8: 44592 | AW8: ENERO | AX8: 2022 | AY8: BBVA C.A.
A9: 29 | B9: Real Seguros, S.A. | C9: 1554959.3 | D9: 5084.97 | E9: 0 | F9: 0 | G9: 0 | H9: 0 | I9: 0 | J9: 0 | K9: 0 | L9: 0 | M9: 0 | N9: 0 | O9: 0 | P9: 91.85 | Q9: 0 | R9: 0 | S9: 0 | T9: 5176.82 | U9: 381252 | V9: 389411.41 | W9: 109631.86 | X9: 284962.69 | Y9: 163796.31 | Z9: 0 | AA9: 0 | AB9: 18522.7 | AC9: 0 | AD9: 0 | AE9: 31964.11 | AF9: 0 | AG9: 0 | AH9: 0 | AI9: 0 | AJ9: 64175.9 | AK9: 0 | AL9: 1205.55 | AM9: 0 | AN9: 85906.63 | AO9: 0 | AP9: 14646.61 | AQ9: 4306.7 | AR9: 0 | AS9: 1443717 | AT9: 106065.49 | AU9: 0 | AV9: 44592 | AW9: ENERO | AX9: 2022 | AY9: REAL S.A.
A10: 32 | B10: Adriática de Seguros, C.A. | C10: 0 | D10: 0 | E10: 0 | F10: 0 | G10: 0 | H10: 0 | I10: 0 | J10: 0 | K10: 0 | L10: 0 | M10: 0 | N10: 0 | O10: 0 | P10: 0 | Q10: 0 | R10: 0 | S10: 0 | T10: 0 | U10: 0 | V10: 0 | W10: 0 | X10: 0 | Y10: 0 | Z10: 0 | AA10: 0 | AB10: 0 | AC10: 0 | AD10: 0 | AE10: 0 | AF10: 0 | AG10: 0 | AH10: 0 | AI10: 0 | AJ10: 0 | AK10: 0 | AL10: 0 | AM10: 0 | AN10: 0 | AO10: 0 | AP10: 0 | AQ10: 0 | AR10: 0 | AS10: 0 | AT10: 0 | AU10: 0 | AV10: 44592 | AW10: ENERO | AX10: 2022 | AY10: ADRIÁTICA C.A.
A11: 40 | B11: Venezolana de Seguros y Vida C.A., | C11: 948561.69 | D11: 0 | E11: 0 | F11: 0 | G11: 28645.5 | H11: 0 | I11: 0 | J11: 41.76 | K11: 11977.75 | L11: 0 | M11: 249718.74 | N11: 502048.28 | O11: 751767.02 | P11: 24982.47 | Q11: 0 | R11: 0 | S11: 0 | T11: 817414.5 | U11: 35458.04 | V11: 2241.55 | W11: 0.08 | X11: 0 | Y11: 2658.21 | Z11: 0 | AA11: 9143.24 | AB11: 0 | AC11: 56036.96 | AD11: 0 | AE11: 52.5 | AF11: 0 | AG11: 0 | AH11: 0 | AI11: 0 | AJ11: 0 | AK11: 17334.14 | AL11: 0 | AM11: 0 | AN11: 5236.47 | AO11: 0 | AP11: 0 | AQ11: 0 | AR11: 0 | AS11: 105590.58 | AT11: 25556.61 | AU11: 2986 | AV11: 44592 | AW11: ENERO | AX11: 2022 | AY11: VENEZOLANA C.A.
A12: 44 | B12: Andes C.A., Seguros | C12: 666453.65 | D12: 770.05 | E12: 0 | F12: 0 | G12: 3.91 | H12: 0 | I12: 0 | J12: 3930.51 | K12: 34307.59 | L12: 0 | M12: 404758.02 | N12: 84515.8 | O12: 489273.82 | P12: 3352.18 | Q12: 0 | R12: 0 | S12: 0 | T12: 531638.06 | U12: 5586.93 | V12: 3841.89 | W12: 5189.47 | X12: 0 | Y12: 4645.65 | Z12: 0 | AA12: 77.72 | AB12: 0 | AC12: 20230.28 | AD12: 0 | AE12: 0 | AF12: 0 | AG12: 0 | AH12: 0 | AI12: 0 | AJ12: 4372.31 | AK12: 69426.64 | AL12: 25.22 | AM12: 0 | AN12: 14331.14 | AO12: 0 | AP12: 762.09 | AQ12: 0 | AR12: 0 | AS12: 43944.25 | AT12: 90871.34 | AU12: 6326.25 | AV12: 44592 | AW12: ENERO | AX12: 2022 | AY12: ANDES C.A.
A13: 46 | B13: Nuevo Mundo S.A., Seguros | C13: 485068.94 | D13: 3267.05 | E13: 0 | F13: 0 | G13: 0 | H13: 0 | I13: 0 | J13: 21359.76 | K13: 4632.08 | L13: 0 | M13: 255840.14 | N13: 0 | O13: 255840.14 | P13: 4160.32 | Q13: 0 | R13: 0 | S13: 0 | T13: 289259.35 | U13: 45.52 | V13: 215.12 | W13: 1.24 | X13: 0 | Y13: 90.64 | Z13: 0 | AA13: 0 | AB13: 0 | AC13: 138388.6 | AD13: 0 | AE13: 0 | AF13: 0 | AG13: 0 | AH13: 0 | AI13: 0 | AJ13: 0.05 | AK13: 49129.24 | AL13: 1724.08 | AM13: 0 | AN13: 2371.58 | AO13: 0 | AP13: 0 | AQ13: 0 | AR13: 0 | AS13: 138741.17 | AT13: 57068.42 | AU13: 3843.52 | AV13: 44592 | AW13: ENERO | AX13: 2022 | AY13: NUEVO MUNDO S.A.
... A2423: 127 | B2423: Latitud Seguros, C.A. | C2423: 1.4009621e+09 | D2423: 2513265.9 | E2423: 0 | F2423: 4030237.6 | G2423: 4.8292603e+08 | H2423: 149142.63 | I2423: 4.8961868e+08 | J2423: 0 | K2423: 0 | L2423: 0 | M2423: 0 | N2423: 0 | O2423: 0 | P2423: 0 | Q2423: 0 | R2423: 0 | S2423: 0 | T2423: 0 | U2423: 107496.36 | V2423: 47164.3 | W2423: 5203031.6 | X2423: 3292770.9 | Y2423: 6845221.9 | Z2423: 0 | AA2423: 0 | AB2423: 0 | AC2423: 1.2107767e+08 | AD2423: 0 | AE2423: 18289573 | AF2423: 0 | AG2423: 0 | AH2423: 95049183 | AI2423: 0 | AJ2423: 4.6906134e+08 | AK2423: 41408047 | AL2423: 5534003.5 | AM2423: 0 | AN2423: 6992313.9 | AO2423: 0 | AP2423: 4546060.5 | AQ2423: 0 | AR2423: 0 | AS2423: 7.1897345e+08 | AT2423: 58480425 | AU2423: 1.3388949e+08 | AV2423: 46142 | AW2423: ABRIL | AX2423: 2026 | AY2423: LATITUD C.A.

Sheet TasasBCV
A1: AÑO | B1: MES | C1: TasaPromedio | D1: Tasa_Cierre
A2: 2021 | B2: ENERO | C2: 1.5076087 | D2: 1.8236273
A3: 2021 | B3: FEBRERO | C3: 1.7972468 | D3: 1.8713611
A4: 2021 | B4: MARZO | C4: 1.8623761 | D4: 1.9680642
A5: 2021 | B5: ABRIL | C5: 2.3858996 | D5: 2.7461518
A6: 2021 | B6: MAYO | C6: 2.9355707 | D6: 3.1008642
A7: 2021 | B7: JUNIO | C7: 3.133701 | D7: 3.2040795
A8: 2021 | B8: JULIO | C8: 3.5315921 | D8: 3.9831735
A9: 2021 | B9: AGOSTO | C9: 4.0974014 | D9: 4.1445029
A10: 2021 | B10: SEPTIEMBRE | C10: 4.0666838 | D10: 4.1386176
A11: 2021 | B11: OCTUBRE | C11: 4.2049368 | D11: 4.3881
A12: 2021 | B12: NOVIEMBRE | C12: 4.499995 | D12: 4.6078
A13: 2021 | B13: DICIEMBRE | C13: 4.61379 | D13: 4.5897
... A65: 2026 | B65: ABRIL | C65: 479.97 | D65: 487.12

Sheet NombreCorto
A1: Nombre | B1: NombreCorto
A2: Mercantil C.A., Seguros | B2: MERCANTIL C.A.
A3: Caracas C.A., Seguros | B3: CARACAS C.A.
A4: Pirámide C.A., Seguros | B4: PIRÁMIDE C.A.
A5: Internacional, S.A. de Seguros | B5: INTERNACIONAL S.A.
A6: Mapfre La Seguridad, C.A. de Seguros | B6: MAPFRE C.A.
A7: Constitución C.A., Seguros | B7: CONSTITUCIÓN C.A.
A8: Hispana de Seguros, S.A. | B8: HISPANA S.A.
A9: Oceánica de Seguros, C.A. | B9: OCEÁNICA C.A.
A10: Real Seguros, S.A. | B10: REAL S.A.
A11: Banesco Seguros C.A. | B11: BANESCO C.A.
A12: Universitas, C.A. Seguros | B12: UNIVERSITAS C.A.
... A52: Regional, C.A. de Seguros | B52: REGIONAL C.A.

Sheet LOGOS
A1: Cod_Empresa | B1: Nombre | C1: NombreCorto | D1: Logo
A2: 74 | B2: Mercantil C.A., Seguros | C2: MERCANTIL C.A.
A3: 13 | B3: Caracas C.A., Seguros | C3: CARACAS C.A.
A4: 80 | B4: Pirámide C.A., Seguros | C4: PIRAMIDE C.A.
A5: 100 | B5: Internacional, S.A. de Seguros | C5: INTERNACIONAL S.A.
A6: 12 | B6: Mapfre La Seguridad, C.A. de Seguros | C6: MAPFRE C.A.
A7: 96 | B7: Constitución C.A., Seguros | C7: CONSTITUCIÓN C.A.
A8: 114 | B8: Hispana de Seguros, S.A. | C8: HISPANA S.A.
A9: 117 | B9: Oceánica de Seguros, C.A. | C9: OCEÁNICA C.A.
A10: 29 | B10: Real Seguros, S.A. | C10: REAL S.A.
A11: 109 | B11: Banesco Seguros C.A. | C11: BANESCO C.A.
A12: 83 | B12: Universitas, C.A. Seguros | C12: UNIVERSITAS C.A.
A13: 23 | B13: Estar Seguros, S.A. | C13: ESTAR S.A.
... A52: 89 | B52: Regional, C.A. de Seguros | C52: REGIONAL C.A.
